{"affiliate_name": "CrossFit Grimaud", "affiliate_id": 33426, "total_athletes": 39, "rx_count": 39, "scaled_count": 0, "gym_rank": 2420, "total_gyms": 8587, "gym_rank_pct": 28.2, "overall_median_pct": 72.3, "workout_stats": {"wod1": {"name": "26.1", "type": "engine", "gym_median": 67.2, "global_median": 54.3, "gym_rank_pct": 69.0}, "wod2": {"name": "26.2", "type": "gymnastics", "gym_median": 71.1, "global_median": 55.5, "gym_rank_pct": 78.4}, "wod3": {"name": "26.3", "type": "barbell", "gym_median": 69.7, "global_median": 57.4, "gym_rank_pct": 70.6}}, "gym_archetype": "Gymnast", "best_workout": {"key": "wod2", "name": "26.2", "type": "gymnastics"}, "worst_workout": {"key": "wod1", "name": "26.1", "type": "engine"}, "muscle_up": {"gym_got_mu": 30, "gym_total": 39, "gym_mu_pct": 76.9, "global_mu_pct": 63.1, "global_got_mu": 124606, "global_total": 197366, "athletes": [{"name": "Tristan Kirchner", "reps": 180, "got_mu": true}, {"name": "Antoine ARY", "reps": 180, "got_mu": true}, {"name": "Christian Martinez", "reps": 180, "got_mu": true}, {"name": "Seymour Saulnier", "reps": 129, "got_mu": true}, {"name": "Maximilien Hasson", "reps": 129, "got_mu": true}, {"name": "Tiago Santos Pinheiro", "reps": 127, "got_mu": true}, {"name": "Maxime Alberge", "reps": 124, "got_mu": true}, {"name": "Pierre Etienne Mathot", "reps": 121, "got_mu": true}, {"name": "Laurent Sinopoli", "reps": 119, "got_mu": true}, {"name": "Francois roux", "reps": 118, "got_mu": true}, {"name": "Thibault Forneris", "reps": 118, "got_mu": true}, {"name": "Idriss Abdallah", "reps": 118, "got_mu": true}, {"name": "St\u00e9phanie Goujon", "reps": 118, "got_mu": true}, {"name": "Mathilda Carlon", "reps": 118, "got_mu": true}, {"name": "Guillaume Peres", "reps": 117, "got_mu": true}, {"name": "Fabien Vizzini", "reps": 117, "got_mu": true}, {"name": "St\u00e9phane Fournier-N\u00e9ri", "reps": 117, "got_mu": true}, {"name": "Alexey Derevianko", "reps": 115, "got_mu": true}, {"name": "Emma Cornillac", "reps": 114, "got_mu": true}, {"name": "Damien Desmet", "reps": 112, "got_mu": true}, {"name": "Tom jullien", "reps": 112, "got_mu": true}, {"name": "Pierre Loreti", "reps": 112, "got_mu": true}, {"name": "Rudy Robin", "reps": 112, "got_mu": true}, {"name": "Charly Pupetto", "reps": 112, "got_mu": true}, {"name": "Samantha Cuvelier", "reps": 112, "got_mu": true}, {"name": "Leonardi Coralie", "reps": 112, "got_mu": true}, {"name": "Alexia van Vyve", "reps": 112, "got_mu": true}, {"name": "Camille Lieubray", "reps": 112, "got_mu": true}, {"name": "Ilona Sepanski", "reps": 112, "got_mu": true}, {"name": "Lou Carbonnel", "reps": 112, "got_mu": true}, {"name": "Loic Teurkia", "reps": 93, "got_mu": false}, {"name": "Aleksandr JOGALEV", "reps": 91, "got_mu": false}, {"name": "Norbert LIMA BRAS", "reps": 88, "got_mu": false}, {"name": "Zsanett Novelinka", "reps": 80, "got_mu": false}, {"name": "Enzo Baile", "reps": 68, "got_mu": false}, {"name": "Virginie Carbonnel", "reps": 68, "got_mu": false}, {"name": "Muriel S\u00e9n\u00e9quier", "reps": 68, "got_mu": false}, {"name": "Ana\u00efs Rondini", "reps": 68, "got_mu": false}, {"name": "Marlene Kwiatkowski", "reps": 47, "got_mu": false}]}, "similar_gyms": {"gym_size": 39, "size_range": [28, 50], "similar_count": 1655, "gym_rank_among_similar": 292, "similar_median_pct": 57.4, "similar_p75_pct": 68.3, "similar_p25_pct": 45.4, "gym_pct": 72.3, "similar_pcts": [5.2, 9.2, 9.5, 12.3, 12.7, 13.4, 13.8, 13.8, 13.9, 13.9, 14.9, 14.9, 14.9, 15.1, 15.2, 16.0, 16.1, 16.6, 16.7, 17.6, 17.6, 17.8, 18.9, 19.0, 19.2, 19.4, 20.0, 20.2, 20.3, 20.4, 20.4, 20.8, 20.9, 21.0, 21.2, 21.5, 21.7, 21.8, 21.9, 22.2, 22.3, 22.3, 22.3, 22.5, 22.8, 22.9, 22.9, 22.9, 23.0, 23.0, 23.1, 23.3, 23.4, 23.7, 23.9, 24.1, 24.3, 24.3, 24.7, 24.8, 24.9, 24.9, 25.2, 25.3, 25.5, 25.6, 25.8, 25.9, 26.0, 26.1, 26.4, 26.6, 26.6, 26.7, 26.8, 26.9, 26.9, 26.9, 27.1, 27.1, 27.3, 27.3, 27.5, 27.6, 27.9, 28.0, 28.1, 28.1, 28.2, 28.3, 28.3, 28.3, 28.5, 28.6, 28.7, 28.8, 28.9, 28.9, 29.0, 29.1, 29.2, 29.3, 29.3, 29.4, 29.5, 29.6, 29.7, 30.0, 30.1, 30.2, 30.2, 30.4, 30.5, 30.6, 30.6, 30.8, 30.9, 30.9, 31.0, 31.1, 31.2, 31.2, 31.2, 31.3, 31.3, 31.5, 31.6, 31.6, 31.7, 31.9, 31.9, 32.0, 32.0, 32.0, 32.1, 32.2, 32.3, 32.3, 32.3, 32.4, 32.6, 32.6, 32.7, 32.7, 32.7, 32.8, 32.9, 32.9, 33.0, 33.1, 33.3, 33.4, 33.6, 34.0, 34.0, 34.1, 34.1, 34.3, 34.4, 34.4, 34.5, 34.5, 34.6, 34.7, 34.7, 34.9, 34.9, 34.9, 35.1, 35.1, 35.2, 35.2, 35.2, 35.3, 35.3, 35.3, 35.4, 35.4, 35.6, 35.7, 35.8, 35.8, 35.9, 35.9, 35.9, 36.0, 36.0, 36.1, 36.1, 36.2, 36.2, 36.2, 36.3, 36.4, 36.5, 36.5, 36.6, 36.6, 36.7, 36.7, 36.8, 36.8, 36.8, 36.9, 37.0, 37.1, 37.2, 37.3, 37.4, 37.5, 37.5, 37.5, 37.5, 37.7, 37.7, 37.7, 37.8, 37.8, 37.9, 37.9, 38.0, 38.0, 38.0, 38.1, 38.1, 38.1, 38.2, 38.2, 38.2, 38.2, 38.3, 38.3, 38.3, 38.4, 38.5, 38.5, 38.6, 38.6, 38.7, 38.7, 38.7, 38.7, 38.8, 38.8, 38.8, 38.8, 38.9, 39.0, 39.1, 39.1, 39.1, 39.2, 39.2, 39.2, 39.3, 39.3, 39.5, 39.5, 39.5, 39.5, 39.6, 39.6, 39.6, 39.8, 39.9, 40.0, 40.0, 40.1, 40.1, 40.1, 40.2, 40.2, 40.2, 40.3, 40.4, 40.4, 40.5, 40.5, 40.5, 40.6, 40.6, 40.6, 40.7, 40.7, 40.7, 40.9, 40.9, 41.0, 41.1, 41.2, 41.2, 41.2, 41.3, 41.3, 41.3, 41.4, 41.4, 41.4, 41.4, 41.4, 41.4, 41.5, 41.5, 41.5, 41.6, 41.6, 41.6, 41.6, 41.6, 41.6, 41.7, 41.7, 41.8, 41.8, 41.9, 41.9, 42.0, 42.0, 42.0, 42.0, 42.2, 42.3, 42.3, 42.3, 42.4, 42.4, 42.5, 42.5, 42.5, 42.6, 42.7, 42.7, 42.8, 42.8, 42.8, 42.9, 42.9, 42.9, 42.9, 43.0, 43.0, 43.1, 43.1, 43.1, 43.1, 43.1, 43.1, 43.2, 43.2, 43.3, 43.4, 43.5, 43.5, 43.5, 43.6, 43.6, 43.7, 43.7, 43.7, 43.7, 43.8, 43.8, 43.8, 43.8, 43.9, 43.9, 44.0, 44.1, 44.1, 44.1, 44.2, 44.2, 44.2, 44.2, 44.2, 44.3, 44.3, 44.3, 44.3, 44.3, 44.3, 44.4, 44.4, 44.4, 44.4, 44.5, 44.5, 44.5, 44.6, 44.7, 44.7, 44.7, 44.7, 44.7, 44.7, 44.7, 44.8, 44.8, 44.9, 45.0, 45.1, 45.1, 45.1, 45.1, 45.1, 45.2, 45.2, 45.2, 45.3, 45.3, 45.3, 45.4, 45.4, 45.4, 45.4, 45.5, 45.5, 45.6, 45.6, 45.7, 45.7, 45.7, 45.7, 45.7, 45.8, 45.9, 45.9, 45.9, 46.0, 46.0, 46.1, 46.1, 46.1, 46.1, 46.2, 46.2, 46.2, 46.2, 46.3, 46.3, 46.3, 46.5, 46.5, 46.5, 46.5, 46.5, 46.6, 46.6, 46.8, 46.8, 46.8, 46.9, 46.9, 46.9, 47.0, 47.0, 47.0, 47.0, 47.0, 47.0, 47.1, 47.1, 47.1, 47.1, 47.1, 47.2, 47.2, 47.4, 47.4, 47.4, 47.4, 47.5, 47.6, 47.6, 47.6, 47.6, 47.8, 47.8, 47.8, 47.9, 47.9, 47.9, 47.9, 47.9, 48.0, 48.0, 48.0, 48.1, 48.1, 48.1, 48.1, 48.1, 48.2, 48.2, 48.2, 48.2, 48.2, 48.3, 48.3, 48.4, 48.4, 48.4, 48.4, 48.4, 48.4, 48.5, 48.6, 48.6, 48.7, 48.7, 48.7, 48.8, 48.8, 48.9, 48.9, 49.0, 49.0, 49.0, 49.1, 49.1, 49.1, 49.1, 49.2, 49.3, 49.3, 49.3, 49.3, 49.3, 49.4, 49.4, 49.5, 49.5, 49.5, 49.6, 49.7, 49.8, 49.8, 49.8, 49.8, 49.9, 50.0, 50.0, 50.0, 50.0, 50.0, 50.1, 50.2, 50.2, 50.4, 50.4, 50.4, 50.5, 50.5, 50.5, 50.5, 50.5, 50.5, 50.6, 50.6, 50.6, 50.6, 50.7, 50.7, 50.8, 50.8, 50.8, 50.8, 50.8, 50.8, 50.8, 50.8, 50.8, 50.9, 50.9, 50.9, 50.9, 51.0, 51.0, 51.1, 51.1, 51.1, 51.1, 51.2, 51.2, 51.2, 51.2, 51.2, 51.2, 51.3, 51.3, 51.3, 51.3, 51.3, 51.3, 51.3, 51.3, 51.4, 51.4, 51.4, 51.4, 51.5, 51.5, 51.5, 51.5, 51.5, 51.6, 51.6, 51.6, 51.6, 51.7, 51.7, 51.8, 51.8, 51.8, 51.8, 51.9, 51.9, 52.0, 52.0, 52.0, 52.0, 52.0, 52.0, 52.1, 52.1, 52.1, 52.2, 52.2, 52.3, 52.3, 52.3, 52.3, 52.4, 52.4, 52.5, 52.5, 52.5, 52.6, 52.6, 52.6, 52.6, 52.6, 52.6, 52.7, 52.7, 52.7, 52.8, 52.8, 52.8, 52.8, 52.8, 52.8, 52.9, 52.9, 52.9, 52.9, 53.0, 53.0, 53.0, 53.0, 53.0, 53.0, 53.1, 53.1, 53.1, 53.1, 53.2, 53.2, 53.2, 53.2, 53.2, 53.2, 53.3, 53.3, 53.4, 53.4, 53.4, 53.4, 53.4, 53.4, 53.5, 53.5, 53.5, 53.5, 53.6, 53.6, 53.6, 53.7, 53.7, 53.7, 53.7, 53.7, 53.8, 53.8, 53.9, 53.9, 53.9, 53.9, 53.9, 54.0, 54.0, 54.0, 54.0, 54.0, 54.0, 54.1, 54.1, 54.1, 54.1, 54.2, 54.3, 54.3, 54.3, 54.4, 54.4, 54.4, 54.4, 54.4, 54.5, 54.5, 54.5, 54.6, 54.6, 54.6, 54.6, 54.6, 54.7, 54.7, 54.7, 54.8, 54.8, 54.8, 54.9, 54.9, 55.0, 55.0, 55.0, 55.1, 55.1, 55.1, 55.1, 55.1, 55.2, 55.2, 55.2, 55.3, 55.3, 55.3, 55.3, 55.3, 55.3, 55.4, 55.4, 55.5, 55.5, 55.5, 55.5, 55.5, 55.6, 55.6, 55.6, 55.7, 55.7, 55.7, 55.7, 55.7, 55.7, 55.8, 55.8, 55.9, 55.9, 55.9, 56.0, 56.0, 56.0, 56.0, 56.0, 56.1, 56.1, 56.1, 56.2, 56.2, 56.2, 56.2, 56.2, 56.2, 56.4, 56.4, 56.4, 56.4, 56.4, 56.4, 56.5, 56.5, 56.5, 56.6, 56.6, 56.6, 56.7, 56.7, 56.8, 56.8, 56.8, 56.8, 56.8, 56.8, 56.8, 56.8, 56.9, 56.9, 57.0, 57.0, 57.0, 57.0, 57.0, 57.0, 57.1, 57.1, 57.1, 57.2, 57.2, 57.2, 57.2, 57.2, 57.3, 57.3, 57.3, 57.4, 57.4, 57.4, 57.5, 57.5, 57.6, 57.6, 57.6, 57.6, 57.6, 57.7, 57.7, 57.7, 57.7, 57.8, 57.8, 57.8, 57.8, 57.8, 57.9, 57.9, 57.9, 57.9, 57.9, 58.0, 58.0, 58.0, 58.0, 58.0, 58.1, 58.1, 58.1, 58.1, 58.1, 58.1, 58.1, 58.1, 58.2, 58.2, 58.2, 58.2, 58.2, 58.3, 58.3, 58.3, 58.3, 58.3, 58.3, 58.4, 58.4, 58.4, 58.5, 58.6, 58.6, 58.6, 58.6, 58.6, 58.6, 58.7, 58.7, 58.7, 58.8, 58.8, 58.8, 58.8, 58.8, 58.8, 58.9, 58.9, 58.9, 58.9, 59.0, 59.0, 59.0, 59.1, 59.1, 59.3, 59.3, 59.4, 59.4, 59.4, 59.4, 59.5, 59.5, 59.5, 59.5, 59.5, 59.5, 59.5, 59.5, 59.6, 59.6, 59.6, 59.6, 59.7, 59.7, 59.7, 59.8, 59.8, 59.8, 59.8, 59.8, 59.9, 59.9, 60.0, 60.0, 60.0, 60.1, 60.1, 60.1, 60.1, 60.1, 60.1, 60.1, 60.1, 60.2, 60.2, 60.2, 60.2, 60.3, 60.3, 60.3, 60.3, 60.4, 60.4, 60.4, 60.5, 60.5, 60.5, 60.5, 60.6, 60.6, 60.6, 60.7, 60.7, 60.8, 60.8, 60.8, 60.8, 60.8, 60.9, 60.9, 60.9, 60.9, 60.9, 61.0, 61.0, 61.0, 61.1, 61.1, 61.1, 61.1, 61.1, 61.1, 61.1, 61.1, 61.2, 61.2, 61.2, 61.3, 61.3, 61.3, 61.3, 61.3, 61.3, 61.4, 61.4, 61.4, 61.4, 61.4, 61.4, 61.4, 61.5, 61.5, 61.6, 61.6, 61.6, 61.6, 61.6, 61.7, 61.7, 61.8, 61.8, 61.8, 61.9, 61.9, 61.9, 61.9, 62.0, 62.0, 62.0, 62.0, 62.1, 62.1, 62.1, 62.1, 62.2, 62.2, 62.2, 62.3, 62.3, 62.3, 62.3, 62.4, 62.4, 62.4, 62.4, 62.4, 62.4, 62.4, 62.5, 62.5, 62.6, 62.6, 62.7, 62.8, 62.8, 62.8, 62.8, 62.8, 62.8, 62.8, 62.9, 62.9, 62.9, 63.0, 63.0, 63.0, 63.0, 63.1, 63.1, 63.1, 63.1, 63.1, 63.1, 63.1, 63.3, 63.3, 63.3, 63.3, 63.3, 63.4, 63.4, 63.4, 63.5, 63.6, 63.6, 63.6, 63.7, 63.7, 63.7, 63.7, 63.7, 63.8, 63.8, 63.8, 63.8, 63.8, 63.9, 63.9, 63.9, 63.9, 64.0, 64.0, 64.0, 64.0, 64.0, 64.0, 64.1, 64.1, 64.1, 64.2, 64.2, 64.2, 64.2, 64.2, 64.3, 64.3, 64.3, 64.3, 64.3, 64.3, 64.4, 64.4, 64.4, 64.4, 64.5, 64.5, 64.5, 64.5, 64.6, 64.6, 64.6, 64.7, 64.7, 64.7, 64.7, 64.7, 64.7, 64.8, 64.9, 65.0, 65.0, 65.0, 65.0, 65.1, 65.1, 65.1, 65.1, 65.2, 65.2, 65.2, 65.2, 65.3, 65.3, 65.3, 65.4, 65.4, 65.4, 65.4, 65.6, 65.6, 65.6, 65.7, 65.7, 65.7, 65.8, 65.8, 65.9, 65.9, 65.9, 65.9, 66.0, 66.0, 66.0, 66.1, 66.1, 66.1, 66.1, 66.1, 66.1, 66.2, 66.2, 66.3, 66.3, 66.3, 66.4, 66.4, 66.5, 66.6, 66.6, 66.6, 66.6, 66.6, 66.6, 66.6, 66.6, 66.7, 66.7, 66.7, 66.7, 66.8, 66.8, 66.9, 66.9, 66.9, 66.9, 66.9, 67.0, 67.0, 67.0, 67.0, 67.0, 67.1, 67.1, 67.1, 67.1, 67.2, 67.2, 67.2, 67.2, 67.2, 67.3, 67.4, 67.4, 67.5, 67.5, 67.5, 67.5, 67.5, 67.5, 67.6, 67.6, 67.7, 67.7, 67.8, 67.8, 67.8, 67.8, 67.8, 67.9, 67.9, 67.9, 67.9, 68.1, 68.1, 68.2, 68.2, 68.2, 68.2, 68.2, 68.3, 68.3, 68.3, 68.4, 68.4, 68.5, 68.5, 68.5, 68.5, 68.5, 68.6, 68.6, 68.6, 68.7, 68.7, 68.7, 68.8, 68.8, 68.8, 68.9, 68.9, 69.0, 69.0, 69.0, 69.1, 69.1, 69.1, 69.2, 69.2, 69.3, 69.3, 69.4, 69.4, 69.4, 69.4, 69.4, 69.4, 69.4, 69.5, 69.5, 69.6, 69.6, 69.6, 69.6, 69.7, 69.7, 69.7, 69.7, 69.7, 69.9, 70.0, 70.0, 70.0, 70.0, 70.1, 70.2, 70.2, 70.2, 70.2, 70.2, 70.3, 70.3, 70.3, 70.3, 70.3, 70.4, 70.4, 70.4, 70.5, 70.5, 70.5, 70.6, 70.7, 70.7, 70.8, 70.8, 70.8, 70.9, 71.0, 71.0, 71.0, 71.1, 71.1, 71.1, 71.1, 71.1, 71.2, 71.2, 71.3, 71.3, 71.4, 71.5, 71.5, 71.6, 71.6, 71.6, 71.6, 71.6, 71.7, 71.7, 71.7, 71.7, 71.7, 71.7, 71.8, 71.8, 71.8, 71.9, 71.9, 71.9, 71.9, 72.0, 72.0, 72.1, 72.1, 72.1, 72.1, 72.1, 72.2, 72.3, 72.3, 72.3, 72.3, 72.3, 72.3, 72.3, 72.4, 72.4, 72.4, 72.4, 72.5, 72.5, 72.5, 72.6, 72.6, 72.6, 72.7, 72.8, 72.9, 72.9, 72.9, 72.9, 73.1, 73.1, 73.1, 73.2, 73.2, 73.2, 73.2, 73.2, 73.2, 73.3, 73.3, 73.3, 73.3, 73.4, 73.4, 73.4, 73.5, 73.5, 73.5, 73.5, 73.5, 73.5, 73.6, 73.6, 73.7, 73.7, 73.8, 73.8, 73.9, 73.9, 73.9, 74.0, 74.0, 74.0, 74.0, 74.1, 74.1, 74.1, 74.2, 74.2, 74.2, 74.3, 74.4, 74.4, 74.4, 74.5, 74.5, 74.6, 74.6, 74.7, 74.8, 74.8, 74.8, 74.9, 74.9, 75.0, 75.1, 75.1, 75.2, 75.2, 75.2, 75.3, 75.3, 75.4, 75.4, 75.4, 75.4, 75.4, 75.5, 75.5, 75.5, 75.5, 75.6, 75.6, 75.6, 75.6, 75.6, 75.7, 75.7, 75.8, 75.8, 75.8, 75.9, 76.0, 76.1, 76.1, 76.1, 76.1, 76.3, 76.4, 76.4, 76.5, 76.6, 76.8, 76.8, 76.8, 76.8, 76.9, 76.9, 77.0, 77.2, 77.2, 77.3, 77.4, 77.5, 77.5, 77.5, 77.6, 77.6, 77.6, 77.7, 77.8, 77.8, 77.8, 77.9, 77.9, 77.9, 77.9, 78.0, 78.1, 78.1, 78.1, 78.1, 78.2, 78.3, 78.4, 78.4, 78.4, 78.5, 78.5, 78.5, 78.5, 78.5, 78.6, 78.6, 78.6, 78.7, 78.7, 78.7, 78.8, 78.8, 78.8, 78.8, 78.8, 78.8, 78.8, 78.9, 78.9, 79.0, 79.0, 79.0, 79.1, 79.2, 79.2, 79.4, 79.4, 79.4, 79.4, 79.4, 79.5, 79.5, 79.6, 79.7, 79.7, 79.7, 79.8, 79.8, 79.9, 79.9, 80.0, 80.1, 80.1, 80.2, 80.5, 80.5, 80.5, 80.5, 80.7, 80.8, 80.8, 80.9, 81.1, 81.2, 81.3, 81.3, 81.4, 81.4, 81.5, 81.5, 81.5, 81.5, 81.7, 81.7, 81.7, 81.9, 81.9, 82.0, 82.0, 82.2, 82.2, 82.4, 82.4, 82.5, 82.6, 82.8, 82.8, 82.8, 82.8, 83.2, 83.3, 83.4, 83.4, 83.5, 83.5, 83.5, 83.6, 83.6, 83.7, 83.7, 83.8, 83.9, 84.0, 84.1, 84.2, 84.3, 84.4, 84.5, 84.6, 84.6, 84.6, 84.8, 84.9, 85.0, 85.0, 85.2, 85.3, 85.4, 85.6, 85.6, 85.7, 85.8, 85.8, 86.1, 86.1, 86.2, 86.3, 86.4, 86.4, 86.5, 86.6, 86.6, 86.8, 86.9, 87.2, 87.5, 87.5, 87.8, 87.9, 88.7, 88.7, 89.3, 89.4, 89.5, 89.5, 89.5, 89.9, 89.9, 90.3, 90.3, 90.7, 91.2, 91.9, 94.3, 94.8, 97.6], "comparable_gyms": [{"name": "CrossFit Aledo", "pct": 72.3, "rank": 2412}, {"name": "CrossFit Arnhem", "pct": 72.3, "rank": 2415}, {"name": "BTS CrossFit", "pct": 72.3, "rank": 2422}, {"name": "CrossFit des Graves", "pct": 72.3, "rank": 2423}, {"name": "Workshop CrossFit", "pct": 72.3, "rank": 2426}, {"name": "NKY CrossFit", "pct": 72.3, "rank": 2429}, {"name": "Camp Rhino CrossFit", "pct": 72.3, "rank": 2430}, {"name": "CrossFit Gjovik", "pct": 72.2, "rank": 2439}, {"name": "CrossFit Canberra", "pct": 72.4, "rank": 2396}, {"name": "CrossFit East Turku", "pct": 72.4, "rank": 2398}]}, "rx_decision": {"gym_rx_count": 39, "gym_scaled_count": 0, "gym_rx_pct": 100.0, "global_rx_pct": 95.6, "by_age": [{"age_range": "18-24", "gym_rx_pct": 100.0, "global_rx_pct": 96.1, "gym_count": 3}, {"age_range": "25-29", "gym_rx_pct": 100.0, "global_rx_pct": 96.4, "gym_count": 11}, {"age_range": "30-34", "gym_rx_pct": 100.0, "global_rx_pct": 96.3, "gym_count": 6}, {"age_range": "35-39", "gym_rx_pct": 100.0, "global_rx_pct": 96.0, "gym_count": 4}, {"age_range": "40-44", "gym_rx_pct": 100.0, "global_rx_pct": 95.2, "gym_count": 5}, {"age_range": "45-49", "gym_rx_pct": 100.0, "global_rx_pct": 94.3, "gym_count": 4}, {"age_range": "50-65", "gym_rx_pct": 100.0, "global_rx_pct": 93.0, "gym_count": 4}]}, "hidden_gems": [{"name": "St\u00e9phane Fournier-N\u00e9ri", "overall_pct": 35.6, "best_workout": "26.3", "best_pct": 87.2, "gap": 51.6, "wod1": 65.1, "wod2": 70.6, "wod3": 87.2}, {"name": "Lou Carbonnel", "overall_pct": 30.9, "best_workout": "26.2", "best_pct": 58.7, "gap": 27.8, "wod1": 19.6, "wod2": 58.7, "wod3": 44.6}, {"name": "Muriel S\u00e9n\u00e9quier", "overall_pct": 23.2, "best_workout": "26.3", "best_pct": 48.0, "gap": 24.9, "wod1": 5.9, "wod2": 25.0, "wod3": 48.0}, {"name": "Idriss Abdallah", "overall_pct": 48.6, "best_workout": "26.2", "best_pct": 71.6, "gap": 23.0, "wod1": 39.9, "wod2": 71.6, "wod3": 13.6}, {"name": "Ilona Sepanski", "overall_pct": 39.5, "best_workout": "26.2", "best_pct": 58.0, "gap": 18.5, "wod1": 32.0, "wod2": 58.0, "wod3": 21.3}, {"name": "Zsanett Novelinka", "overall_pct": 72.0, "best_workout": "26.1", "best_pct": 83.1, "gap": 11.1, "wod1": 83.1, "wod2": 36.0, "wod3": 64.0}], "awards": [{"title": "Women's MVP", "subtitle": "Highest overall percentile", "name": "Samantha Cuvelier", "detail": "Overall 95th percentile \u2014 your gym's top performer", "stats": {"wod1": 93.8, "wod2": 75.7, "wod3": 98.5}}, {"title": "Women's Wildcard", "subtitle": "Biggest swing between workouts", "name": "Zsanett Novelinka", "detail": "Range: 47 percentile points between best and worst", "stats": {"wod1": 83.1, "wod2": 36.0, "wod3": 64.0}}, {"title": "Women's Best on 26.1", "subtitle": "Top performer on 26.1", "name": "St\u00e9phanie Goujon", "detail": "85th percentile on 26.1", "stats": {"wod1": 85.0, "wod2": 84.8, "wod3": 97.8}}, {"title": "Women's Best on 26.2", "subtitle": "Top performer on 26.2", "name": "Emma Cornillac", "detail": "81th percentile on 26.2", "stats": {"wod1": 52.9, "wod2": 80.7, "wod3": 69.7}}, {"title": "Women's Best on 26.3", "subtitle": "Top performer on 26.3", "name": "Leonardi Coralie", "detail": "86th percentile on 26.3", "stats": {"wod1": 68.8, "wod2": 72.5, "wod3": 85.9}}, {"title": "Women's Metronome", "subtitle": "Most consistent across all 3 workouts", "name": "Virginie Carbonnel", "detail": "Volatility: 2.3 \u2014 nearly the same percentile every week", "stats": {"wod1": 19.5, "wod2": 21.4, "wod3": 24.1}}, {"title": "Women's Closer", "subtitle": "Biggest improvement Week 1 \u2192 Week 3", "name": "Muriel S\u00e9n\u00e9quier", "detail": "Jumped 42 percentile points from 26.1 to 26.3", "stats": {"wod1": 5.9, "wod2": 25.0, "wod3": 48.0}}, {"title": "Women's Best 40\u201344", "subtitle": "Top performer ages 40\u201344", "name": "Marlene Kwiatkowski", "detail": "Age 44, overall 39th percentile", "stats": {"wod1": 16.2, "wod2": 13.4, "wod3": 18.5}}, {"title": "Men's MVP", "subtitle": "Highest overall percentile", "name": "Maxime Alberge", "detail": "Overall 96th percentile \u2014 your gym's top performer", "stats": {"wod1": 98.4, "wod2": 80.6, "wod3": 99.7}}, {"title": "Men's Wildcard", "subtitle": "Biggest swing between workouts", "name": "Idriss Abdallah", "detail": "Range: 58 percentile points between best and worst", "stats": {"wod1": 39.9, "wod2": 71.6, "wod3": 13.6}}, {"title": "Men's Best on 26.1", "subtitle": "Top performer on 26.1", "name": "Antoine ARY", "detail": "92th percentile on 26.1", "stats": {"wod1": 92.2, "wod2": 94.0, "wod3": 82.4}}, {"title": "Men's Best on 26.2", "subtitle": "Top performer on 26.2", "name": "Tristan Kirchner", "detail": "96th percentile on 26.2", "stats": {"wod1": 87.3, "wod2": 95.6, "wod3": 93.8}}, {"title": "Men's Best on 26.3", "subtitle": "Top performer on 26.3", "name": "Christian Martinez", "detail": "90th percentile on 26.3", "stats": {"wod1": 83.6, "wod2": 89.2, "wod3": 90.3}}, {"title": "Men's Metronome", "subtitle": "Most consistent across all 3 workouts", "name": "Thibault Forneris", "detail": "Volatility: 2.0 \u2014 nearly the same percentile every week", "stats": {"wod1": 73.5, "wod2": 71.7, "wod3": 69.5}}, {"title": "Men's Closer", "subtitle": "Biggest improvement Week 1 \u2192 Week 3", "name": "St\u00e9phane Fournier-N\u00e9ri", "detail": "Jumped 22 percentile points from 26.1 to 26.3", "stats": {"wod1": 65.1, "wod2": 70.6, "wod3": 87.2}}, {"title": "Men's Best 35\u201339", "subtitle": "Top performer ages 35\u201339", "name": "Rudy Robin", "detail": "Age 37, overall 50th percentile", "stats": {"wod1": 46.7, "wod2": 40.3, "wod3": 45.4}}, {"title": "Men's Best 40\u201344", "subtitle": "Top performer ages 40\u201344", "name": "Pierre Etienne Mathot", "detail": "Age 43, overall 77th percentile", "stats": {"wod1": 71.6, "wod2": 76.2, "wod3": 69.7}}, {"title": "Men's Best 45\u201349", "subtitle": "Top performer ages 45\u201349", "name": "Alexey Derevianko", "detail": "Age 48, overall 73th percentile", "stats": {"wod1": 65.7, "wod2": 65.4, "wod3": 71.8}}, {"title": "Men's Best 50\u201354", "subtitle": "Top performer ages 50\u201354", "name": "Damien Desmet", "detail": "Age 52, overall 71th percentile", "stats": {"wod1": 74.1, "wod2": 49.2, "wod3": 74.6}}], "what_if": [{"name": "Idriss Abdallah", "actual_pct": 41.7, "best_pct": 71.6, "potential_gain": 29.9, "best_workout": "26.2", "wod1": 39.9, "wod2": 71.6, "wod3": 13.6}, {"name": "Zsanett Novelinka", "actual_pct": 61.0, "best_pct": 83.1, "potential_gain": 22.0, "best_workout": "26.1", "wod1": 83.1, "wod2": 36.0, "wod3": 64.0}, {"name": "Muriel S\u00e9n\u00e9quier", "actual_pct": 26.3, "best_pct": 48.0, "potential_gain": 21.8, "best_workout": "26.3", "wod1": 5.9, "wod2": 25.0, "wod3": 48.0}, {"name": "Ilona Sepanski", "actual_pct": 37.1, "best_pct": 58.0, "potential_gain": 20.9, "best_workout": "26.2", "wod1": 32.0, "wod2": 58.0, "wod3": 21.3}, {"name": "Lou Carbonnel", "actual_pct": 41.0, "best_pct": 58.7, "potential_gain": 17.7, "best_workout": "26.2", "wod1": 19.6, "wod2": 58.7, "wod3": 44.6}, {"name": "St\u00e9phane Fournier-N\u00e9ri", "actual_pct": 74.3, "best_pct": 87.2, "potential_gain": 12.9, "best_workout": "26.3", "wod1": 65.1, "wod2": 70.6, "wod3": 87.2}, {"name": "Emma Cornillac", "actual_pct": 67.8, "best_pct": 80.7, "potential_gain": 12.9, "best_workout": "26.2", "wod1": 52.9, "wod2": 80.7, "wod3": 69.7}, {"name": "Tom jullien", "actual_pct": 64.7, "best_pct": 75.5, "potential_gain": 10.9, "best_workout": "26.3", "wod1": 74.0, "wod2": 44.5, "wod3": 75.5}, {"name": "Leonardi Coralie", "actual_pct": 75.7, "best_pct": 85.9, "potential_gain": 10.2, "best_workout": "26.3", "wod1": 68.8, "wod2": 72.5, "wod3": 85.9}, {"name": "Laurent Sinopoli", "actual_pct": 63.6, "best_pct": 73.4, "potential_gain": 9.7, "best_workout": "26.2", "wod1": 52.0, "wod2": 73.4, "wod3": 65.5}], "consistency": {"gym_median_vol": 7.36, "gym_mean_vol": 9.5, "global_median_vol": 9.4, "global_mean_vol": 11.47, "athletes": [{"name": "Thibault Forneris", "vol": 2.01, "range": 4.0, "wod1": 73.5, "wod2": 71.7, "wod3": 69.5}, {"name": "Loic Teurkia", "vol": 2.03, "range": 3.9, "wod1": 25.5, "wod2": 29.4, "wod3": 28.4}, {"name": "Virginie Carbonnel", "vol": 2.32, "range": 4.6, "wod1": 19.5, "wod2": 21.4, "wod3": 24.1}, {"name": "Marlene Kwiatkowski", "vol": 2.54, "range": 5.1, "wod1": 16.2, "wod2": 13.4, "wod3": 18.5}, {"name": "Pierre Etienne Mathot", "vol": 3.33, "range": 6.5, "wod1": 71.6, "wod2": 76.2, "wod3": 69.7}, {"name": "Rudy Robin", "vol": 3.38, "range": 6.4, "wod1": 46.7, "wod2": 40.3, "wod3": 45.4}, {"name": "Christian Martinez", "vol": 3.59, "range": 6.7, "wod1": 83.6, "wod2": 89.2, "wod3": 90.3}, {"name": "Alexey Derevianko", "vol": 3.6, "range": 6.4, "wod1": 65.7, "wod2": 65.4, "wod3": 71.8}, {"name": "Tristan Kirchner", "vol": 4.41, "range": 8.4, "wod1": 87.3, "wod2": 95.6, "wod3": 93.8}, {"name": "Seymour Saulnier", "vol": 4.46, "range": 8.9, "wod1": 90.7, "wod2": 85.4, "wod3": 81.8}, {"name": "Enzo Baile", "vol": 5.41, "range": 10.0, "wod1": 4.5, "wod2": 13.1, "wod3": 14.5}, {"name": "Alexia van Vyve", "vol": 6.01, "range": 11.8, "wod1": 75.5, "wod2": 71.8, "wod3": 63.7}, {"name": "Antoine ARY", "vol": 6.26, "range": 11.6, "wod1": 92.2, "wod2": 94.0, "wod3": 82.4}, {"name": "Camille Lieubray", "vol": 6.77, "range": 12.2, "wod1": 62.1, "wod2": 73.3, "wod3": 74.3}, {"name": "Guillaume Peres", "vol": 6.95, "range": 12.3, "wod1": 82.3, "wod2": 70.0, "wod3": 70.6}, {"name": "Tiago Santos Pinheiro", "vol": 7.1, "range": 13.6, "wod1": 72.6, "wod2": 83.0, "wod3": 69.4}, {"name": "Maximilien Hasson", "vol": 7.21, "range": 13.8, "wod1": 71.1, "wod2": 84.9, "wod3": 74.4}, {"name": "Aleksandr JOGALEV", "vol": 7.29, "range": 13.5, "wod1": 28.3, "wod2": 26.5, "wod3": 39.9}, {"name": "St\u00e9phanie Goujon", "vol": 7.43, "range": 13.0, "wod1": 85.0, "wod2": 84.8, "wod3": 97.8}, {"name": "Francois roux", "vol": 8.45, "range": 16.9, "wod1": 89.3, "wod2": 72.4, "wod3": 81.4}, {"name": "Ana\u00efs Rondini", "vol": 8.85, "range": 17.7, "wod1": 5.6, "wod2": 23.3, "wod3": 14.4}, {"name": "Leonardi Coralie", "vol": 8.99, "range": 17.1, "wod1": 68.8, "wod2": 72.5, "wod3": 85.9}, {"name": "Pierre Loreti", "vol": 9.29, "range": 16.7, "wod1": 58.0, "wod2": 41.3, "wod3": 56.6}, {"name": "Maxime Alberge", "vol": 10.65, "range": 19.1, "wod1": 98.4, "wod2": 80.6, "wod3": 99.7}, {"name": "Laurent Sinopoli", "vol": 10.82, "range": 21.4, "wod1": 52.0, "wod2": 73.4, "wod3": 65.5}, {"name": "Fabien Vizzini", "vol": 11.02, "range": 20.9, "wod1": 53.9, "wod2": 70.4, "wod3": 74.8}, {"name": "St\u00e9phane Fournier-N\u00e9ri", "vol": 11.49, "range": 22.1, "wod1": 65.1, "wod2": 70.6, "wod3": 87.2}, {"name": "Samantha Cuvelier", "vol": 12.04, "range": 22.8, "wod1": 93.8, "wod2": 75.7, "wod3": 98.5}, {"name": "Emma Cornillac", "vol": 14.0, "range": 27.8, "wod1": 52.9, "wod2": 80.7, "wod3": 69.7}, {"name": "Damien Desmet", "vol": 14.5, "range": 25.3, "wod1": 74.1, "wod2": 49.2, "wod3": 74.6}, {"name": "Tom jullien", "vol": 17.5, "range": 31.1, "wod1": 74.0, "wod2": 44.5, "wod3": 75.5}, {"name": "Ilona Sepanski", "vol": 18.87, "range": 36.7, "wod1": 32.0, "wod2": 58.0, "wod3": 21.3}, {"name": "Lou Carbonnel", "vol": 19.8, "range": 39.1, "wod1": 19.6, "wod2": 58.7, "wod3": 44.6}, {"name": "Muriel S\u00e9n\u00e9quier", "vol": 21.11, "range": 42.2, "wod1": 5.9, "wod2": 25.0, "wod3": 48.0}, {"name": "Zsanett Novelinka", "vol": 23.67, "range": 47.1, "wod1": 83.1, "wod2": 36.0, "wod3": 64.0}, {"name": "Idriss Abdallah", "vol": 29.03, "range": 58.0, "wod1": 39.9, "wod2": 71.6, "wod3": 13.6}], "global_hist": [3734, 5998, 8092, 10240, 11685, 12327, 11755, 11584, 11276, 10510, 9754, 8837, 7656, 6439, 5889, 5059, 4281, 3720, 3238, 2856, 2360, 2050, 1734, 1519, 1338, 1268, 1068, 1043, 923, 811, 760, 682, 645, 587, 570, 536, 500, 490, 455], "global_edges": [0.0, 1.0256410256410255, 2.051282051282051, 3.0769230769230766, 4.102564102564102, 5.128205128205128, 6.153846153846153, 7.179487179487179, 8.205128205128204, 9.23076923076923, 10.256410256410255, 11.282051282051281, 12.307692307692307, 13.333333333333332, 14.358974358974358, 15.384615384615383, 16.41025641025641, 17.435897435897434, 18.46153846153846, 19.487179487179485, 20.51282051282051, 21.538461538461537, 22.564102564102562, 23.589743589743588, 24.615384615384613, 25.64102564102564, 26.666666666666664, 27.69230769230769, 28.717948717948715, 29.74358974358974, 30.769230769230766, 31.794871794871792, 32.82051282051282, 33.84615384615384, 34.87179487179487, 35.8974358974359, 36.92307692307692, 37.94871794871794, 38.97435897435897, 40.0]}, "demographics": {"gym_median_age": 32, "global_median_age": 36, "gym_men": 25, "gym_women": 14, "gym_men_pct": 64.1, "global_men_pct": 54.1, "age_bins": [17.5, 22.5, 27.5, 32.5, 37.5, 42.5, 47.5, 52.5, 57.5, 62.5], "gym_age_pct": [5.1, 7.7, 28.2, 15.4, 10.3, 12.8, 10.3, 10.3, 0.0, 0.0], "global_age_pct": [1.9, 4.9, 14.6, 22.2, 22.2, 16.8, 11.2, 6.3, 0.0, 0.0]}, "athletes": [{"name": "Samantha Cuvelier", "division": "women_rx", "overall_rank": 4944, "overall_pct": 95.0, "wod1_pct": 93.8, "wod2_pct": 75.7, "wod3_pct": 98.5, "wod1_reps": 264, "wod2_reps": 112, "wod3_reps": 240, "archetype": "Barbell", "volatility": 12.0, "age": 35, "wrapped": {"persona": "The Sniper", "headline": "The Sniper", "tagline": "One shot. One kill. Your 26.3 was elite.", "best_workout": "26.3", "best_pct": 98.5, "worst_workout": "26.2", "worst_pct": 75.7, "spread": 22.8, "gym_rank": 1, "gym_total": 39, "award": "Women's MVP"}, "num_opens": 2}, {"name": "Maxime Alberge", "division": "men_rx", "overall_rank": 4961, "overall_pct": 95.8, "wod1_pct": 98.4, "wod2_pct": 80.6, "wod3_pct": 99.7, "wod1_reps": 296, "wod2_reps": 124, "wod3_reps": 254, "archetype": "Barbell", "volatility": 10.6, "age": 31, "wrapped": {"persona": "The Sniper", "headline": "The Sniper", "tagline": "One shot. One kill. Your 26.3 was elite.", "best_workout": "26.3", "best_pct": 99.7, "worst_workout": "26.2", "worst_pct": 80.6, "spread": 19.1, "gym_rank": 2, "gym_total": 39, "award": "Men's MVP"}, "height_in": 70, "weight_lb": 214, "num_opens": 3}, {"name": "St\u00e9phanie Goujon", "division": "women_rx", "overall_rank": 5554, "overall_pct": 94.4, "wod1_pct": 85.0, "wod2_pct": 84.8, "wod3_pct": 97.8, "wod1_reps": 239, "wod2_reps": 118, "wod3_reps": 234, "archetype": "Barbell", "volatility": 7.4, "age": 42, "wrapped": {"persona": "The Natural", "headline": "The Natural", "tagline": "First Open. Top 89%. Explain yourself.", "best_workout": "26.3", "best_pct": 97.8, "worst_workout": "26.2", "worst_pct": 84.8, "spread": 13.0, "gym_rank": 3, "gym_total": 39, "award": "Women's Best on 26.1"}, "num_opens": 1}, {"name": "Tristan Kirchner", "division": "men_rx", "overall_rank": 6454, "overall_pct": 94.5, "wod1_pct": 87.3, "wod2_pct": 95.6, "wod3_pct": 93.8, "wod1_reps": 248, "wod2_reps": 180, "wod3_reps": 212, "archetype": "Gymnast", "volatility": 4.4, "age": 32, "wrapped": {"persona": "The Natural", "headline": "The Natural", "tagline": "First Open. Top 92%. Explain yourself.", "best_workout": "26.2", "best_pct": 95.6, "worst_workout": "26.1", "worst_pct": 87.3, "spread": 8.4, "gym_rank": 4, "gym_total": 39, "award": "Men's Best on 26.2"}, "height_in": 72, "weight_lb": 187, "num_opens": 10}, {"name": "Antoine ARY", "division": "men_rx", "overall_rank": 8907, "overall_pct": 92.4, "wod1_pct": 92.2, "wod2_pct": 94.0, "wod3_pct": 82.4, "wod1_reps": 261, "wod2_reps": 180, "wod3_reps": 192, "archetype": "Gymnast", "volatility": 6.3, "age": 28, "wrapped": {"persona": "The Natural", "headline": "The Natural", "tagline": "First Open. Top 90%. Explain yourself.", "best_workout": "26.2", "best_pct": 94.0, "worst_workout": "26.3", "worst_pct": 82.4, "spread": 11.6, "gym_rank": 5, "gym_total": 39, "award": "Men's Best on 26.1"}, "height_in": 68, "weight_lb": 152, "num_opens": 3}, {"name": "Christian Martinez", "division": "men_rx", "overall_rank": 10389, "overall_pct": 91.2, "wod1_pct": 83.6, "wod2_pct": 89.2, "wod3_pct": 90.3, "wod1_reps": 241, "wod2_reps": 180, "wod3_reps": 204, "archetype": "Barbell", "volatility": 3.6, "age": 35, "wrapped": {"persona": "The Metronome", "headline": "The Metronome", "tagline": "You don't have peaks and valleys. You have a flatline of excellence.", "best_workout": "26.3", "best_pct": 90.3, "worst_workout": "26.1", "worst_pct": 83.6, "spread": 6.7, "gym_rank": 6, "gym_total": 39, "award": "Men's Best on 26.3"}, "height_in": 68, "weight_lb": 176, "num_opens": 6}, {"name": "Seymour Saulnier", "division": "men_rx", "overall_rank": 11887, "overall_pct": 89.9, "wod1_pct": 90.7, "wod2_pct": 85.4, "wod3_pct": 81.8, "wod1_reps": 257, "wod2_reps": 129, "wod3_reps": 191, "archetype": "Engine", "volatility": 4.5, "age": 28, "wrapped": {"persona": "The Natural", "headline": "The Natural", "tagline": "First Open. Top 86%. Explain yourself.", "best_workout": "26.1", "best_pct": 90.7, "worst_workout": "26.3", "worst_pct": 81.8, "spread": 8.9, "gym_rank": 7, "gym_total": 39, "award": null}, "num_opens": 2}, {"name": "Leonardi Coralie", "division": "women_rx", "overall_rank": 16573, "overall_pct": 83.3, "wod1_pct": 68.8, "wod2_pct": 72.5, "wod3_pct": 85.9, "wod1_reps": 212, "wod2_reps": 112, "wod3_reps": 200, "archetype": "Barbell", "volatility": 9.0, "age": 35, "wrapped": {"persona": "The Comeback Kid", "headline": "The Comeback Kid", "tagline": "You gained 17 percentile points from Week 1 to Week 3. Peaked when it mattered.", "best_workout": "26.3", "best_pct": 85.9, "worst_workout": "26.1", "worst_pct": 68.8, "spread": 17.1, "gym_rank": 8, "gym_total": 39, "award": "Women's Best on 26.3"}, "num_opens": 3}, {"name": "Francois roux", "division": "men_rx", "overall_rank": 16812, "overall_pct": 85.7, "wod1_pct": 89.3, "wod2_pct": 72.4, "wod3_pct": 81.4, "wod1_reps": 253, "wod2_reps": 118, "wod3_reps": 190, "archetype": "Engine", "volatility": 8.5, "age": 31, "wrapped": {"persona": "The Natural", "headline": "The Natural", "tagline": "First Open. Top 81%. Explain yourself.", "best_workout": "26.1", "best_pct": 89.3, "worst_workout": "26.2", "worst_pct": 72.4, "spread": 16.9, "gym_rank": 9, "gym_total": 39, "award": null}, "height_in": 75, "weight_lb": 249, "num_opens": 3}, {"name": "Alexia van Vyve", "division": "women_rx", "overall_rank": 20861, "overall_pct": 78.9, "wod1_pct": 75.5, "wod2_pct": 71.8, "wod3_pct": 63.7, "wod1_reps": 222, "wod2_reps": 112, "wod3_reps": 172, "archetype": "Engine", "volatility": 6.0, "age": 28, "wrapped": {"persona": "The Natural", "headline": "The Natural", "tagline": "First Open. Top 70%. Explain yourself.", "best_workout": "26.1", "best_pct": 75.5, "worst_workout": "26.3", "worst_pct": 63.7, "spread": 11.8, "gym_rank": 10, "gym_total": 39, "award": null}, "height_in": 70, "weight_lb": 135, "num_opens": null}, {"name": "Camille Lieubray", "division": "women_rx", "overall_rank": 21094, "overall_pct": 78.7, "wod1_pct": 62.1, "wod2_pct": 73.3, "wod3_pct": 74.3, "wod1_reps": 203, "wod2_reps": 112, "wod3_reps": 183, "archetype": "Barbell", "volatility": 6.8, "age": 29, "wrapped": {"persona": "The Natural", "headline": "The Natural", "tagline": "First Open. Top 70%. Explain yourself.", "best_workout": "26.3", "best_pct": 74.3, "worst_workout": "26.1", "worst_pct": 62.1, "spread": 12.2, "gym_rank": 11, "gym_total": 39, "award": null}, "num_opens": 1}, {"name": "Maximilien Hasson", "division": "men_rx", "overall_rank": 21881, "overall_pct": 81.4, "wod1_pct": 71.1, "wod2_pct": 84.9, "wod3_pct": 74.4, "wod1_reps": 222, "wod2_reps": 129, "wod3_reps": 183, "archetype": "Gymnast", "volatility": 7.2, "age": 31, "wrapped": {"persona": "The Natural", "headline": "The Natural", "tagline": "First Open. Top 77%. Explain yourself.", "best_workout": "26.2", "best_pct": 84.9, "worst_workout": "26.1", "worst_pct": 71.1, "spread": 13.8, "gym_rank": 12, "gym_total": 39, "award": null}, "num_opens": null}, {"name": "Emma Cornillac", "division": "women_rx", "overall_rank": 22446, "overall_pct": 77.4, "wod1_pct": 52.9, "wod2_pct": 80.7, "wod3_pct": 69.7, "wod1_reps": 191, "wod2_reps": 114, "wod3_reps": 180, "archetype": "Gymnast", "volatility": 14.0, "age": 20, "wrapped": {"persona": "The Comeback Kid", "headline": "The Comeback Kid", "tagline": "You gained 17 percentile points from Week 1 to Week 3. Peaked when it mattered.", "best_workout": "26.2", "best_pct": 80.7, "worst_workout": "26.1", "worst_pct": 52.9, "spread": 27.8, "gym_rank": 13, "gym_total": 39, "award": "Women's Best on 26.2"}, "height_in": 64, "weight_lb": 121, "num_opens": 2}, {"name": "Tiago Santos Pinheiro", "division": "men_rx", "overall_rank": 23999, "overall_pct": 79.6, "wod1_pct": 72.6, "wod2_pct": 83.0, "wod3_pct": 69.4, "wod1_reps": 225, "wod2_reps": 127, "wod3_reps": 180, "archetype": "Gymnast", "volatility": 7.1, "age": 27, "wrapped": {"persona": "The Natural", "headline": "The Natural", "tagline": "First Open. Top 75%. Explain yourself.", "best_workout": "26.2", "best_pct": 83.0, "worst_workout": "26.3", "worst_pct": 69.4, "spread": 13.6, "gym_rank": 14, "gym_total": 39, "award": null}, "height_in": 70, "weight_lb": 176, "num_opens": null}, {"name": "Guillaume Peres", "division": "men_rx", "overall_rank": 24381, "overall_pct": 79.3, "wod1_pct": 82.3, "wod2_pct": 70.0, "wod3_pct": 70.6, "wod1_reps": 239, "wod2_reps": 117, "wod3_reps": 180, "archetype": "Engine", "volatility": 6.9, "age": 29, "wrapped": {"persona": "The Natural", "headline": "The Natural", "tagline": "First Open. Top 74%. Explain yourself.", "best_workout": "26.1", "best_pct": 82.3, "worst_workout": "26.2", "worst_pct": 70.0, "spread": 12.3, "gym_rank": 15, "gym_total": 39, "award": null}, "num_opens": 1}, {"name": "Pierre Etienne Mathot", "division": "men_rx", "overall_rank": 26703, "overall_pct": 77.4, "wod1_pct": 71.6, "wod2_pct": 76.2, "wod3_pct": 69.7, "wod1_reps": 223, "wod2_reps": 121, "wod3_reps": 180, "archetype": "Gymnast", "volatility": 3.3, "age": 43, "wrapped": {"persona": "The Natural", "headline": "The Natural", "tagline": "First Open. Top 72%. Explain yourself.", "best_workout": "26.2", "best_pct": 76.2, "worst_workout": "26.3", "worst_pct": 69.7, "spread": 6.5, "gym_rank": 16, "gym_total": 39, "award": "Men's Best 40\u201344"}, "height_in": 74, "weight_lb": 192, "num_opens": 5}, {"name": "Thibault Forneris", "division": "men_rx", "overall_rank": 27722, "overall_pct": 76.5, "wod1_pct": 73.5, "wod2_pct": 71.7, "wod3_pct": 69.5, "wod1_reps": 226, "wod2_reps": 118, "wod3_reps": 180, "archetype": "Engine", "volatility": 2.0, "age": 21, "wrapped": {"persona": "The Natural", "headline": "The Natural", "tagline": "First Open. Top 72%. Explain yourself.", "best_workout": "26.1", "best_pct": 73.5, "worst_workout": "26.3", "worst_pct": 69.5, "spread": 4.0, "gym_rank": 17, "gym_total": 39, "award": "Men's Metronome"}, "num_opens": null}, {"name": "Zsanett Novelinka", "division": "women_rx", "overall_rank": 27776, "overall_pct": 72.0, "wod1_pct": 83.1, "wod2_pct": 36.0, "wod3_pct": 64.0, "wod1_reps": 235, "wod2_reps": 80, "wod3_reps": 172, "archetype": "Engine", "volatility": 23.7, "age": 34, "wrapped": {"persona": "The Natural", "headline": "The Natural", "tagline": "First Open. Top 61%. Explain yourself.", "best_workout": "26.1", "best_pct": 83.1, "worst_workout": "26.2", "worst_pct": 36.0, "spread": 47.1, "gym_rank": 18, "gym_total": 39, "award": "Women's Wildcard"}, "num_opens": null}, {"name": "Alexey Derevianko", "division": "men_rx", "overall_rank": 32270, "overall_pct": 72.6, "wod1_pct": 65.7, "wod2_pct": 65.4, "wod3_pct": 71.8, "wod1_reps": 216, "wod2_reps": 115, "wod3_reps": 181, "archetype": "Barbell", "volatility": 3.6, "age": 48, "wrapped": {"persona": "The Natural", "headline": "The Natural", "tagline": "First Open. Top 68%. Explain yourself.", "best_workout": "26.3", "best_pct": 71.8, "worst_workout": "26.2", "worst_pct": 65.4, "spread": 6.4, "gym_rank": 19, "gym_total": 39, "award": "Men's Best 45\u201349"}, "height_in": 72, "num_opens": 3}, {"name": "Fabien Vizzini", "division": "men_rx", "overall_rank": 33788, "overall_pct": 71.3, "wod1_pct": 53.9, "wod2_pct": 70.4, "wod3_pct": 74.8, "wod1_reps": 201, "wod2_reps": 117, "wod3_reps": 183, "archetype": "Barbell", "volatility": 11.0, "age": 44, "wrapped": {"persona": "The Comeback Kid", "headline": "The Comeback Kid", "tagline": "You gained 21 percentile points from Week 1 to Week 3. Peaked when it mattered.", "best_workout": "26.3", "best_pct": 74.8, "worst_workout": "26.1", "worst_pct": 53.9, "spread": 20.9, "gym_rank": 20, "gym_total": 39, "award": null}, "height_in": 70, "weight_lb": 176, "num_opens": 2}, {"name": "Damien Desmet", "division": "men_rx", "overall_rank": 34241, "overall_pct": 71.0, "wod1_pct": 74.1, "wod2_pct": 49.2, "wod3_pct": 74.6, "wod1_reps": 227, "wod2_reps": 112, "wod3_reps": 183, "archetype": "Barbell", "volatility": 14.5, "age": 52, "wrapped": {"persona": "The Natural", "headline": "The Natural", "tagline": "First Open. Top 66%. Explain yourself.", "best_workout": "26.3", "best_pct": 74.6, "worst_workout": "26.2", "worst_pct": 49.2, "spread": 25.3, "gym_rank": 21, "gym_total": 39, "award": "Men's Best 50\u201354"}, "num_opens": 1}, {"name": "Tom jullien", "division": "men_rx", "overall_rank": 35859, "overall_pct": 69.6, "wod1_pct": 74.0, "wod2_pct": 44.5, "wod3_pct": 75.5, "wod1_reps": 227, "wod2_reps": 112, "wod3_reps": 184, "archetype": "Barbell", "volatility": 17.5, "age": 26, "wrapped": {"persona": "The Natural", "headline": "The Natural", "tagline": "First Open. Top 65%. Explain yourself.", "best_workout": "26.3", "best_pct": 75.5, "worst_workout": "26.2", "worst_pct": 44.5, "spread": 31.1, "gym_rank": 22, "gym_total": 39, "award": null}, "num_opens": null}, {"name": "Laurent Sinopoli", "division": "men_rx", "overall_rank": 37163, "overall_pct": 68.5, "wod1_pct": 52.0, "wod2_pct": 73.4, "wod3_pct": 65.5, "wod1_reps": 199, "wod2_reps": 119, "wod3_reps": 175, "archetype": "Gymnast", "volatility": 10.8, "age": 50, "wrapped": {"persona": "The Natural", "headline": "The Natural", "tagline": "First Open. Top 64%. Explain yourself.", "best_workout": "26.2", "best_pct": 73.4, "worst_workout": "26.1", "worst_pct": 52.0, "spread": 21.4, "gym_rank": 23, "gym_total": 39, "award": null}, "height_in": 70, "weight_lb": 183, "num_opens": 5}, {"name": "Pierre Loreti", "division": "men_rx", "overall_rank": 50650, "overall_pct": 57.1, "wod1_pct": 58.0, "wod2_pct": 41.3, "wod3_pct": 56.6, "wod1_reps": 207, "wod2_reps": 112, "wod3_reps": 164, "archetype": "Engine", "volatility": 9.3, "age": 47, "wrapped": {"persona": "The Ageless", "headline": "The Ageless", "tagline": "Age 47. Still making 25-year-olds nervous.", "best_workout": "26.1", "best_pct": 58.0, "worst_workout": "26.2", "worst_pct": 41.3, "spread": 16.7, "gym_rank": 24, "gym_total": 39, "award": null}, "height_in": 72, "weight_lb": 163, "num_opens": 5}, {"name": "Rudy Robin", "division": "men_rx", "overall_rank": 59221, "overall_pct": 49.8, "wod1_pct": 46.7, "wod2_pct": 40.3, "wod3_pct": 45.4, "wod1_reps": 193, "wod2_reps": 112, "wod3_reps": 150, "archetype": "Engine", "volatility": 3.4, "age": 37, "wrapped": {"persona": "The Origin Story", "headline": "The Origin Story", "tagline": "Every great athlete has a Chapter 1. This is yours.", "best_workout": "26.1", "best_pct": 46.7, "worst_workout": "26.2", "worst_pct": 40.3, "spread": 6.4, "gym_rank": 25, "gym_total": 39, "award": "Men's Best 35\u201339"}, "num_opens": 2}, {"name": "Ilona Sepanski", "division": "women_rx", "overall_rank": 59956, "overall_pct": 39.5, "wod1_pct": 32.0, "wod2_pct": 58.0, "wod3_pct": 21.3, "wod1_reps": 166, "wod2_reps": 112, "wod3_reps": 123, "archetype": "Gymnast", "volatility": 18.9, "age": 26, "wrapped": {"persona": "The Origin Story", "headline": "The Origin Story", "tagline": "Every great athlete has a Chapter 1. This is yours.", "best_workout": "26.2", "best_pct": 58.0, "worst_workout": "26.3", "worst_pct": 21.3, "spread": 36.7, "gym_rank": 26, "gym_total": 39, "award": null}, "num_opens": null}, {"name": "Marlene Kwiatkowski", "division": "women_rx", "overall_rank": 60094, "overall_pct": 39.4, "wod1_pct": 16.2, "wod2_pct": 13.4, "wod3_pct": 18.5, "wod1_reps": 144, "wod2_reps": 47, "wod3_reps": 116, "archetype": "Barbell", "volatility": 2.5, "age": 44, "wrapped": {"persona": "The Wolf", "headline": "The Wolf", "tagline": "Part of the pack. Stronger because of it.", "best_workout": "26.3", "best_pct": 18.5, "worst_workout": "26.2", "worst_pct": 13.4, "spread": 5.1, "gym_rank": 27, "gym_total": 39, "award": "Women's Best 40\u201344"}, "num_opens": null}, {"name": "Idriss Abdallah", "division": "men_rx", "overall_rank": 60665, "overall_pct": 48.6, "wod1_pct": 39.9, "wod2_pct": 71.6, "wod3_pct": 13.6, "wod1_reps": 185, "wod2_reps": 118, "wod3_reps": 36, "archetype": "Gymnast", "volatility": 29.0, "age": 26, "wrapped": {"persona": "The Origin Story", "headline": "The Origin Story", "tagline": "Every great athlete has a Chapter 1. This is yours.", "best_workout": "26.2", "best_pct": 71.6, "worst_workout": "26.3", "worst_pct": 13.6, "spread": 58.0, "gym_rank": 28, "gym_total": 39, "award": "Men's Wildcard"}, "num_opens": 3}, {"name": "Virginie Carbonnel", "division": "women_rx", "overall_rank": 66759, "overall_pct": 32.6, "wod1_pct": 19.5, "wod2_pct": 21.4, "wod3_pct": 24.1, "wod1_reps": 149, "wod2_reps": 68, "wod3_reps": 129, "archetype": "Barbell", "volatility": 2.3, "age": 50, "wrapped": {"persona": "The Ageless", "headline": "The Ageless", "tagline": "Age 50. Still making 25-year-olds nervous.", "best_workout": "26.3", "best_pct": 24.1, "worst_workout": "26.1", "worst_pct": 19.5, "spread": 4.6, "gym_rank": 29, "gym_total": 39, "award": "Women's Metronome"}, "num_opens": 3}, {"name": "Charly Pupetto", "division": "men_rx", "overall_rank": 67257, "overall_pct": null, "wod1_pct": 50.4, "wod2_pct": 54.3, "wod3_pct": null, "wod1_reps": 197, "wod2_reps": 112, "wod3_reps": 0, "archetype": "Gymnast", "volatility": 30.3, "age": 16, "wrapped": {"persona": "The Origin Story", "headline": "The Origin Story", "tagline": "Every great athlete has a Chapter 1. This is yours.", "best_workout": "26.2", "best_pct": 54.3, "worst_workout": "26.3", "worst_pct": 0.0, "spread": 54.3, "gym_rank": 30, "gym_total": 39, "award": null}, "num_opens": null}, {"name": "Lou Carbonnel", "division": "women_rx", "overall_rank": 68498, "overall_pct": 30.9, "wod1_pct": 19.6, "wod2_pct": 58.7, "wod3_pct": 44.6, "wod1_reps": 149, "wod2_reps": 112, "wod3_reps": 148, "archetype": "Gymnast", "volatility": 19.8, "age": 17, "wrapped": {"persona": "The Comeback Kid", "headline": "The Comeback Kid", "tagline": "You gained 25 percentile points from Week 1 to Week 3. Peaked when it mattered.", "best_workout": "26.2", "best_pct": 58.7, "worst_workout": "26.1", "worst_pct": 19.6, "spread": 39.1, "gym_rank": 31, "gym_total": 39, "award": null}, "num_opens": null}, {"name": "Mathilda Carlon", "division": "women_rx", "overall_rank": 71865, "overall_pct": null, "wod1_pct": null, "wod2_pct": 84.3, "wod3_pct": 33.3, "wod1_reps": 0, "wod2_reps": 118, "wod3_reps": 137, "archetype": "Gymnast", "volatility": 42.4, "age": 24, "wrapped": {"persona": "The Origin Story", "headline": "The Origin Story", "tagline": "Every great athlete has a Chapter 1. This is yours.", "best_workout": "26.2", "best_pct": 84.3, "worst_workout": "26.1", "worst_pct": 0.0, "spread": 84.3, "gym_rank": 32, "gym_total": 39, "award": null}, "num_opens": null}, {"name": "Aleksandr JOGALEV", "division": "men_rx", "overall_rank": 72857, "overall_pct": 38.2, "wod1_pct": 28.3, "wod2_pct": 26.5, "wod3_pct": 39.9, "wod1_reps": 170, "wod2_reps": 91, "wod3_reps": 143, "archetype": "Barbell", "volatility": 7.3, "age": 46, "wrapped": {"persona": "The Slow Burn", "headline": "The Slow Burn", "tagline": "Started quiet. Finished loud.", "best_workout": "26.3", "best_pct": 39.9, "worst_workout": "26.2", "worst_pct": 26.5, "spread": 13.5, "gym_rank": 33, "gym_total": 39, "award": null}, "height_in": 70, "weight_lb": 205, "num_opens": 2}, {"name": "St\u00e9phane Fournier-N\u00e9ri", "division": "men_rx", "overall_rank": 75974, "overall_pct": 35.6, "wod1_pct": 65.1, "wod2_pct": 70.6, "wod3_pct": 87.2, "wod1_reps": 215, "wod2_reps": 117, "wod3_reps": 201, "archetype": "Barbell", "volatility": 11.5, "age": 34, "wrapped": {"persona": "The Comeback Kid", "headline": "The Comeback Kid", "tagline": "You gained 22 percentile points from Week 1 to Week 3. Peaked when it mattered.", "best_workout": "26.3", "best_pct": 87.2, "worst_workout": "26.1", "worst_pct": 65.1, "spread": 22.1, "gym_rank": 34, "gym_total": 39, "award": "Men's Closer"}, "num_opens": null}, {"name": "Muriel S\u00e9n\u00e9quier", "division": "women_rx", "overall_rank": 76159, "overall_pct": 23.2, "wod1_pct": 5.9, "wod2_pct": 25.0, "wod3_pct": 48.0, "wod1_reps": 105, "wod2_reps": 68, "wod3_reps": 152, "archetype": "Barbell", "volatility": 21.1, "age": 54, "wrapped": {"persona": "The Comeback Kid", "headline": "The Comeback Kid", "tagline": "You gained 42 percentile points from Week 1 to Week 3. Peaked when it mattered.", "best_workout": "26.3", "best_pct": 48.0, "worst_workout": "26.1", "worst_pct": 5.9, "spread": 42.2, "gym_rank": 35, "gym_total": 39, "award": "Women's Closer"}, "height_in": 67, "weight_lb": 159, "num_opens": null}, {"name": "Loic Teurkia", "division": "men_rx", "overall_rank": 77504, "overall_pct": 34.3, "wod1_pct": 25.5, "wod2_pct": 29.4, "wod3_pct": 28.4, "wod1_reps": 166, "wod2_reps": 93, "wod3_reps": 134, "archetype": "Gymnast", "volatility": 2.0, "age": 40, "wrapped": {"persona": "The Ageless", "headline": "The Ageless", "tagline": "Age 40. Still making 25-year-olds nervous.", "best_workout": "26.2", "best_pct": 29.4, "worst_workout": "26.1", "worst_pct": 25.5, "spread": 3.9, "gym_rank": 36, "gym_total": 39, "award": null}, "num_opens": null}, {"name": "Ana\u00efs Rondini", "division": "women_rx", "overall_rank": 81053, "overall_pct": 18.2, "wod1_pct": 5.6, "wod2_pct": 23.3, "wod3_pct": 14.4, "wod1_reps": 103, "wod2_reps": 68, "wod3_reps": 99, "archetype": "Gymnast", "volatility": 8.9, "age": 27, "wrapped": {"persona": "The Wolf", "headline": "The Wolf", "tagline": "Part of the pack. Stronger because of it.", "best_workout": "26.2", "best_pct": 23.3, "worst_workout": "26.1", "worst_pct": 5.6, "spread": 17.7, "gym_rank": 37, "gym_total": 39, "award": null}, "num_opens": null}, {"name": "Norbert LIMA BRAS", "division": "men_rx", "overall_rank": 95984, "overall_pct": null, "wod1_pct": 14.7, "wod2_pct": 21.0, "wod3_pct": null, "wod1_reps": 149, "wod2_reps": 88, "wod3_reps": 0, "archetype": "Gymnast", "volatility": 10.8, "age": 48, "wrapped": {"persona": "The Wolf", "headline": "The Wolf", "tagline": "Part of the pack. Stronger because of it.", "best_workout": "26.2", "best_pct": 21.0, "worst_workout": "26.3", "worst_pct": 0.0, "spread": 21.0, "gym_rank": 38, "gym_total": 39, "award": null}, "num_opens": 1}, {"name": "Enzo Baile", "division": "men_rx", "overall_rank": 105132, "overall_pct": 10.9, "wod1_pct": 4.5, "wod2_pct": 13.1, "wod3_pct": 14.5, "wod1_reps": 102, "wod2_reps": 68, "wod3_reps": 93, "archetype": "Barbell", "volatility": 5.4, "age": 27, "wrapped": {"persona": "The Wolf", "headline": "The Wolf", "tagline": "Part of the pack. Stronger because of it.", "best_workout": "26.3", "best_pct": 14.5, "worst_workout": "26.1", "worst_pct": 4.5, "spread": 10.0, "gym_rank": 39, "gym_total": 39, "award": null}, "height_in": 70, "weight_lb": 232, "num_opens": null}]}