{"affiliate_name": "Hubmind CrossFit", "affiliate_id": 35992, "total_athletes": 79, "rx_count": 74, "scaled_count": 5, "gym_rank": 7855, "total_gyms": 8587, "gym_rank_pct": 91.5, "overall_median_pct": 33.0, "workout_stats": {"wod1": {"name": "26.1", "type": "engine", "gym_median": 34.6, "global_median": 54.3, "gym_rank_pct": 13.8}, "wod2": {"name": "26.2", "type": "gymnastics", "gym_median": 41.1, "global_median": 55.5, "gym_rank_pct": 18.4}, "wod3": {"name": "26.3", "type": "barbell", "gym_median": 37.5, "global_median": 57.4, "gym_rank_pct": 10.0}}, "gym_archetype": "Gymnast", "best_workout": {"key": "wod2", "name": "26.2", "type": "gymnastics"}, "worst_workout": {"key": "wod1", "name": "26.1", "type": "engine"}, "muscle_up": {"gym_got_mu": 31, "gym_total": 59, "gym_mu_pct": 52.5, "global_mu_pct": 63.1, "global_got_mu": 124606, "global_total": 197366, "athletes": [{"name": "Jose Carlos Gutierrez Garibay", "reps": 180, "got_mu": true}, {"name": "Bruno Gonzalez Villalobos", "reps": 180, "got_mu": true}, {"name": "Miguel Angel Tovar Ovalle", "reps": 132, "got_mu": true}, {"name": "Luis Fernando Napoleon Napoles Casta\u00f1eda", "reps": 128, "got_mu": true}, {"name": "Fernanda Cruz", "reps": 127, "got_mu": true}, {"name": "Jorge Loredo", "reps": 123, "got_mu": true}, {"name": "Irwin Cohen", "reps": 119, "got_mu": true}, {"name": "Genaro Velasco", "reps": 119, "got_mu": true}, {"name": "Graciela Canzonetta", "reps": 118, "got_mu": true}, {"name": "Jose Maria Guerra", "reps": 117, "got_mu": true}, {"name": "Ricardo Cajal", "reps": 116, "got_mu": true}, {"name": "Paloma Escandon", "reps": 116, "got_mu": true}, {"name": "Mauro Tapia", "reps": 114, "got_mu": true}, {"name": "Israel Aldana", "reps": 112, "got_mu": true}, {"name": "Diego Gonzalez Figueroa", "reps": 112, "got_mu": true}, {"name": "Daniel Sanchez", "reps": 112, "got_mu": true}, {"name": "David Casillas", "reps": 112, "got_mu": true}, {"name": "Gustavo Carrillo", "reps": 112, "got_mu": true}, {"name": "Alonso Careaga", "reps": 112, "got_mu": true}, {"name": "Francisco Granados", "reps": 112, "got_mu": true}, {"name": "Eduardo Negrete", "reps": 112, "got_mu": true}, {"name": "Ver\u00f3nica Genis", "reps": 112, "got_mu": true}, {"name": "Mariana Jacob", "reps": 112, "got_mu": true}, {"name": "Itzel Vazquez Alvarez", "reps": 112, "got_mu": true}, {"name": "Paola Corona", "reps": 112, "got_mu": true}, {"name": "Gabriela Sanchez Lopez", "reps": 112, "got_mu": true}, {"name": "Rosibel Cabello", "reps": 112, "got_mu": true}, {"name": "Rebeca Avimelech", "reps": 112, "got_mu": true}, {"name": "Barbara Anez", "reps": 112, "got_mu": true}, {"name": "Karla Garibay", "reps": 112, "got_mu": true}, {"name": "Eliana Cardozo", "reps": 112, "got_mu": true}, {"name": "Xiomara De La Torre", "reps": 108, "got_mu": false}, {"name": "Ana Paola Orozco Ponce", "reps": 102, "got_mu": false}, {"name": "Gerardo Hernandez", "reps": 91, "got_mu": false}, {"name": "Omero Gonz\u00e1lez", "reps": 91, "got_mu": false}, {"name": "Yoseline Hoffman", "reps": 91, "got_mu": false}, {"name": "Daniel montiel", "reps": 90, "got_mu": false}, {"name": "Alejandro Garcia", "reps": 90, "got_mu": false}, {"name": "Juan Carlos Villarreal", "reps": 89, "got_mu": false}, {"name": "Armando Maita", "reps": 89, "got_mu": false}, {"name": "Erick Ovando", "reps": 89, "got_mu": false}, {"name": "Ana Sofia Trejo", "reps": 89, "got_mu": false}, {"name": "Luis Puerta", "reps": 87, "got_mu": false}, {"name": "Marcos Daniel Escamilla Gochar", "reps": 84, "got_mu": false}, {"name": "Diego Echeverria", "reps": 79, "got_mu": false}, {"name": "Rogelio Espinosa", "reps": 75, "got_mu": false}, {"name": "Jonathan Campos", "reps": 71, "got_mu": false}, {"name": "Iveth Bogota", "reps": 69, "got_mu": false}, {"name": "Emilia Loredo", "reps": 68, "got_mu": false}, {"name": "Kim Mejia", "reps": 68, "got_mu": false}, {"name": "Anaya Atlan", "reps": 68, "got_mu": false}, {"name": "Laura Assis Iragorri", "reps": 68, "got_mu": false}, {"name": "Gabriela Schlam", "reps": 68, "got_mu": false}, {"name": "Laura Laurian", "reps": 68, "got_mu": false}, {"name": "Liliana Torres", "reps": 68, "got_mu": false}, {"name": "Karol Cueto", "reps": 68, "got_mu": false}, {"name": "Daniela Valverde", "reps": 68, "got_mu": false}, {"name": "Adriana Arely Minero", "reps": 68, "got_mu": false}, {"name": "Geraldine Gonzalez", "reps": 68, "got_mu": false}]}, "similar_gyms": {"gym_size": 79, "size_range": [56, 102], "similar_count": 571, "gym_rank_among_similar": 501, "similar_median_pct": 52.2, "similar_p75_pct": 62.2, "similar_p25_pct": 41.3, "gym_pct": 33.0, "similar_pcts": [9.5, 13.4, 13.4, 14.0, 14.2, 15.7, 16.7, 17.7, 18.6, 19.1, 19.4, 20.1, 20.2, 20.7, 21.6, 21.8, 21.9, 21.9, 22.4, 23.3, 23.5, 23.6, 23.7, 24.1, 24.1, 24.3, 24.3, 24.3, 24.3, 24.4, 24.6, 24.7, 25.1, 25.4, 26.3, 26.3, 26.4, 26.6, 26.8, 26.9, 27.2, 27.4, 27.8, 28.3, 28.4, 28.8, 28.8, 28.8, 28.9, 29.0, 29.0, 29.6, 29.7, 29.9, 30.0, 30.1, 30.2, 30.3, 30.7, 30.8, 30.8, 31.0, 31.4, 31.4, 31.7, 31.9, 32.1, 32.2, 32.3, 32.3, 32.8, 33.9, 33.9, 34.0, 34.0, 34.1, 34.5, 34.5, 34.6, 34.6, 34.9, 35.0, 35.2, 35.3, 35.3, 35.4, 35.6, 35.6, 35.6, 35.8, 35.9, 36.1, 36.2, 36.3, 36.3, 36.4, 36.6, 36.7, 37.0, 37.1, 37.2, 37.2, 37.2, 37.3, 37.6, 37.7, 37.7, 38.0, 38.2, 38.3, 38.3, 38.3, 38.3, 38.4, 38.7, 38.8, 38.9, 39.0, 39.1, 39.3, 39.4, 39.5, 39.6, 39.8, 39.9, 40.1, 40.4, 40.5, 40.5, 40.6, 40.7, 40.7, 40.7, 40.7, 40.8, 40.9, 40.9, 41.0, 41.0, 41.1, 41.1, 41.3, 41.3, 41.3, 41.4, 41.5, 41.5, 41.5, 41.5, 41.6, 41.8, 41.9, 41.9, 41.9, 42.0, 42.1, 42.2, 42.3, 42.3, 42.5, 42.5, 42.7, 42.8, 42.9, 43.0, 43.0, 43.2, 43.2, 43.3, 43.3, 43.3, 43.3, 43.4, 43.4, 43.4, 43.5, 43.5, 43.6, 43.6, 43.7, 43.7, 43.9, 43.9, 44.1, 44.2, 44.3, 44.4, 44.4, 44.5, 44.6, 44.6, 44.6, 44.7, 44.8, 45.1, 45.1, 45.3, 45.3, 45.4, 45.4, 45.5, 45.6, 45.7, 45.7, 45.7, 45.7, 45.7, 45.9, 45.9, 46.0, 46.6, 46.6, 46.8, 46.8, 46.9, 46.9, 47.1, 47.1, 47.2, 47.5, 47.5, 47.6, 47.6, 47.6, 47.6, 47.7, 47.8, 47.8, 47.9, 47.9, 48.0, 48.0, 48.2, 48.2, 48.2, 48.2, 48.5, 48.5, 48.5, 48.5, 48.6, 48.6, 48.6, 48.7, 48.8, 48.8, 48.9, 49.0, 49.1, 49.3, 49.3, 49.4, 49.5, 49.5, 49.5, 49.6, 49.6, 49.6, 49.8, 49.9, 50.0, 50.0, 50.2, 50.2, 50.3, 50.3, 50.3, 50.5, 50.7, 50.8, 50.9, 50.9, 51.0, 51.0, 51.2, 51.3, 51.6, 51.7, 51.7, 51.8, 51.8, 52.0, 52.0, 52.1, 52.2, 52.2, 52.3, 52.4, 52.5, 52.6, 52.7, 52.8, 52.9, 52.9, 53.0, 53.0, 53.1, 53.1, 53.3, 53.4, 53.4, 53.5, 53.7, 53.7, 53.7, 53.7, 53.8, 53.9, 54.0, 54.0, 54.1, 54.1, 54.2, 54.2, 54.3, 54.3, 54.3, 54.4, 54.4, 54.5, 54.5, 54.5, 54.5, 54.5, 54.6, 54.6, 54.6, 54.7, 54.7, 54.8, 54.8, 54.9, 55.0, 55.0, 55.3, 55.3, 55.3, 55.4, 55.5, 55.6, 55.6, 55.7, 55.7, 55.7, 55.8, 55.9, 55.9, 56.0, 56.0, 56.1, 56.2, 56.2, 56.3, 56.3, 56.3, 56.4, 56.6, 56.6, 56.7, 56.7, 56.8, 56.8, 56.9, 56.9, 56.9, 57.0, 57.0, 57.0, 57.2, 57.2, 57.4, 57.4, 57.4, 57.5, 57.6, 57.7, 57.9, 57.9, 57.9, 58.0, 58.0, 58.1, 58.2, 58.2, 58.4, 58.5, 58.5, 58.6, 58.6, 58.7, 58.7, 58.7, 58.7, 58.9, 59.0, 59.0, 59.1, 59.1, 59.2, 59.3, 59.4, 59.5, 59.5, 59.6, 59.6, 59.6, 59.7, 59.7, 59.7, 59.8, 59.9, 60.0, 60.1, 60.5, 60.5, 60.6, 60.9, 60.9, 61.0, 61.3, 61.5, 61.6, 61.6, 61.8, 61.8, 61.9, 62.0, 62.1, 62.3, 62.5, 62.5, 62.6, 62.7, 62.8, 62.8, 62.8, 62.9, 63.0, 63.1, 63.1, 63.2, 63.3, 63.4, 63.5, 63.6, 63.6, 63.6, 63.6, 63.8, 63.8, 63.9, 64.0, 64.0, 64.0, 64.3, 64.4, 64.4, 64.4, 64.4, 64.5, 64.5, 64.8, 64.9, 65.2, 65.3, 65.3, 65.4, 65.5, 65.6, 65.6, 65.8, 66.0, 66.0, 66.3, 66.6, 66.8, 66.8, 66.8, 67.2, 67.5, 67.8, 68.0, 68.0, 68.1, 68.2, 68.2, 68.2, 68.3, 68.4, 68.5, 68.7, 68.8, 68.8, 68.9, 69.1, 69.1, 69.1, 69.3, 69.4, 69.5, 69.6, 69.7, 69.9, 70.3, 70.3, 70.3, 70.3, 70.4, 70.4, 70.8, 71.1, 71.2, 71.6, 71.7, 71.9, 72.1, 72.2, 72.3, 72.4, 72.4, 72.7, 72.8, 72.9, 72.9, 72.9, 73.0, 73.2, 73.2, 73.3, 73.8, 73.9, 74.1, 74.3, 74.4, 74.4, 74.6, 74.7, 75.0, 75.2, 75.4, 75.6, 75.6, 76.1, 76.1, 77.1, 77.2, 77.3, 77.9, 78.4, 78.4, 78.8, 79.9, 80.9, 81.4, 82.8, 82.8, 83.0, 83.4, 83.5, 83.5, 83.5, 83.7, 84.0, 84.2, 84.2, 84.5, 84.6, 86.9, 88.2, 88.7, 88.7], "comparable_gyms": [{"name": "CrossFit Rev Weatherford", "pct": 32.8, "rank": 7867}, {"name": "CrossFit Overthrow", "pct": 32.3, "rank": 7903}, {"name": "Premier CrossFit", "pct": 32.3, "rank": 7904}, {"name": "CrossFit Naga", "pct": 32.2, "rank": 7910}, {"name": "CrossFit Taniwha", "pct": 33.9, "rank": 7811}, {"name": "CrossFit Palo Alto", "pct": 33.9, "rank": 7812}, {"name": "CrossFit Payerne", "pct": 32.1, "rank": 7913}, {"name": "CrossFit Kempton", "pct": 34.0, "rank": 7804}, {"name": "Onyx Tribe CrossFit", "pct": 34.0, "rank": 7806}, {"name": "CrossFit PFC", "pct": 34.1, "rank": 7795}]}, "rx_decision": {"gym_rx_count": 74, "gym_scaled_count": 5, "gym_rx_pct": 93.7, "global_rx_pct": 95.6, "by_age": [{"age_range": "18-24", "gym_rx_pct": 100.0, "global_rx_pct": 96.1, "gym_count": 8}, {"age_range": "25-29", "gym_rx_pct": 100.0, "global_rx_pct": 96.4, "gym_count": 13}, {"age_range": "30-34", "gym_rx_pct": 100.0, "global_rx_pct": 96.3, "gym_count": 14}, {"age_range": "35-39", "gym_rx_pct": 100.0, "global_rx_pct": 96.0, "gym_count": 17}, {"age_range": "40-44", "gym_rx_pct": 81.8, "global_rx_pct": 95.2, "gym_count": 11}, {"age_range": "45-49", "gym_rx_pct": 72.7, "global_rx_pct": 94.3, "gym_count": 11}, {"age_range": "50-65", "gym_rx_pct": 100.0, "global_rx_pct": 93.0, "gym_count": 4}]}, "hidden_gems": [{"name": "Miguel Angel Tovar Ovalle", "overall_pct": 14.4, "best_workout": "26.2", "best_pct": 91.2, "gap": 76.9, "wod1": 91.2, "wod2": 91.2, "wod3": 75.8}, {"name": "Alejandro Garcia", "overall_pct": 10.1, "best_workout": "26.3", "best_pct": 78.1, "gap": 68.0, "wod1": 59.7, "wod2": 25.4, "wod3": 78.1}, {"name": "Omero Gonz\u00e1lez", "overall_pct": 27.3, "best_workout": "26.1", "best_pct": 85.4, "gap": 58.1, "wod1": 85.4, "wod2": 27.1, "wod3": 32.2}, {"name": "Fernanda Cruz", "overall_pct": 44.3, "best_workout": "26.2", "best_pct": 89.0, "gap": 44.7, "wod1": 31.2, "wod2": 89.0, "wod3": 33.5}, {"name": "Eliana Cardozo", "overall_pct": 22.2, "best_workout": "26.2", "best_pct": 66.7, "gap": 44.6, "wod1": 36.7, "wod2": 66.7, "wod3": 48.4}, {"name": "Francisco Granados", "overall_pct": 9.4, "best_workout": "26.3", "best_pct": 53.3, "gap": 43.9, "wod1": 34.1, "wod2": 49.6, "wod3": 53.3}, {"name": "Paloma Escandon", "overall_pct": 40.2, "best_workout": "26.2", "best_pct": 82.8, "gap": 42.6, "wod1": 13.4, "wod2": 82.8, "wod3": 35.9}, {"name": "Eduardo Negrete", "overall_pct": 7.2, "best_workout": "26.1", "best_pct": 40.3, "gap": 33.1, "wod1": 40.3, "wod2": 36.5, "wod3": 22.9}], "awards": [{"title": "Women's MVP", "subtitle": "Highest overall percentile", "name": "Graciela Canzonetta", "detail": "Overall 93th percentile \u2014 your gym's top performer", "stats": {"wod1": 91.3, "wod2": 84.6, "wod3": 88.0}}, {"title": "Women's Wildcard", "subtitle": "Biggest swing between workouts", "name": "Paloma Escandon", "detail": "Range: 69 percentile points between best and worst", "stats": {"wod1": 13.4, "wod2": 82.8, "wod3": 35.9}}, {"title": "Women's Best on 26.1", "subtitle": "Top performer on 26.1", "name": "Ver\u00f3nica Genis", "detail": "81th percentile on 26.1", "stats": {"wod1": 80.8, "wod2": 65.9, "wod3": 89.8}}, {"title": "Women's Best on 26.2", "subtitle": "Top performer on 26.2", "name": "Fernanda Cruz", "detail": "89th percentile on 26.2", "stats": {"wod1": 31.2, "wod2": 89.0, "wod3": 33.5}}, {"title": "Women's Best on 26.3", "subtitle": "Top performer on 26.3", "name": "Mariana Jacob", "detail": "88th percentile on 26.3", "stats": {"wod1": 75.3, "wod2": 66.9, "wod3": 87.5}}, {"title": "Women's Metronome", "subtitle": "Most consistent across all 3 workouts", "name": "Laura Assis Iragorri", "detail": "Volatility: 4.6 \u2014 nearly the same percentile every week", "stats": {"wod1": 32.5, "wod2": 23.9, "wod3": 25.3}}, {"title": "Women's Closer", "subtitle": "Biggest improvement Week 1 \u2192 Week 3", "name": "Ana Paola Orozco Ponce", "detail": "Jumped 46 percentile points from 26.1 to 26.3", "stats": {"wod1": 17.2, "wod2": 48.7, "wod3": 62.8}}, {"title": "Women's Best 35\u201339", "subtitle": "Top performer ages 35\u201339", "name": "Itzel Vazquez Alvarez", "detail": "Age 36, overall 79th percentile", "stats": {"wod1": 58.3, "wod2": 67.7, "wod3": 84.6}}, {"title": "Women's Best 45\u201349", "subtitle": "Top performer ages 45\u201349", "name": "Iveth Bogota", "detail": "Age 48, overall 54th percentile", "stats": {"wod1": 40.7, "wod2": 28.2, "wod3": 42.8}}, {"title": "Women's Best 50\u201354", "subtitle": "Top performer ages 50\u201354", "name": "Karla Garibay", "detail": "Age 53, overall 27th percentile", "stats": {"wod1": 53.3, "wod2": 51.6, "wod3": 12.3}}, {"title": "Men's MVP", "subtitle": "Highest overall percentile", "name": "Jose Carlos Gutierrez Garibay", "detail": "Overall 89th percentile \u2014 your gym's top performer", "stats": {"wod1": 87.4, "wod2": 88.4, "wod3": 80.4}}, {"title": "Men's Wildcard", "subtitle": "Biggest swing between workouts", "name": "Omero Gonz\u00e1lez", "detail": "Range: 58 percentile points between best and worst", "stats": {"wod1": 85.4, "wod2": 27.1, "wod3": 32.2}}, {"title": "Men's Best on 26.1", "subtitle": "Top performer on 26.1", "name": "Miguel Angel Tovar Ovalle", "detail": "91th percentile on 26.1", "stats": {"wod1": 91.2, "wod2": 91.2, "wod3": 75.8}}, {"title": "Men's Best on 26.2", "subtitle": "Top performer on 26.2", "name": "Bruno Gonzalez Villalobos", "detail": "92th percentile on 26.2", "stats": {"wod1": 82.5, "wod2": 91.5, "wod3": 81.2}}, {"title": "Men's Best on 26.3", "subtitle": "Top performer on 26.3", "name": "Israel Aldana", "detail": "80th percentile on 26.3", "stats": {"wod1": 64.3, "wod2": 43.1, "wod3": 79.6}}, {"title": "Men's Metronome", "subtitle": "Most consistent across all 3 workouts", "name": "Gustavo Carrillo", "detail": "Volatility: 1.0 \u2014 nearly the same percentile every week", "stats": {"wod1": 36.0, "wod2": 37.3, "wod3": 35.3}}, {"title": "Men's Closer", "subtitle": "Biggest improvement Week 1 \u2192 Week 3", "name": "Gerardo Hernandez", "detail": "Jumped 23 percentile points from 26.1 to 26.3", "stats": {"wod1": 16.9, "wod2": 27.3, "wod3": 39.9}}, {"title": "Men's Best 35\u201339", "subtitle": "Top performer ages 35\u201339", "name": "Jorge Loredo", "detail": "Age 37, overall 84th percentile", "stats": {"wod1": 86.0, "wod2": 79.1, "wod3": 73.5}}, {"title": "Men's Best 40\u201344", "subtitle": "Top performer ages 40\u201344", "name": "Luis Fernando Napoleon Napoles Casta\u00f1eda", "detail": "Age 40, overall 79th percentile", "stats": {"wod1": 61.5, "wod2": 83.8, "wod3": 78.2}}, {"title": "Men's Best 45\u201349", "subtitle": "Top performer ages 45\u201349", "name": "Alonso Careaga", "detail": "Age 46, overall 42th percentile", "stats": {"wod1": 29.2, "wod2": 39.9, "wod3": 37.1}}], "what_if": [{"name": "Paloma Escandon", "actual_pct": 44.1, "best_pct": 82.8, "potential_gain": 38.7, "best_workout": "26.2", "wod1": 13.4, "wod2": 82.8, "wod3": 35.9}, {"name": "Fernanda Cruz", "actual_pct": 51.2, "best_pct": 89.0, "potential_gain": 37.8, "best_workout": "26.2", "wod1": 31.2, "wod2": 89.0, "wod3": 33.5}, {"name": "Omero Gonz\u00e1lez", "actual_pct": 48.2, "best_pct": 85.4, "potential_gain": 37.2, "best_workout": "26.1", "wod1": 85.4, "wod2": 27.1, "wod3": 32.2}, {"name": "Alejandro Garcia", "actual_pct": 54.4, "best_pct": 78.1, "potential_gain": 23.8, "best_workout": "26.3", "wod1": 59.7, "wod2": 25.4, "wod3": 78.1}, {"name": "Barbara Anez", "actual_pct": 39.7, "best_pct": 60.6, "potential_gain": 20.9, "best_workout": "26.2", "wod1": 25.2, "wod2": 60.6, "wod3": 33.2}, {"name": "Ana Paola Orozco Ponce", "actual_pct": 42.9, "best_pct": 62.8, "potential_gain": 19.9, "best_workout": "26.3", "wod1": 17.2, "wod2": 48.7, "wod3": 62.8}, {"name": "Emilia Loredo", "actual_pct": 32.1, "best_pct": 51.6, "potential_gain": 19.5, "best_workout": "26.3", "wod1": 18.1, "wod2": 26.6, "wod3": 51.6}, {"name": "Gabriela Sanchez Lopez", "actual_pct": 50.3, "best_pct": 69.0, "potential_gain": 18.7, "best_workout": "26.1", "wod1": 69.0, "wod2": 57.4, "wod3": 24.6}, {"name": "Israel Aldana", "actual_pct": 62.3, "best_pct": 79.6, "potential_gain": 17.3, "best_workout": "26.3", "wod1": 64.3, "wod2": 43.1, "wod3": 79.6}, {"name": "Eliana Cardozo", "actual_pct": 50.6, "best_pct": 66.7, "potential_gain": 16.1, "best_workout": "26.2", "wod1": 36.7, "wod2": 66.7, "wod3": 48.4}], "consistency": {"gym_median_vol": 9.62, "gym_mean_vol": 12.11, "global_median_vol": 9.4, "global_mean_vol": 11.47, "athletes": [{"name": "Gustavo Carrillo", "vol": 1.02, "range": 2.0, "wod1": 36.0, "wod2": 37.3, "wod3": 35.3}, {"name": "David Casillas", "vol": 2.83, "range": 5.5, "wod1": 35.1, "wod2": 39.2, "wod3": 40.6}, {"name": "Graciela Canzonetta", "vol": 3.38, "range": 6.8, "wod1": 91.3, "wod2": 84.6, "wod3": 88.0}, {"name": "Diego Gonzalez Figueroa", "vol": 4.3, "range": 8.3, "wod1": 59.2, "wod2": 50.9, "wod3": 57.1}, {"name": "Jose Carlos Gutierrez Garibay", "vol": 4.38, "range": 8.1, "wod1": 87.4, "wod2": 88.4, "wod3": 80.4}, {"name": "Laura Assis Iragorri", "vol": 4.6, "range": 8.6, "wod1": 32.5, "wod2": 23.9, "wod3": 25.3}, {"name": "Kim Mejia", "vol": 5.24, "range": 10.3, "wod1": 27.2, "wod2": 23.8, "wod3": 16.9}, {"name": "Alonso Careaga", "vol": 5.54, "range": 10.7, "wod1": 29.2, "wod2": 39.9, "wod3": 37.1}, {"name": "Bruno Gonzalez Villalobos", "vol": 5.63, "range": 10.4, "wod1": 82.5, "wod2": 91.5, "wod3": 81.2}, {"name": "Rogelio Espinosa", "vol": 6.0, "range": 10.9, "wod1": 5.9, "wod2": 15.7, "wod3": 16.8}, {"name": "Diego Echeverria", "vol": 6.02, "range": 11.2, "wod1": 7.7, "wod2": 17.1, "wod3": 19.0}, {"name": "Jorge Loredo", "vol": 6.28, "range": 12.5, "wod1": 86.0, "wod2": 79.1, "wod3": 73.5}, {"name": "Adriana Arely Minero", "vol": 7.67, "range": 14.7, "wod1": 7.0, "wod2": 21.6, "wod3": 18.1}, {"name": "Liliana Torres", "vol": 7.8, "range": 14.0, "wod1": 9.5, "wod2": 23.6, "wod3": 22.5}, {"name": "Iveth Bogota", "vol": 7.92, "range": 14.6, "wod1": 40.7, "wod2": 28.2, "wod3": 42.8}, {"name": "Ricardo Cajal", "vol": 7.99, "range": 14.1, "wod1": 55.2, "wod2": 68.7, "wod3": 69.3}, {"name": "Juan Carlos Villarreal", "vol": 8.08, "range": 15.9, "wod1": 16.4, "wod2": 22.1, "wod3": 32.3}, {"name": "Armando Maita", "vol": 8.08, "range": 15.9, "wod1": 12.6, "wod2": 23.1, "wod3": 28.5}, {"name": "Gabriela Schlam", "vol": 8.5, "range": 16.9, "wod1": 8.8, "wod2": 25.7, "wod3": 18.8}, {"name": "Miguel Angel Tovar Ovalle", "vol": 8.91, "range": 15.4, "wod1": 91.2, "wod2": 91.2, "wod3": 75.8}, {"name": "Anaya Atlan", "vol": 8.99, "range": 18.0, "wod1": 5.5, "wod2": 23.5, "wod3": 13.6}, {"name": "Eduardo Negrete", "vol": 9.17, "range": 17.4, "wod1": 40.3, "wod2": 36.5, "wod3": 22.9}, {"name": "Karol Cueto", "vol": 10.06, "range": 17.7, "wod1": 6.5, "wod2": 23.7, "wod3": 24.2}, {"name": "Francisco Granados", "vol": 10.18, "range": 19.2, "wod1": 34.1, "wod2": 49.6, "wod3": 53.3}, {"name": "Mariana Jacob", "vol": 10.38, "range": 20.6, "wod1": 75.3, "wod2": 66.9, "wod3": 87.5}, {"name": "Ana Sofia Trejo", "vol": 11.25, "range": 20.5, "wod1": 24.0, "wod2": 42.3, "wod3": 44.5}, {"name": "Gerardo Hernandez", "vol": 11.52, "range": 23.0, "wod1": 16.9, "wod2": 27.3, "wod3": 39.9}, {"name": "Luis Fernando Napoleon Napoles Casta\u00f1eda", "vol": 11.61, "range": 22.3, "wod1": 61.5, "wod2": 83.8, "wod3": 78.2}, {"name": "Daniela Valverde", "vol": 12.02, "range": 23.0, "wod1": 4.1, "wod2": 21.6, "wod3": 27.1}, {"name": "Ver\u00f3nica Genis", "vol": 12.05, "range": 23.9, "wod1": 80.8, "wod2": 65.9, "wod3": 89.8}, {"name": "Marcos Daniel Escamilla Gochar", "vol": 12.53, "range": 24.9, "wod1": 13.3, "wod2": 38.2, "wod3": 23.0}, {"name": "Paola Corona", "vol": 13.2, "range": 26.0, "wod1": 63.9, "wod2": 55.0, "wod3": 37.9}, {"name": "Itzel Vazquez Alvarez", "vol": 13.33, "range": 26.3, "wod1": 58.3, "wod2": 67.7, "wod3": 84.6}, {"name": "Eliana Cardozo", "vol": 15.13, "range": 30.0, "wod1": 36.7, "wod2": 66.7, "wod3": 48.4}, {"name": "Emilia Loredo", "vol": 17.4, "range": 33.5, "wod1": 18.1, "wod2": 26.6, "wod3": 51.6}, {"name": "Israel Aldana", "vol": 18.36, "range": 36.6, "wod1": 64.3, "wod2": 43.1, "wod3": 79.6}, {"name": "Barbara Anez", "vol": 18.56, "range": 35.4, "wod1": 25.2, "wod2": 60.6, "wod3": 33.2}, {"name": "Gabriela Sanchez Lopez", "vol": 23.06, "range": 44.5, "wod1": 69.0, "wod2": 57.4, "wod3": 24.6}, {"name": "Karla Garibay", "vol": 23.18, "range": 41.0, "wod1": 53.3, "wod2": 51.6, "wod3": 12.3}, {"name": "Ana Paola Orozco Ponce", "vol": 23.34, "range": 45.6, "wod1": 17.2, "wod2": 48.7, "wod3": 62.8}, {"name": "Alejandro Garcia", "vol": 26.78, "range": 52.8, "wod1": 59.7, "wod2": 25.4, "wod3": 78.1}, {"name": "Omero Gonz\u00e1lez", "vol": 32.29, "range": 58.3, "wod1": 85.4, "wod2": 27.1, "wod3": 32.2}, {"name": "Fernanda Cruz", "vol": 32.73, "range": 57.8, "wod1": 31.2, "wod2": 89.0, "wod3": 33.5}, {"name": "Paloma Escandon", "vol": 35.39, "range": 69.4, "wod1": 13.4, "wod2": 82.8, "wod3": 35.9}], "global_hist": [3734, 5998, 8092, 10240, 11685, 12327, 11755, 11584, 11276, 10510, 9754, 8837, 7656, 6439, 5889, 5059, 4281, 3720, 3238, 2856, 2360, 2050, 1734, 1519, 1338, 1268, 1068, 1043, 923, 811, 760, 682, 645, 587, 570, 536, 500, 490, 455], "global_edges": [0.0, 1.0256410256410255, 2.051282051282051, 3.0769230769230766, 4.102564102564102, 5.128205128205128, 6.153846153846153, 7.179487179487179, 8.205128205128204, 9.23076923076923, 10.256410256410255, 11.282051282051281, 12.307692307692307, 13.333333333333332, 14.358974358974358, 15.384615384615383, 16.41025641025641, 17.435897435897434, 18.46153846153846, 19.487179487179485, 20.51282051282051, 21.538461538461537, 22.564102564102562, 23.589743589743588, 24.615384615384613, 25.64102564102564, 26.666666666666664, 27.69230769230769, 28.717948717948715, 29.74358974358974, 30.769230769230766, 31.794871794871792, 32.82051282051282, 33.84615384615384, 34.87179487179487, 35.8974358974359, 36.92307692307692, 37.94871794871794, 38.97435897435897, 40.0]}, "demographics": {"gym_median_age": 36, "global_median_age": 36, "gym_men": 39, "gym_women": 40, "gym_men_pct": 49.4, "global_men_pct": 54.1, "age_bins": [17.5, 22.5, 27.5, 32.5, 37.5, 42.5, 47.5, 52.5, 57.5, 62.5], "gym_age_pct": [3.8, 7.6, 16.5, 17.7, 21.5, 13.9, 13.9, 5.1, 0.0, 0.0], "global_age_pct": [1.9, 4.9, 14.6, 22.2, 22.2, 16.8, 11.2, 6.3, 0.0, 0.0]}, "athletes": [{"name": "Miguel Angel Tovar Ovalle", "division": "men_scaled", "overall_rank": 313, "overall_pct": 93.7, "wod1_pct": 97.4, "wod2_pct": 82.8, "wod3_pct": 86.3, "wod1_reps": 258, "wod2_reps": 132, "wod3_reps": 184, "archetype": "Engine", "volatility": 7.7, "age": 40, "wrapped": {"persona": "The Natural", "headline": "The Natural", "tagline": "First Open. Top 89%. Explain yourself.", "best_workout": "26.1", "best_pct": 97.4, "worst_workout": "26.2", "worst_pct": 82.8, "spread": 14.7, "gym_rank": 1, "gym_total": 79, "award": "Men's Best on 26.1"}, "num_opens": 1}, {"name": "Alejandro Garcia", "division": "men_scaled", "overall_rank": 2094, "overall_pct": 58.1, "wod1_pct": 70.9, "wod2_pct": 11.3, "wod3_pct": 88.5, "wod1_reps": 210, "wod2_reps": 90, "wod3_reps": 186, "archetype": "Barbell", "volatility": 40.5, "age": 45, "wrapped": {"persona": "The Comeback Kid", "headline": "The Comeback Kid", "tagline": "You gained 18 percentile points from Week 1 to Week 3. Peaked when it mattered.", "best_workout": "26.3", "best_pct": 88.5, "worst_workout": "26.2", "worst_pct": 11.3, "spread": 77.2, "gym_rank": 2, "gym_total": 79, "award": null}, "height_in": 66, "weight_lb": 176, "num_opens": 6}, {"name": "Francisco Granados", "division": "men_scaled", "overall_rank": 2499, "overall_pct": 50.0, "wod1_pct": 32.6, "wod2_pct": 34.0, "wod3_pct": 57.1, "wod1_reps": 178, "wod2_reps": 112, "wod3_reps": 160, "archetype": "Barbell", "volatility": 13.8, "age": 48, "wrapped": {"persona": "The Comeback Kid", "headline": "The Comeback Kid", "tagline": "You gained 25 percentile points from Week 1 to Week 3. Peaked when it mattered.", "best_workout": "26.3", "best_pct": 57.1, "worst_workout": "26.1", "worst_pct": 32.6, "spread": 24.5, "gym_rank": 3, "gym_total": 79, "award": null}, "num_opens": 1}, {"name": "Eduardo Negrete", "division": "men_scaled", "overall_rank": 3858, "overall_pct": 22.8, "wod1_pct": 42.9, "wod2_pct": 26.0, "wod3_pct": 12.7, "wod1_reps": 185, "wod2_reps": 112, "wod3_reps": 128, "archetype": "Engine", "volatility": 15.1, "age": 41, "wrapped": {"persona": "The Ageless", "headline": "The Ageless", "tagline": "Age 41. Still making 25-year-olds nervous.", "best_workout": "26.1", "best_pct": 42.9, "worst_workout": "26.3", "worst_pct": 12.7, "spread": 30.2, "gym_rank": 4, "gym_total": 79, "award": null}, "num_opens": 1}, {"name": "Eliana Cardozo", "division": "women_scaled", "overall_rank": 3904, "overall_pct": 21.9, "wod1_pct": 11.0, "wod2_pct": 45.7, "wod3_pct": 20.0, "wod1_reps": 172, "wod2_reps": 112, "wod3_reps": 152, "archetype": "Gymnast", "volatility": 18.0, "age": 47, "wrapped": {"persona": "The Ageless", "headline": "The Ageless", "tagline": "Age 47. Still making 25-year-olds nervous.", "best_workout": "26.2", "best_pct": 45.7, "worst_workout": "26.1", "worst_pct": 11.0, "spread": 34.8, "gym_rank": 5, "gym_total": 79, "award": null}, "num_opens": 2}, {"name": "Graciela Canzonetta", "division": "women_rx", "overall_rank": 6707, "overall_pct": 93.2, "wod1_pct": 91.3, "wod2_pct": 84.6, "wod3_pct": 88.0, "wod1_reps": 254, "wod2_reps": 118, "wod3_reps": 204, "archetype": "Engine", "volatility": 3.4, "age": 44, "wrapped": {"persona": "The Metronome", "headline": "The Metronome", "tagline": "You don't have peaks and valleys. You have a flatline of excellence.", "best_workout": "26.1", "best_pct": 91.3, "worst_workout": "26.2", "worst_pct": 84.6, "spread": 6.8, "gym_rank": 6, "gym_total": 79, "award": "Women's MVP"}, "num_opens": 5}, {"name": "Jose Carlos Gutierrez Garibay", "division": "men_rx", "overall_rank": 12661, "overall_pct": 89.3, "wod1_pct": 87.4, "wod2_pct": 88.4, "wod3_pct": 80.4, "wod1_reps": 249, "wod2_reps": 180, "wod3_reps": 189, "archetype": "Gymnast", "volatility": 4.4, "age": 23, "wrapped": {"persona": "The Natural", "headline": "The Natural", "tagline": "First Open. Top 85%. Explain yourself.", "best_workout": "26.2", "best_pct": 88.4, "worst_workout": "26.3", "worst_pct": 80.4, "spread": 8.1, "gym_rank": 7, "gym_total": 79, "award": "Men's MVP"}, "height_in": 71, "weight_lb": 196, "num_opens": 6}, {"name": "Bruno Gonzalez Villalobos", "division": "men_rx", "overall_rank": 13322, "overall_pct": 88.7, "wod1_pct": 82.5, "wod2_pct": 91.5, "wod3_pct": 81.2, "wod1_reps": 240, "wod2_reps": 180, "wod3_reps": 190, "archetype": "Gymnast", "volatility": 5.6, "age": 25, "wrapped": {"persona": "The Natural", "headline": "The Natural", "tagline": "First Open. Top 85%. Explain yourself.", "best_workout": "26.2", "best_pct": 91.5, "worst_workout": "26.3", "worst_pct": 81.2, "spread": 10.4, "gym_rank": 8, "gym_total": 79, "award": "Men's Best on 26.2"}, "num_opens": 2}, {"name": "Ver\u00f3nica Genis", "division": "women_rx", "overall_rank": 14252, "overall_pct": 85.6, "wod1_pct": 80.8, "wod2_pct": 65.9, "wod3_pct": 89.8, "wod1_reps": 231, "wod2_reps": 112, "wod3_reps": 205, "archetype": "Barbell", "volatility": 12.1, "age": 43, "wrapped": {"persona": "The Natural", "headline": "The Natural", "tagline": "First Open. Top 79%. Explain yourself.", "best_workout": "26.3", "best_pct": 89.8, "worst_workout": "26.2", "worst_pct": 65.9, "spread": 23.9, "gym_rank": 9, "gym_total": 79, "award": "Women's Best on 26.1"}, "height_in": 61, "num_opens": 2}, {"name": "Mariana Jacob", "division": "women_rx", "overall_rank": 16057, "overall_pct": 83.8, "wod1_pct": 75.3, "wod2_pct": 66.9, "wod3_pct": 87.5, "wod1_reps": 221, "wod2_reps": 112, "wod3_reps": 204, "archetype": "Barbell", "volatility": 10.4, "age": 38, "wrapped": {"persona": "The Natural", "headline": "The Natural", "tagline": "First Open. Top 77%. Explain yourself.", "best_workout": "26.3", "best_pct": 87.5, "worst_workout": "26.2", "worst_pct": 66.9, "spread": 20.6, "gym_rank": 10, "gym_total": 79, "award": "Women's Best on 26.3"}, "num_opens": 1}, {"name": "Jorge Loredo", "division": "men_rx", "overall_rank": 18609, "overall_pct": 84.2, "wod1_pct": 86.0, "wod2_pct": 79.1, "wod3_pct": 73.5, "wod1_reps": 246, "wod2_reps": 123, "wod3_reps": 182, "archetype": "Engine", "volatility": 6.3, "age": 37, "wrapped": {"persona": "The Natural", "headline": "The Natural", "tagline": "First Open. Top 80%. Explain yourself.", "best_workout": "26.1", "best_pct": 86.0, "worst_workout": "26.3", "worst_pct": 73.5, "spread": 12.5, "gym_rank": 11, "gym_total": 79, "award": "Men's Best 35\u201339"}, "height_in": 74, "weight_lb": 201, "num_opens": 7}, {"name": "Itzel Vazquez Alvarez", "division": "women_rx", "overall_rank": 20824, "overall_pct": 79.0, "wod1_pct": 58.3, "wod2_pct": 67.7, "wod3_pct": 84.6, "wod1_reps": 198, "wod2_reps": 112, "wod3_reps": 198, "archetype": "Barbell", "volatility": 13.3, "age": 36, "wrapped": {"persona": "The Comeback Kid", "headline": "The Comeback Kid", "tagline": "You gained 26 percentile points from Week 1 to Week 3. Peaked when it mattered.", "best_workout": "26.3", "best_pct": 84.6, "worst_workout": "26.1", "worst_pct": 58.3, "spread": 26.3, "gym_rank": 12, "gym_total": 79, "award": "Women's Best 35\u201339"}, "num_opens": 1}, {"name": "Luis Fernando Napoleon Napoles Casta\u00f1eda", "division": "men_rx", "overall_rank": 24516, "overall_pct": 79.2, "wod1_pct": 61.5, "wod2_pct": 83.8, "wod3_pct": 78.2, "wod1_reps": 211, "wod2_reps": 128, "wod3_reps": 187, "archetype": "Gymnast", "volatility": 11.6, "age": 40, "wrapped": {"persona": "The Comeback Kid", "headline": "The Comeback Kid", "tagline": "You gained 17 percentile points from Week 1 to Week 3. Peaked when it mattered.", "best_workout": "26.2", "best_pct": 83.8, "worst_workout": "26.1", "worst_pct": 61.5, "spread": 22.3, "gym_rank": 13, "gym_total": 79, "award": "Men's Best 40\u201344"}, "height_in": 67, "weight_lb": 187, "num_opens": 2}, {"name": "Paola Corona", "division": "women_rx", "overall_rank": 34387, "overall_pct": 65.3, "wod1_pct": 63.9, "wod2_pct": 55.0, "wod3_pct": 37.9, "wod1_reps": 205, "wod2_reps": 112, "wod3_reps": 140, "archetype": "Engine", "volatility": 13.2, "age": 20, "wrapped": {"persona": "The Origin Story", "headline": "The Origin Story", "tagline": "Every great athlete has a Chapter 1. This is yours.", "best_workout": "26.1", "best_pct": 63.9, "worst_workout": "26.3", "worst_pct": 37.9, "spread": 26.0, "gym_rank": 14, "gym_total": 79, "award": null}, "num_opens": 1}, {"name": "Gabriela Sanchez Lopez", "division": "women_rx", "overall_rank": 35647, "overall_pct": 64.0, "wod1_pct": 69.0, "wod2_pct": 57.4, "wod3_pct": 24.6, "wod1_reps": 212, "wod2_reps": 112, "wod3_reps": 130, "archetype": "Engine", "volatility": 23.1, "age": 22, "wrapped": {"persona": "The Origin Story", "headline": "The Origin Story", "tagline": "Every great athlete has a Chapter 1. This is yours.", "best_workout": "26.1", "best_pct": 69.0, "worst_workout": "26.3", "worst_pct": 24.6, "spread": 44.5, "gym_rank": 15, "gym_total": 79, "award": null}, "num_opens": 1}, {"name": "Ricardo Cajal", "division": "men_rx", "overall_rank": 36094, "overall_pct": 69.4, "wod1_pct": 55.2, "wod2_pct": 68.7, "wod3_pct": 69.3, "wod1_reps": 203, "wod2_reps": 116, "wod3_reps": 180, "archetype": "Barbell", "volatility": 8.0, "age": 38, "wrapped": {"persona": "The Natural", "headline": "The Natural", "tagline": "First Open. Top 64%. Explain yourself.", "best_workout": "26.3", "best_pct": 69.3, "worst_workout": "26.1", "worst_pct": 55.2, "spread": 14.1, "gym_rank": 16, "gym_total": 79, "award": null}, "height_in": 69, "weight_lb": 183, "num_opens": 7}, {"name": "Israel Aldana", "division": "men_rx", "overall_rank": 38726, "overall_pct": 67.2, "wod1_pct": 64.3, "wod2_pct": 43.1, "wod3_pct": 79.6, "wod1_reps": 214, "wod2_reps": 112, "wod3_reps": 188, "archetype": "Barbell", "volatility": 18.4, "age": 51, "wrapped": {"persona": "The Comeback Kid", "headline": "The Comeback Kid", "tagline": "You gained 15 percentile points from Week 1 to Week 3. Peaked when it mattered.", "best_workout": "26.3", "best_pct": 79.6, "worst_workout": "26.2", "worst_pct": 43.1, "spread": 36.6, "gym_rank": 17, "gym_total": 79, "award": "Men's Best on 26.3"}, "num_opens": 1}, {"name": "Rosibel Cabello", "division": "women_rx", "overall_rank": 44984, "overall_pct": null, "wod1_pct": 65.2, "wod2_pct": 63.2, "wod3_pct": null, "wod1_reps": 208, "wod2_reps": 112, "wod3_reps": 0, "archetype": "Engine", "volatility": 37.1, "age": 37, "wrapped": {"persona": "The Natural", "headline": "The Natural", "tagline": "First Open. Top 64%. Explain yourself.", "best_workout": "26.1", "best_pct": 65.2, "worst_workout": "26.3", "worst_pct": 0.0, "spread": 65.2, "gym_rank": 18, "gym_total": 79, "award": null}, "num_opens": 1}, {"name": "Rebeca Avimelech", "division": "women_rx", "overall_rank": 45790, "overall_pct": null, "wod1_pct": 50.7, "wod2_pct": 72.9, "wod3_pct": null, "wod1_reps": 188, "wod2_reps": 112, "wod3_reps": 0, "archetype": "Gymnast", "volatility": 37.4, "age": 44, "wrapped": {"persona": "The Natural", "headline": "The Natural", "tagline": "First Open. Top 62%. Explain yourself.", "best_workout": "26.2", "best_pct": 72.9, "worst_workout": "26.3", "worst_pct": 0.0, "spread": 72.9, "gym_rank": 19, "gym_total": 79, "award": null}, "num_opens": 1}, {"name": "Iveth Bogota", "division": "women_rx", "overall_rank": 45900, "overall_pct": 53.7, "wod1_pct": 40.7, "wod2_pct": 28.2, "wod3_pct": 42.8, "wod1_reps": 177, "wod2_reps": 69, "wod3_reps": 146, "archetype": "Barbell", "volatility": 7.9, "age": 48, "wrapped": {"persona": "The Ageless", "headline": "The Ageless", "tagline": "Age 48. Still making 25-year-olds nervous.", "best_workout": "26.3", "best_pct": 42.8, "worst_workout": "26.2", "worst_pct": 28.2, "spread": 14.6, "gym_rank": 20, "gym_total": 79, "award": "Women's Best 45\u201349"}, "height_in": 63, "weight_lb": 115, "num_opens": 8}, {"name": "Diego Gonzalez Figueroa", "division": "men_rx", "overall_rank": 46253, "overall_pct": 60.8, "wod1_pct": 59.2, "wod2_pct": 50.9, "wod3_pct": 57.1, "wod1_reps": 210, "wod2_reps": 112, "wod3_reps": 164, "archetype": "Engine", "volatility": 4.3, "age": 33, "wrapped": {"persona": "The Origin Story", "headline": "The Origin Story", "tagline": "Every great athlete has a Chapter 1. This is yours.", "best_workout": "26.1", "best_pct": 59.2, "worst_workout": "26.2", "worst_pct": 50.9, "spread": 8.3, "gym_rank": 21, "gym_total": 79, "award": null}, "num_opens": 1}, {"name": "Marcos Daniel Escamilla Gochar", "division": "women_rx", "overall_rank": 55090, "overall_pct": 44.4, "wod1_pct": 13.3, "wod2_pct": 38.2, "wod3_pct": 23.0, "wod1_reps": 136, "wod2_reps": 84, "wod3_reps": 126, "archetype": "Gymnast", "volatility": 12.5, "age": 30, "wrapped": {"persona": "The Origin Story", "headline": "The Origin Story", "tagline": "Every great athlete has a Chapter 1. This is yours.", "best_workout": "26.2", "best_pct": 38.2, "worst_workout": "26.1", "worst_pct": 13.3, "spread": 24.9, "gym_rank": 22, "gym_total": 79, "award": null}, "num_opens": 1}, {"name": "Fernanda Cruz", "division": "women_rx", "overall_rank": 55166, "overall_pct": 44.3, "wod1_pct": 31.2, "wod2_pct": 89.0, "wod3_pct": 33.5, "wod1_reps": 165, "wod2_reps": 127, "wod3_reps": 137, "archetype": "Gymnast", "volatility": 32.7, "age": 34, "wrapped": {"persona": "The Origin Story", "headline": "The Origin Story", "tagline": "Every great athlete has a Chapter 1. This is yours.", "best_workout": "26.2", "best_pct": 89.0, "worst_workout": "26.1", "worst_pct": 31.2, "spread": 57.8, "gym_rank": 23, "gym_total": 79, "award": "Women's Best on 26.2"}, "num_opens": 1}, {"name": "Xiomara De La Torre", "division": "women_rx", "overall_rank": 56349, "overall_pct": null, "wod1_pct": 36.7, "wod2_pct": 50.3, "wod3_pct": null, "wod1_reps": 172, "wod2_reps": 108, "wod3_reps": 0, "archetype": "Gymnast", "volatility": 26.0, "age": 33, "wrapped": {"persona": "The Origin Story", "headline": "The Origin Story", "tagline": "Every great athlete has a Chapter 1. This is yours.", "best_workout": "26.2", "best_pct": 50.3, "worst_workout": "26.3", "worst_pct": 0.0, "spread": 50.3, "gym_rank": 24, "gym_total": 79, "award": null}, "num_opens": 1}, {"name": "Barbara Anez", "division": "women_rx", "overall_rank": 58410, "overall_pct": 41.1, "wod1_pct": 25.2, "wod2_pct": 60.6, "wod3_pct": 33.2, "wod1_reps": 158, "wod2_reps": 112, "wod3_reps": 137, "archetype": "Gymnast", "volatility": 18.6, "age": 36, "wrapped": {"persona": "The Origin Story", "headline": "The Origin Story", "tagline": "Every great athlete has a Chapter 1. This is yours.", "best_workout": "26.2", "best_pct": 60.6, "worst_workout": "26.1", "worst_pct": 25.2, "spread": 35.4, "gym_rank": 25, "gym_total": 79, "award": null}, "num_opens": 1}, {"name": "Paloma Escandon", "division": "women_rx", "overall_rank": 59233, "overall_pct": 40.2, "wod1_pct": 13.4, "wod2_pct": 82.8, "wod3_pct": 35.9, "wod1_reps": 136, "wod2_reps": 116, "wod3_reps": 139, "archetype": "Gymnast", "volatility": 35.4, "age": 25, "wrapped": {"persona": "The Comeback Kid", "headline": "The Comeback Kid", "tagline": "You gained 22 percentile points from Week 1 to Week 3. Peaked when it mattered.", "best_workout": "26.2", "best_pct": 82.8, "worst_workout": "26.1", "worst_pct": 13.4, "spread": 69.4, "gym_rank": 26, "gym_total": 79, "award": "Women's Wildcard"}, "num_opens": 1}, {"name": "Mauro Tapia", "division": "men_rx", "overall_rank": 63460, "overall_pct": null, "wod1_pct": 50.3, "wod2_pct": 64.2, "wod3_pct": null, "wod1_reps": 197, "wod2_reps": 114, "wod3_reps": 0, "archetype": "Gymnast", "volatility": 33.8, "age": 26, "wrapped": {"persona": "The Origin Story", "headline": "The Origin Story", "tagline": "Every great athlete has a Chapter 1. This is yours.", "best_workout": "26.2", "best_pct": 64.2, "worst_workout": "26.3", "worst_pct": 0.0, "spread": 64.2, "gym_rank": 27, "gym_total": 79, "award": null}, "num_opens": 1}, {"name": "Daniel Sanchez", "division": "men_rx", "overall_rank": 65384, "overall_pct": null, "wod1_pct": 65.2, "wod2_pct": 45.0, "wod3_pct": null, "wod1_reps": 215, "wod2_reps": 112, "wod3_reps": 0, "archetype": "Engine", "volatility": 33.4, "age": 31, "wrapped": {"persona": "The Origin Story", "headline": "The Origin Story", "tagline": "Every great athlete has a Chapter 1. This is yours.", "best_workout": "26.1", "best_pct": 65.2, "worst_workout": "26.3", "worst_pct": 0.0, "spread": 65.2, "gym_rank": 28, "gym_total": 79, "award": null}, "height_in": 73, "weight_lb": 250, "num_opens": 8}, {"name": "David Casillas", "division": "men_rx", "overall_rank": 65610, "overall_pct": 44.4, "wod1_pct": 35.1, "wod2_pct": 39.2, "wod3_pct": 40.6, "wod1_reps": 179, "wod2_reps": 112, "wod3_reps": 144, "archetype": "Barbell", "volatility": 2.8, "age": 38, "wrapped": {"persona": "The Origin Story", "headline": "The Origin Story", "tagline": "Every great athlete has a Chapter 1. This is yours.", "best_workout": "26.3", "best_pct": 40.6, "worst_workout": "26.1", "worst_pct": 35.1, "spread": 5.5, "gym_rank": 29, "gym_total": 79, "award": null}, "num_opens": 3}, {"name": "Sheila Leyva", "division": "women_rx", "overall_rank": 65728, "overall_pct": null, "wod1_pct": 78.1, "wod2_pct": null, "wod3_pct": null, "wod1_reps": 226, "wod2_reps": 0, "wod3_reps": 0, "archetype": "Engine", "volatility": 45.1, "age": 28, "wrapped": {"persona": "The Natural", "headline": "The Natural", "tagline": "First Open. Top 78%. Explain yourself.", "best_workout": "26.1", "best_pct": 78.1, "worst_workout": "26.2", "worst_pct": 0.0, "spread": 78.1, "gym_rank": 30, "gym_total": 79, "award": null}, "num_opens": 1}, {"name": "Jose Maria Guerra", "division": "men_rx", "overall_rank": 66081, "overall_pct": null, "wod1_pct": null, "wod2_pct": 70.0, "wod3_pct": 48.3, "wod1_reps": 0, "wod2_reps": 117, "wod3_reps": 155, "archetype": "Gymnast", "volatility": 35.8, "age": 38, "wrapped": {"persona": "The Origin Story", "headline": "The Origin Story", "tagline": "Every great athlete has a Chapter 1. This is yours.", "best_workout": "26.2", "best_pct": 70.0, "worst_workout": "26.1", "worst_pct": 0.0, "spread": 70.0, "gym_rank": 31, "gym_total": 79, "award": null}, "num_opens": 1}, {"name": "Gustavo Carrillo", "division": "men_rx", "overall_rank": 67834, "overall_pct": 42.5, "wod1_pct": 36.0, "wod2_pct": 37.3, "wod3_pct": 35.3, "wod1_reps": 180, "wod2_reps": 112, "wod3_reps": 139, "archetype": "Gymnast", "volatility": 1.0, "age": 33, "wrapped": {"persona": "The Origin Story", "headline": "The Origin Story", "tagline": "Every great athlete has a Chapter 1. This is yours.", "best_workout": "26.2", "best_pct": 37.3, "worst_workout": "26.3", "worst_pct": 35.3, "spread": 2.0, "gym_rank": 32, "gym_total": 79, "award": "Men's Metronome"}, "num_opens": 1}, {"name": "Ana Paola Orozco Ponce", "division": "women_rx", "overall_rank": 68122, "overall_pct": 31.3, "wod1_pct": 17.2, "wod2_pct": 48.7, "wod3_pct": 62.8, "wod1_reps": 145, "wod2_reps": 102, "wod3_reps": 171, "archetype": "Barbell", "volatility": 23.3, "age": 48, "wrapped": {"persona": "The Comeback Kid", "headline": "The Comeback Kid", "tagline": "You gained 46 percentile points from Week 1 to Week 3. Peaked when it mattered.", "best_workout": "26.3", "best_pct": 62.8, "worst_workout": "26.1", "worst_pct": 17.2, "spread": 45.6, "gym_rank": 33, "gym_total": 79, "award": "Women's Closer"}, "num_opens": 1}, {"name": "Alonso Careaga", "division": "men_rx", "overall_rank": 68738, "overall_pct": 41.7, "wod1_pct": 29.2, "wod2_pct": 39.9, "wod3_pct": 37.1, "wod1_reps": 171, "wod2_reps": 112, "wod3_reps": 140, "archetype": "Gymnast", "volatility": 5.5, "age": 46, "wrapped": {"persona": "The Ageless", "headline": "The Ageless", "tagline": "Age 46. Still making 25-year-olds nervous.", "best_workout": "26.2", "best_pct": 39.9, "worst_workout": "26.1", "worst_pct": 29.2, "spread": 10.7, "gym_rank": 34, "gym_total": 79, "award": "Men's Best 45\u201349"}, "num_opens": 1}, {"name": "Brenda Barrangan", "division": "women_rx", "overall_rank": 70421, "overall_pct": null, "wod1_pct": 63.2, "wod2_pct": null, "wod3_pct": null, "wod1_reps": 204, "wod2_reps": 0, "wod3_reps": 0, "archetype": "Engine", "volatility": 36.5, "age": 35, "wrapped": {"persona": "The Natural", "headline": "The Natural", "tagline": "First Open. Top 63%. Explain yourself.", "best_workout": "26.1", "best_pct": 63.2, "worst_workout": "26.2", "worst_pct": 0.0, "spread": 63.2, "gym_rank": 35, "gym_total": 79, "award": null}, "num_opens": 1}, {"name": "Emilia Loredo", "division": "women_rx", "overall_rank": 71677, "overall_pct": 27.7, "wod1_pct": 18.1, "wod2_pct": 26.6, "wod3_pct": 51.6, "wod1_reps": 147, "wod2_reps": 68, "wod3_reps": 156, "archetype": "Barbell", "volatility": 17.4, "age": 34, "wrapped": {"persona": "The Comeback Kid", "headline": "The Comeback Kid", "tagline": "You gained 33 percentile points from Week 1 to Week 3. Peaked when it mattered.", "best_workout": "26.3", "best_pct": 51.6, "worst_workout": "26.1", "worst_pct": 18.1, "spread": 33.5, "gym_rank": 36, "gym_total": 79, "award": null}, "num_opens": 1}, {"name": "Karla Garibay", "division": "women_rx", "overall_rank": 72666, "overall_pct": 26.7, "wod1_pct": 53.3, "wod2_pct": 51.6, "wod3_pct": 12.3, "wod1_reps": 191, "wod2_reps": 112, "wod3_reps": 36, "archetype": "Engine", "volatility": 23.2, "age": 53, "wrapped": {"persona": "The Ageless", "headline": "The Ageless", "tagline": "Age 53. Still making 25-year-olds nervous.", "best_workout": "26.1", "best_pct": 53.3, "worst_workout": "26.3", "worst_pct": 12.3, "spread": 41.0, "gym_rank": 37, "gym_total": 79, "award": "Women's Best 50\u201354"}, "num_opens": 1}, {"name": "Allison Salas", "division": "women_rx", "overall_rank": 73919, "overall_pct": null, "wod1_pct": 12.4, "wod2_pct": null, "wod3_pct": 21.9, "wod1_reps": 134, "wod2_reps": 0, "wod3_reps": 124, "archetype": "Barbell", "volatility": 11.0, "age": 25, "wrapped": {"persona": "The Wolf", "headline": "The Wolf", "tagline": "Part of the pack. Stronger because of it.", "best_workout": "26.3", "best_pct": 21.9, "worst_workout": "26.2", "worst_pct": 0.0, "spread": 21.9, "gym_rank": 38, "gym_total": 79, "award": null}, "height_in": 64, "num_opens": 1}, {"name": "Irwin Cohen", "division": "men_rx", "overall_rank": 74158, "overall_pct": null, "wod1_pct": 12.8, "wod2_pct": 72.7, "wod3_pct": null, "wod1_reps": 145, "wod2_reps": 119, "wod3_reps": 0, "archetype": "Gymnast", "volatility": 38.8, "age": 16, "wrapped": {"persona": "The Origin Story", "headline": "The Origin Story", "tagline": "Every great athlete has a Chapter 1. This is yours.", "best_workout": "26.2", "best_pct": 72.7, "worst_workout": "26.3", "worst_pct": 0.0, "spread": 72.7, "gym_rank": 39, "gym_total": 79, "award": null}, "num_opens": 1}, {"name": "Gerardo Hernandez", "division": "men_rx", "overall_rank": 77009, "overall_pct": 34.7, "wod1_pct": 16.9, "wod2_pct": 27.3, "wod3_pct": 39.9, "wod1_reps": 153, "wod2_reps": 91, "wod3_reps": 143, "archetype": "Barbell", "volatility": 11.5, "age": 31, "wrapped": {"persona": "The Comeback Kid", "headline": "The Comeback Kid", "tagline": "You gained 23 percentile points from Week 1 to Week 3. Peaked when it mattered.", "best_workout": "26.3", "best_pct": 39.9, "worst_workout": "26.1", "worst_pct": 16.9, "spread": 23.0, "gym_rank": 40, "gym_total": 79, "award": "Men's Closer"}, "num_opens": 1}, {"name": "Eliana Cardozo", "division": "women_rx", "overall_rank": 77138, "overall_pct": 22.2, "wod1_pct": 36.7, "wod2_pct": 66.7, "wod3_pct": 48.4, "wod1_reps": 172, "wod2_reps": 112, "wod3_reps": 152, "archetype": "Gymnast", "volatility": 15.1, "age": 47, "wrapped": {"persona": "The Slow Burn", "headline": "The Slow Burn", "tagline": "Started quiet. Finished loud.", "best_workout": "26.2", "best_pct": 66.7, "worst_workout": "26.1", "worst_pct": 36.7, "spread": 30.0, "gym_rank": 41, "gym_total": 79, "award": null}, "num_opens": 2}, {"name": "Kim Mejia", "division": "women_rx", "overall_rank": 78954, "overall_pct": 20.3, "wod1_pct": 27.2, "wod2_pct": 23.8, "wod3_pct": 16.9, "wod1_reps": 160, "wod2_reps": 68, "wod3_reps": 110, "archetype": "Engine", "volatility": 5.2, "age": 28, "wrapped": {"persona": "The Origin Story", "headline": "The Origin Story", "tagline": "Every great athlete has a Chapter 1. This is yours.", "best_workout": "26.1", "best_pct": 27.2, "worst_workout": "26.3", "worst_pct": 16.9, "spread": 10.3, "gym_rank": 42, "gym_total": 79, "award": null}, "num_opens": 1}, {"name": "Anaya Atlan", "division": "women_rx", "overall_rank": 81107, "overall_pct": 18.2, "wod1_pct": 5.5, "wod2_pct": 23.5, "wod3_pct": 13.6, "wod1_reps": 102, "wod2_reps": 68, "wod3_reps": 92, "archetype": "Gymnast", "volatility": 9.0, "age": 21, "wrapped": {"persona": "The Wolf", "headline": "The Wolf", "tagline": "Part of the pack. Stronger because of it.", "best_workout": "26.2", "best_pct": 23.5, "worst_workout": "26.1", "worst_pct": 5.5, "spread": 18.0, "gym_rank": 43, "gym_total": 79, "award": null}, "num_opens": 1}, {"name": "Ana Sofia Trejo", "division": "women_rx", "overall_rank": 81640, "overall_pct": 17.6, "wod1_pct": 24.0, "wod2_pct": 42.3, "wod3_pct": 44.5, "wod1_reps": 156, "wod2_reps": 89, "wod3_reps": 148, "archetype": "Barbell", "volatility": 11.3, "age": 26, "wrapped": {"persona": "The Comeback Kid", "headline": "The Comeback Kid", "tagline": "You gained 20 percentile points from Week 1 to Week 3. Peaked when it mattered.", "best_workout": "26.3", "best_pct": 44.5, "worst_workout": "26.1", "worst_pct": 24.0, "spread": 20.5, "gym_rank": 44, "gym_total": 79, "award": null}, "num_opens": 1}, {"name": "Daniel montiel", "division": "men_rx", "overall_rank": 81673, "overall_pct": null, "wod1_pct": 45.3, "wod2_pct": 24.2, "wod3_pct": null, "wod1_reps": 191, "wod2_reps": 90, "wod3_reps": 0, "archetype": "Engine", "volatility": 22.7, "age": 36, "wrapped": {"persona": "The Origin Story", "headline": "The Origin Story", "tagline": "Every great athlete has a Chapter 1. This is yours.", "best_workout": "26.1", "best_pct": 45.3, "worst_workout": "26.3", "worst_pct": 0.0, "spread": 45.3, "gym_rank": 45, "gym_total": 79, "award": null}, "num_opens": 1}, {"name": "Juan Carlos Villarreal", "division": "men_rx", "overall_rank": 82432, "overall_pct": 30.1, "wod1_pct": 16.4, "wod2_pct": 22.1, "wod3_pct": 32.3, "wod1_reps": 152, "wod2_reps": 89, "wod3_reps": 137, "archetype": "Barbell", "volatility": 8.1, "age": 38, "wrapped": {"persona": "The Comeback Kid", "headline": "The Comeback Kid", "tagline": "You gained 16 percentile points from Week 1 to Week 3. Peaked when it mattered.", "best_workout": "26.3", "best_pct": 32.3, "worst_workout": "26.1", "worst_pct": 16.4, "spread": 15.9, "gym_rank": 46, "gym_total": 79, "award": null}, "num_opens": 1}, {"name": "Juan Echeverria", "division": "men_rx", "overall_rank": 83252, "overall_pct": null, "wod1_pct": 35.6, "wod2_pct": null, "wod3_pct": 38.8, "wod1_reps": 180, "wod2_reps": 0, "wod3_reps": 142, "archetype": "Barbell", "volatility": 21.5, "age": 38, "wrapped": {"persona": "The Origin Story", "headline": "The Origin Story", "tagline": "Every great athlete has a Chapter 1. This is yours.", "best_workout": "26.3", "best_pct": 38.8, "worst_workout": "26.2", "worst_pct": 0.0, "spread": 38.8, "gym_rank": 47, "gym_total": 79, "award": null}, "num_opens": 1}, {"name": "Armando Maita", "division": "men_rx", "overall_rank": 85161, "overall_pct": 27.8, "wod1_pct": 12.6, "wod2_pct": 23.1, "wod3_pct": 28.5, "wod1_reps": 144, "wod2_reps": 89, "wod3_reps": 134, "archetype": "Barbell", "volatility": 8.1, "age": 43, "wrapped": {"persona": "The Comeback Kid", "headline": "The Comeback Kid", "tagline": "You gained 16 percentile points from Week 1 to Week 3. Peaked when it mattered.", "best_workout": "26.3", "best_pct": 28.5, "worst_workout": "26.1", "worst_pct": 12.6, "spread": 15.9, "gym_rank": 48, "gym_total": 79, "award": null}, "num_opens": 1}, {"name": "Omero Gonz\u00e1lez", "division": "men_rx", "overall_rank": 85694, "overall_pct": 27.3, "wod1_pct": 85.4, "wod2_pct": 27.1, "wod3_pct": 32.2, "wod1_reps": 245, "wod2_reps": 91, "wod3_reps": 137, "archetype": "Engine", "volatility": 32.3, "age": 35, "wrapped": {"persona": "The Origin Story", "headline": "The Origin Story", "tagline": "Every great athlete has a Chapter 1. This is yours.", "best_workout": "26.1", "best_pct": 85.4, "worst_workout": "26.2", "worst_pct": 27.1, "spread": 58.3, "gym_rank": 49, "gym_total": 79, "award": "Men's Wildcard"}, "num_opens": 1}, {"name": "Laura Assis Iragorri", "division": "women_rx", "overall_rank": 86242, "overall_pct": 13.0, "wod1_pct": 32.5, "wod2_pct": 23.9, "wod3_pct": 25.3, "wod1_reps": 167, "wod2_reps": 68, "wod3_reps": 131, "archetype": "Engine", "volatility": 4.6, "age": 29, "wrapped": {"persona": "The Origin Story", "headline": "The Origin Story", "tagline": "Every great athlete has a Chapter 1. This is yours.", "best_workout": "26.1", "best_pct": 32.5, "worst_workout": "26.2", "worst_pct": 23.9, "spread": 8.6, "gym_rank": 50, "gym_total": 79, "award": "Women's Metronome"}, "num_opens": 1}, {"name": "Yoseline Hoffman", "division": "women_rx", "overall_rank": 86750, "overall_pct": null, "wod1_pct": 22.3, "wod2_pct": 44.7, "wod3_pct": null, "wod1_reps": 154, "wod2_reps": 91, "wod3_reps": 0, "archetype": "Gymnast", "volatility": 22.3, "age": 35, "wrapped": {"persona": "The Origin Story", "headline": "The Origin Story", "tagline": "Every great athlete has a Chapter 1. This is yours.", "best_workout": "26.2", "best_pct": 44.7, "worst_workout": "26.3", "worst_pct": 0.0, "spread": 44.7, "gym_rank": 51, "gym_total": 79, "award": null}, "num_opens": 1}, {"name": "Manuel Almazan Paniaga", "division": "men_rx", "overall_rank": 89024, "overall_pct": null, "wod1_pct": 56.8, "wod2_pct": null, "wod3_pct": null, "wod1_reps": 205, "wod2_reps": 0, "wod3_reps": 0, "archetype": "Engine", "volatility": 32.8, "age": 33, "wrapped": {"persona": "The Origin Story", "headline": "The Origin Story", "tagline": "Every great athlete has a Chapter 1. This is yours.", "best_workout": "26.1", "best_pct": 56.8, "worst_workout": "26.2", "worst_pct": 0.0, "spread": 56.8, "gym_rank": 52, "gym_total": 79, "award": null}, "num_opens": 1}, {"name": "Lizbeth Serrato", "division": "women_rx", "overall_rank": 89168, "overall_pct": null, "wod1_pct": 49.3, "wod2_pct": null, "wod3_pct": 31.1, "wod1_reps": 187, "wod2_reps": 0, "wod3_reps": 135, "archetype": "Engine", "volatility": 24.9, "age": 46, "wrapped": {"persona": "The Ageless", "headline": "The Ageless", "tagline": "Age 46. Still making 25-year-olds nervous.", "best_workout": "26.1", "best_pct": 49.3, "worst_workout": "26.2", "worst_pct": 0.0, "spread": 49.3, "gym_rank": 53, "gym_total": 79, "award": null}, "num_opens": 1}, {"name": "Gabriela Schlam", "division": "women_rx", "overall_rank": 89748, "overall_pct": 9.4, "wod1_pct": 8.8, "wod2_pct": 25.7, "wod3_pct": 18.8, "wod1_reps": 121, "wod2_reps": 68, "wod3_reps": 116, "archetype": "Gymnast", "volatility": 8.5, "age": 22, "wrapped": {"persona": "The Wolf", "headline": "The Wolf", "tagline": "Part of the pack. Stronger because of it.", "best_workout": "26.2", "best_pct": 25.7, "worst_workout": "26.1", "worst_pct": 8.8, "spread": 16.9, "gym_rank": 54, "gym_total": 79, "award": null}, "num_opens": 1}, {"name": "Diana Olvera", "division": "women_rx", "overall_rank": 89881, "overall_pct": null, "wod1_pct": 24.8, "wod2_pct": null, "wod3_pct": 51.6, "wod1_reps": 157, "wod2_reps": 0, "wod3_reps": 156, "archetype": "Barbell", "volatility": 25.8, "age": 38, "wrapped": {"persona": "The Origin Story", "headline": "The Origin Story", "tagline": "Every great athlete has a Chapter 1. This is yours.", "best_workout": "26.3", "best_pct": 51.6, "worst_workout": "26.2", "worst_pct": 0.0, "spread": 51.6, "gym_rank": 55, "gym_total": 79, "award": null}, "num_opens": 1}, {"name": "Laura Laurian", "division": "women_rx", "overall_rank": 89944, "overall_pct": null, "wod1_pct": 23.9, "wod2_pct": 24.2, "wod3_pct": null, "wod1_reps": 156, "wod2_reps": 68, "wod3_reps": 0, "archetype": "Gymnast", "volatility": 13.9, "age": 30, "wrapped": {"persona": "The Origin Story", "headline": "The Origin Story", "tagline": "Every great athlete has a Chapter 1. This is yours.", "best_workout": "26.2", "best_pct": 24.2, "worst_workout": "26.3", "worst_pct": 0.0, "spread": 24.2, "gym_rank": 56, "gym_total": 79, "award": null}, "num_opens": 1}, {"name": "Liliana Torres", "division": "women_rx", "overall_rank": 90068, "overall_pct": 9.1, "wod1_pct": 9.5, "wod2_pct": 23.6, "wod3_pct": 22.5, "wod1_reps": 125, "wod2_reps": 68, "wod3_reps": 125, "archetype": "Gymnast", "volatility": 7.8, "age": 50, "wrapped": {"persona": "The Slow Burn", "headline": "The Slow Burn", "tagline": "Started quiet. Finished loud.", "best_workout": "26.2", "best_pct": 23.6, "worst_workout": "26.1", "worst_pct": 9.5, "spread": 14.0, "gym_rank": 57, "gym_total": 79, "award": null}, "num_opens": 1}, {"name": "Karol Cueto", "division": "women_rx", "overall_rank": 90250, "overall_pct": 8.9, "wod1_pct": 6.5, "wod2_pct": 23.7, "wod3_pct": 24.2, "wod1_reps": 109, "wod2_reps": 68, "wod3_reps": 129, "archetype": "Barbell", "volatility": 10.1, "age": 21, "wrapped": {"persona": "The Comeback Kid", "headline": "The Comeback Kid", "tagline": "You gained 18 percentile points from Week 1 to Week 3. Peaked when it mattered.", "best_workout": "26.3", "best_pct": 24.2, "worst_workout": "26.1", "worst_pct": 6.5, "spread": 17.7, "gym_rank": 58, "gym_total": 79, "award": null}, "num_opens": 1}, {"name": "Daniela Valverde", "division": "women_rx", "overall_rank": 90965, "overall_pct": 8.2, "wod1_pct": 4.1, "wod2_pct": 21.6, "wod3_pct": 27.1, "wod1_reps": 80, "wod2_reps": 68, "wod3_reps": 132, "archetype": "Barbell", "volatility": 12.0, "age": 29, "wrapped": {"persona": "The Comeback Kid", "headline": "The Comeback Kid", "tagline": "You gained 23 percentile points from Week 1 to Week 3. Peaked when it mattered.", "best_workout": "26.3", "best_pct": 27.1, "worst_workout": "26.1", "worst_pct": 4.1, "spread": 23.0, "gym_rank": 59, "gym_total": 79, "award": null}, "num_opens": 2}, {"name": "Adriana Arely Minero", "division": "women_rx", "overall_rank": 91587, "overall_pct": 7.6, "wod1_pct": 7.0, "wod2_pct": 21.6, "wod3_pct": 18.1, "wod1_reps": 111, "wod2_reps": 68, "wod3_reps": 114, "archetype": "Gymnast", "volatility": 7.7, "age": 32, "wrapped": {"persona": "The Slow Burn", "headline": "The Slow Burn", "tagline": "Started quiet. Finished loud.", "best_workout": "26.2", "best_pct": 21.6, "worst_workout": "26.1", "worst_pct": 7.0, "spread": 14.7, "gym_rank": 60, "gym_total": 79, "award": null}, "num_opens": 1}, {"name": "Geraldine Gonzalez", "division": "women_rx", "overall_rank": 92914, "overall_pct": null, "wod1_pct": 7.4, "wod2_pct": 22.6, "wod3_pct": null, "wod1_reps": 114, "wod2_reps": 68, "wod3_reps": 0, "archetype": "Gymnast", "volatility": 11.5, "age": 34, "wrapped": {"persona": "The Wolf", "headline": "The Wolf", "tagline": "Part of the pack. Stronger because of it.", "best_workout": "26.2", "best_pct": 22.6, "worst_workout": "26.3", "worst_pct": 0.0, "spread": 22.6, "gym_rank": 61, "gym_total": 79, "award": null}, "num_opens": 1}, {"name": "Diego Echeverria", "division": "men_rx", "overall_rank": 93401, "overall_pct": 20.8, "wod1_pct": 7.7, "wod2_pct": 17.1, "wod3_pct": 19.0, "wod1_reps": 128, "wod2_reps": 79, "wod3_reps": 118, "archetype": "Barbell", "volatility": 6.0, "age": 19, "wrapped": {"persona": "The Slow Burn", "headline": "The Slow Burn", "tagline": "Started quiet. Finished loud.", "best_workout": "26.3", "best_pct": 19.0, "worst_workout": "26.1", "worst_pct": 7.7, "spread": 11.2, "gym_rank": 62, "gym_total": 79, "award": null}, "num_opens": 1}, {"name": "Maribel Arcilla", "division": "women_rx", "overall_rank": 93628, "overall_pct": null, "wod1_pct": 38.2, "wod2_pct": null, "wod3_pct": null, "wod1_reps": 174, "wod2_reps": 0, "wod3_reps": 0, "archetype": "Engine", "volatility": 22.1, "age": 33, "wrapped": {"persona": "The Origin Story", "headline": "The Origin Story", "tagline": "Every great athlete has a Chapter 1. This is yours.", "best_workout": "26.1", "best_pct": 38.2, "worst_workout": "26.2", "worst_pct": 0.0, "spread": 38.2, "gym_rank": 63, "gym_total": 79, "award": null}, "num_opens": 1}, {"name": "Ximena Garcia", "division": "women_rx", "overall_rank": 96118, "overall_pct": null, "wod1_pct": 18.7, "wod2_pct": null, "wod3_pct": null, "wod1_reps": 148, "wod2_reps": 0, "wod3_reps": 0, "archetype": "Engine", "volatility": 10.8, "age": 19, "wrapped": {"persona": "The Wolf", "headline": "The Wolf", "tagline": "Part of the pack. Stronger because of it.", "best_workout": "26.1", "best_pct": 18.7, "worst_workout": "26.2", "worst_pct": 0.0, "spread": 18.7, "gym_rank": 64, "gym_total": 79, "award": null}, "num_opens": 1}, {"name": "Erick Ovando", "division": "men_rx", "overall_rank": 97140, "overall_pct": null, "wod1_pct": null, "wod2_pct": 21.9, "wod3_pct": 21.5, "wod1_reps": 0, "wod2_reps": 89, "wod3_reps": 125, "archetype": "Gymnast", "volatility": 12.5, "age": 29, "wrapped": {"persona": "The Origin Story", "headline": "The Origin Story", "tagline": "Every great athlete has a Chapter 1. This is yours.", "best_workout": "26.2", "best_pct": 21.9, "worst_workout": "26.1", "worst_pct": 0.0, "spread": 21.9, "gym_rank": 65, "gym_total": 79, "award": null}, "num_opens": 1}, {"name": "Luis Gomez", "division": "men_rx", "overall_rank": 97467, "overall_pct": null, "wod1_pct": 37.7, "wod2_pct": null, "wod3_pct": null, "wod1_reps": 182, "wod2_reps": 0, "wod3_reps": 0, "archetype": "Engine", "volatility": 21.8, "age": 26, "wrapped": {"persona": "The Origin Story", "headline": "The Origin Story", "tagline": "Every great athlete has a Chapter 1. This is yours.", "best_workout": "26.1", "best_pct": 37.7, "worst_workout": "26.2", "worst_pct": 0.0, "spread": 37.7, "gym_rank": 66, "gym_total": 79, "award": null}, "num_opens": 1}, {"name": "Monserrat Gimenez", "division": "women_rx", "overall_rank": 97704, "overall_pct": null, "wod1_pct": 7.8, "wod2_pct": null, "wod3_pct": null, "wod1_reps": 116, "wod2_reps": 0, "wod3_reps": 0, "archetype": "Engine", "volatility": 4.5, "age": 26, "wrapped": {"persona": "The Wolf", "headline": "The Wolf", "tagline": "Part of the pack. Stronger because of it.", "best_workout": "26.1", "best_pct": 7.8, "worst_workout": "26.2", "worst_pct": 0.0, "spread": 7.8, "gym_rank": 67, "gym_total": 79, "award": null}, "num_opens": 1}, {"name": "Carole Mezghini", "division": "women_rx", "overall_rank": 97836, "overall_pct": null, "wod1_pct": 6.8, "wod2_pct": null, "wod3_pct": null, "wod1_reps": 111, "wod2_reps": 0, "wod3_reps": 0, "archetype": "Engine", "volatility": 3.9, "age": 50, "wrapped": {"persona": "The Wolf", "headline": "The Wolf", "tagline": "Part of the pack. Stronger because of it.", "best_workout": "26.1", "best_pct": 6.8, "worst_workout": "26.2", "worst_pct": 0.0, "spread": 6.8, "gym_rank": 68, "gym_total": 79, "award": null}, "num_opens": 1}, {"name": "Jonathan Campos", "division": "men_rx", "overall_rank": 99759, "overall_pct": null, "wod1_pct": 11.1, "wod2_pct": 14.1, "wod3_pct": null, "wod1_reps": 140, "wod2_reps": 71, "wod3_reps": 0, "archetype": "Gymnast", "volatility": 7.4, "age": 39, "wrapped": {"persona": "The Wolf", "headline": "The Wolf", "tagline": "Part of the pack. Stronger because of it.", "best_workout": "26.2", "best_pct": 14.1, "worst_workout": "26.3", "worst_pct": 0.0, "spread": 14.1, "gym_rank": 69, "gym_total": 79, "award": null}, "num_opens": 1}, {"name": "Miguel Angel Tovar Ovalle", "division": "men_rx", "overall_rank": 100968, "overall_pct": 14.4, "wod1_pct": 91.2, "wod2_pct": 91.2, "wod3_pct": 75.8, "wod1_reps": 258, "wod2_reps": 132, "wod3_reps": 184, "archetype": "Gymnast", "volatility": 8.9, "age": 40, "wrapped": {"persona": "The Sniper", "headline": "The Sniper", "tagline": "One shot. One kill. Your 26.2 was elite.", "best_workout": "26.2", "best_pct": 91.2, "worst_workout": "26.3", "worst_pct": 75.8, "spread": 15.4, "gym_rank": 70, "gym_total": 79, "award": "Men's Best on 26.1"}, "num_opens": 1}, {"name": "Rogelio Espinosa", "division": "men_rx", "overall_rank": 103105, "overall_pct": 12.6, "wod1_pct": 5.9, "wod2_pct": 15.7, "wod3_pct": 16.8, "wod1_reps": 116, "wod2_reps": 75, "wod3_reps": 109, "archetype": "Barbell", "volatility": 6.0, "age": 46, "wrapped": {"persona": "The Slow Burn", "headline": "The Slow Burn", "tagline": "Started quiet. Finished loud.", "best_workout": "26.3", "best_pct": 16.8, "worst_workout": "26.1", "worst_pct": 5.9, "spread": 10.9, "gym_rank": 71, "gym_total": 79, "award": null}, "height_in": 67, "num_opens": 1}, {"name": "Genaro Velasco", "division": "men_rx", "overall_rank": 105403, "overall_pct": null, "wod1_pct": 7.3, "wod2_pct": 72.8, "wod3_pct": null, "wod1_reps": 126, "wod2_reps": 119, "wod3_reps": 0, "archetype": "Gymnast", "volatility": 40.1, "age": 40, "wrapped": {"persona": "The Ageless", "headline": "The Ageless", "tagline": "Age 40. Still making 25-year-olds nervous.", "best_workout": "26.2", "best_pct": 72.8, "worst_workout": "26.3", "worst_pct": 0.0, "spread": 72.8, "gym_rank": 72, "gym_total": 79, "award": null}, "num_opens": 1}, {"name": "Alejandro Garcia", "division": "men_rx", "overall_rank": 105983, "overall_pct": 10.1, "wod1_pct": 59.7, "wod2_pct": 25.4, "wod3_pct": 78.1, "wod1_reps": 210, "wod2_reps": 90, "wod3_reps": 186, "archetype": "Barbell", "volatility": 26.8, "age": 45, "wrapped": {"persona": "The Comeback Kid", "headline": "The Comeback Kid", "tagline": "You gained 18 percentile points from Week 1 to Week 3. Peaked when it mattered.", "best_workout": "26.3", "best_pct": 78.1, "worst_workout": "26.2", "worst_pct": 25.4, "spread": 52.8, "gym_rank": 73, "gym_total": 79, "award": null}, "height_in": 66, "weight_lb": 176, "num_opens": 6}, {"name": "Francisco Granados", "division": "men_rx", "overall_rank": 106885, "overall_pct": 9.4, "wod1_pct": 34.1, "wod2_pct": 49.6, "wod3_pct": 53.3, "wod1_reps": 178, "wod2_reps": 112, "wod3_reps": 160, "archetype": "Barbell", "volatility": 10.2, "age": 48, "wrapped": {"persona": "The Comeback Kid", "headline": "The Comeback Kid", "tagline": "You gained 19 percentile points from Week 1 to Week 3. Peaked when it mattered.", "best_workout": "26.3", "best_pct": 53.3, "worst_workout": "26.1", "worst_pct": 34.1, "spread": 19.2, "gym_rank": 74, "gym_total": 79, "award": null}, "num_opens": 1}, {"name": "Eduardo Negrete", "division": "men_rx", "overall_rank": 109481, "overall_pct": 7.2, "wod1_pct": 40.3, "wod2_pct": 36.5, "wod3_pct": 22.9, "wod1_reps": 185, "wod2_reps": 112, "wod3_reps": 128, "archetype": "Engine", "volatility": 9.2, "age": 41, "wrapped": {"persona": "The Ageless", "headline": "The Ageless", "tagline": "Age 41. Still making 25-year-olds nervous.", "best_workout": "26.1", "best_pct": 40.3, "worst_workout": "26.3", "worst_pct": 22.9, "spread": 17.4, "gym_rank": 75, "gym_total": 79, "award": null}, "num_opens": 1}, {"name": "Luis Puerta", "division": "men_rx", "overall_rank": 109722, "overall_pct": null, "wod1_pct": 5.2, "wod2_pct": 19.7, "wod3_pct": null, "wod1_reps": 110, "wod2_reps": 87, "wod3_reps": 0, "archetype": "Gymnast", "volatility": 10.2, "age": 30, "wrapped": {"persona": "The Wolf", "headline": "The Wolf", "tagline": "Part of the pack. Stronger because of it.", "best_workout": "26.2", "best_pct": 19.7, "worst_workout": "26.3", "worst_pct": 0.0, "spread": 19.7, "gym_rank": 76, "gym_total": 79, "award": null}, "num_opens": 1}, {"name": "Gerardo Gonzalez", "division": "men_rx", "overall_rank": 110665, "overall_pct": null, "wod1_pct": 8.5, "wod2_pct": null, "wod3_pct": null, "wod1_reps": 131, "wod2_reps": 0, "wod3_reps": 0, "archetype": "Engine", "volatility": 4.9, "age": 40, "wrapped": {"persona": "The Wolf", "headline": "The Wolf", "tagline": "Part of the pack. Stronger because of it.", "best_workout": "26.1", "best_pct": 8.5, "worst_workout": "26.2", "worst_pct": 0.0, "spread": 8.5, "gym_rank": 77, "gym_total": 79, "award": null}, "num_opens": 2}, {"name": "Orlando Salinas", "division": "men_rx", "overall_rank": 112673, "overall_pct": null, "wod1_pct": 4.0, "wod2_pct": null, "wod3_pct": null, "wod1_reps": 91, "wod2_reps": 0, "wod3_reps": 0, "archetype": "Engine", "volatility": 2.3, "age": 25, "wrapped": {"persona": "The Wolf", "headline": "The Wolf", "tagline": "Part of the pack. Stronger because of it.", "best_workout": "26.1", "best_pct": 4.0, "worst_workout": "26.2", "worst_pct": 0.0, "spread": 4.0, "gym_rank": 78, "gym_total": 79, "award": null}, "num_opens": 1}, {"name": "Oscar Curiel", "division": "men_rx", "overall_rank": 116098, "overall_pct": null, "wod1_pct": 20.4, "wod2_pct": null, "wod3_pct": null, "wod1_reps": 159, "wod2_reps": 0, "wod3_reps": 0, "archetype": "Engine", "volatility": 11.8, "age": 39, "wrapped": {"persona": "The Origin Story", "headline": "The Origin Story", "tagline": "Every great athlete has a Chapter 1. This is yours.", "best_workout": "26.1", "best_pct": 20.4, "worst_workout": "26.2", "worst_pct": 0.0, "spread": 20.4, "gym_rank": 79, "gym_total": 79, "award": null}, "num_opens": 1}]}