{"affiliate_name": "CrossFit TRG", "affiliate_id": 4695, "total_athletes": 52, "rx_count": 50, "scaled_count": 2, "gym_rank": 8348, "total_gyms": 8587, "gym_rank_pct": 97.2, "overall_median_pct": 21.7, "workout_stats": {"wod1": {"name": "26.1", "type": "engine", "gym_median": 26.6, "global_median": 54.3, "gym_rank_pct": 6.9}, "wod2": {"name": "26.2", "type": "gymnastics", "gym_median": 46.9, "global_median": 55.5, "gym_rank_pct": 28.6}, "wod3": {"name": "26.3", "type": "barbell", "gym_median": 32.5, "global_median": 57.4, "gym_rank_pct": 5.4}}, "gym_archetype": "Gymnast", "best_workout": {"key": "wod2", "name": "26.2", "type": "gymnastics"}, "worst_workout": {"key": "wod1", "name": "26.1", "type": "engine"}, "muscle_up": {"gym_got_mu": 26, "gym_total": 47, "gym_mu_pct": 55.3, "global_mu_pct": 63.1, "global_got_mu": 124606, "global_total": 197366, "athletes": [{"name": "John Michael Encinares", "reps": 132, "got_mu": true}, {"name": "Alan Robson", "reps": 132, "got_mu": true}, {"name": "Mikayla OGrady", "reps": 132, "got_mu": true}, {"name": "PROMILA DANGI", "reps": 132, "got_mu": true}, {"name": "Emma Chavez", "reps": 132, "got_mu": true}, {"name": "Jayde Campion", "reps": 132, "got_mu": true}, {"name": "Gabrielle Ross", "reps": 132, "got_mu": true}, {"name": "Joanna Santoro", "reps": 132, "got_mu": true}, {"name": "Alicia Malatesta", "reps": 132, "got_mu": true}, {"name": "Yashodha Maddumage", "reps": 132, "got_mu": true}, {"name": "Kerry Ceradini", "reps": 132, "got_mu": true}, {"name": "Anthea Obst", "reps": 132, "got_mu": true}, {"name": "Jami Carter", "reps": 126, "got_mu": true}, {"name": "Jose Hernandez", "reps": 115, "got_mu": true}, {"name": "Tim Pearson", "reps": 113, "got_mu": true}, {"name": "Ankur Patel", "reps": 113, "got_mu": true}, {"name": "Damien Ralls", "reps": 112, "got_mu": true}, {"name": "Dace Howard", "reps": 112, "got_mu": true}, {"name": "Bao Chau", "reps": 112, "got_mu": true}, {"name": "Christian Chavez", "reps": 112, "got_mu": true}, {"name": "Marti Duya", "reps": 112, "got_mu": true}, {"name": "Anthony Santoro", "reps": 112, "got_mu": true}, {"name": "Dalvir Singh Sohi", "reps": 112, "got_mu": true}, {"name": "Allison Lindley", "reps": 112, "got_mu": true}, {"name": "Tiff Warnest", "reps": 112, "got_mu": true}, {"name": "Tran Ngo", "reps": 112, "got_mu": true}, {"name": "Don Jayasinghe", "reps": 106, "got_mu": false}, {"name": "Mia Ngo", "reps": 95, "got_mu": false}, {"name": "Stephen Chivers", "reps": 91, "got_mu": false}, {"name": "Phillip Moxey", "reps": 89, "got_mu": false}, {"name": "Lee Warnest", "reps": 88, "got_mu": false}, {"name": "Rohan Howson", "reps": 88, "got_mu": false}, {"name": "Patricia Sorongon", "reps": 86, "got_mu": false}, {"name": "Naveen Munnangi", "reps": 85, "got_mu": false}, {"name": "Emiko Ohara", "reps": 72, "got_mu": false}, {"name": "Brad Hajek", "reps": 70, "got_mu": false}, {"name": "Dylan Kempster", "reps": 68, "got_mu": false}, {"name": "Corey Clark", "reps": 68, "got_mu": false}, {"name": "Ravi Vetrivelu", "reps": 68, "got_mu": false}, {"name": "Stephanie Nguyen", "reps": 68, "got_mu": false}, {"name": "Rachel Dempsey", "reps": 68, "got_mu": false}, {"name": "Jasmine Sekhon", "reps": 68, "got_mu": false}, {"name": "Marnie Pearson", "reps": 68, "got_mu": false}, {"name": "Alexis Wright", "reps": 51, "got_mu": false}, {"name": "Allan Bartlett", "reps": 48, "got_mu": false}, {"name": "Chan Bok", "reps": 47, "got_mu": false}, {"name": "Rachelle Aguada", "reps": 24, "got_mu": false}]}, "similar_gyms": {"gym_size": 52, "size_range": [37, 67], "similar_count": 1216, "gym_rank_among_similar": 1186, "similar_median_pct": 55.3, "similar_p75_pct": 65.6, "similar_p25_pct": 44.2, "gym_pct": 21.7, "similar_pcts": [9.2, 9.5, 11.8, 12.7, 12.8, 13.1, 13.4, 13.8, 13.8, 13.9, 13.9, 14.0, 14.0, 14.9, 14.9, 15.1, 16.0, 16.1, 17.7, 17.8, 17.8, 18.6, 19.0, 19.2, 19.7, 20.1, 20.2, 20.2, 20.8, 21.2, 21.5, 21.8, 21.9, 21.9, 22.3, 22.4, 23.0, 23.0, 23.1, 23.3, 23.5, 23.6, 23.9, 24.1, 24.1, 24.3, 24.6, 24.7, 24.9, 24.9, 25.2, 25.2, 25.4, 25.6, 25.8, 25.8, 25.9, 26.0, 26.1, 26.3, 26.3, 26.4, 26.6, 26.6, 26.9, 26.9, 27.2, 27.3, 27.7, 27.9, 28.0, 28.1, 28.3, 28.3, 28.5, 28.8, 28.8, 28.8, 28.8, 28.9, 28.9, 29.0, 29.0, 29.3, 29.3, 29.4, 29.6, 29.9, 29.9, 29.9, 30.0, 30.0, 30.2, 30.3, 30.4, 30.4, 30.4, 30.5, 30.6, 30.8, 30.8, 30.9, 30.9, 30.9, 31.0, 31.1, 31.1, 31.1, 31.2, 31.2, 31.3, 31.4, 31.4, 31.5, 31.6, 31.9, 32.0, 32.1, 32.1, 32.2, 32.2, 32.2, 32.3, 32.3, 32.6, 32.7, 32.7, 32.9, 32.9, 32.9, 33.4, 33.4, 33.6, 34.0, 34.0, 34.1, 34.1, 34.1, 34.4, 34.4, 34.5, 34.5, 34.6, 34.7, 34.9, 34.9, 35.0, 35.1, 35.2, 35.2, 35.2, 35.2, 35.2, 35.3, 35.3, 35.3, 35.4, 35.4, 35.6, 35.6, 35.8, 35.9, 36.1, 36.1, 36.1, 36.2, 36.2, 36.4, 36.5, 36.6, 36.6, 36.7, 36.7, 36.8, 36.9, 37.0, 37.0, 37.1, 37.2, 37.3, 37.4, 37.5, 37.5, 37.5, 37.6, 37.7, 37.8, 37.8, 38.1, 38.2, 38.2, 38.3, 38.3, 38.3, 38.3, 38.3, 38.6, 38.6, 38.7, 38.8, 38.8, 38.8, 38.9, 38.9, 38.9, 39.2, 39.2, 39.2, 39.3, 39.3, 39.5, 39.5, 39.6, 39.8, 39.9, 40.1, 40.2, 40.2, 40.2, 40.2, 40.3, 40.4, 40.4, 40.6, 40.6, 40.6, 40.7, 40.7, 40.8, 40.9, 40.9, 41.0, 41.1, 41.1, 41.1, 41.2, 41.3, 41.3, 41.4, 41.4, 41.4, 41.4, 41.5, 41.5, 41.5, 41.5, 41.5, 41.5, 41.5, 41.6, 41.6, 41.6, 41.6, 41.8, 41.9, 41.9, 41.9, 42.0, 42.0, 42.0, 42.1, 42.3, 42.3, 42.3, 42.5, 42.5, 42.5, 42.5, 42.5, 42.5, 42.6, 42.8, 42.8, 42.9, 42.9, 43.0, 43.0, 43.0, 43.0, 43.0, 43.1, 43.1, 43.1, 43.1, 43.2, 43.3, 43.3, 43.4, 43.5, 43.5, 43.6, 43.6, 43.7, 43.7, 43.8, 43.9, 43.9, 43.9, 44.1, 44.1, 44.1, 44.1, 44.2, 44.2, 44.2, 44.3, 44.3, 44.3, 44.4, 44.4, 44.4, 44.4, 44.5, 44.5, 44.5, 44.5, 44.6, 44.6, 44.6, 44.6, 44.7, 44.7, 44.7, 44.8, 44.8, 44.8, 44.9, 45.0, 45.1, 45.1, 45.2, 45.3, 45.3, 45.3, 45.4, 45.4, 45.4, 45.4, 45.4, 45.5, 45.5, 45.6, 45.6, 45.6, 45.7, 45.7, 45.7, 45.7, 45.7, 45.7, 45.7, 45.7, 45.9, 45.9, 45.9, 46.0, 46.0, 46.1, 46.1, 46.1, 46.2, 46.2, 46.5, 46.5, 46.5, 46.5, 46.5, 46.6, 46.6, 46.8, 46.8, 46.8, 46.9, 46.9, 46.9, 46.9, 47.0, 47.0, 47.0, 47.0, 47.0, 47.1, 47.1, 47.1, 47.1, 47.3, 47.3, 47.4, 47.4, 47.4, 47.5, 47.5, 47.6, 47.6, 47.7, 47.8, 47.9, 47.9, 48.0, 48.0, 48.0, 48.1, 48.1, 48.1, 48.2, 48.2, 48.2, 48.2, 48.3, 48.3, 48.4, 48.4, 48.4, 48.5, 48.5, 48.5, 48.5, 48.6, 48.6, 48.6, 48.6, 48.6, 48.7, 48.7, 48.7, 48.7, 48.8, 48.8, 48.8, 48.9, 49.0, 49.0, 49.0, 49.0, 49.1, 49.1, 49.1, 49.1, 49.1, 49.2, 49.2, 49.3, 49.3, 49.3, 49.3, 49.3, 49.4, 49.5, 49.5, 49.5, 49.6, 49.6, 49.6, 49.7, 49.8, 49.8, 50.0, 50.0, 50.0, 50.0, 50.1, 50.2, 50.2, 50.3, 50.3, 50.3, 50.5, 50.6, 50.6, 50.7, 50.7, 50.8, 50.8, 50.8, 50.8, 50.9, 50.9, 50.9, 50.9, 51.0, 51.0, 51.1, 51.1, 51.2, 51.2, 51.3, 51.3, 51.3, 51.3, 51.3, 51.3, 51.3, 51.3, 51.3, 51.4, 51.4, 51.4, 51.5, 51.5, 51.6, 51.6, 51.7, 51.7, 51.7, 51.7, 51.7, 51.8, 51.8, 51.8, 51.9, 51.9, 52.0, 52.0, 52.0, 52.0, 52.0, 52.0, 52.0, 52.0, 52.0, 52.1, 52.1, 52.1, 52.1, 52.2, 52.3, 52.3, 52.4, 52.4, 52.4, 52.6, 52.6, 52.6, 52.6, 52.7, 52.7, 52.7, 52.8, 52.8, 52.9, 53.0, 53.0, 53.0, 53.0, 53.0, 53.0, 53.1, 53.1, 53.1, 53.1, 53.2, 53.3, 53.3, 53.4, 53.4, 53.4, 53.4, 53.5, 53.5, 53.5, 53.7, 53.7, 53.7, 53.7, 53.7, 53.8, 53.8, 53.9, 53.9, 54.0, 54.0, 54.1, 54.1, 54.1, 54.2, 54.2, 54.3, 54.3, 54.3, 54.4, 54.5, 54.5, 54.5, 54.6, 54.7, 54.7, 54.7, 54.7, 54.8, 54.8, 54.8, 54.9, 54.9, 55.0, 55.0, 55.0, 55.0, 55.1, 55.1, 55.1, 55.1, 55.2, 55.2, 55.2, 55.3, 55.3, 55.3, 55.3, 55.4, 55.4, 55.5, 55.5, 55.5, 55.5, 55.5, 55.6, 55.6, 55.6, 55.6, 55.6, 55.7, 55.7, 55.7, 55.7, 55.8, 55.8, 55.8, 55.9, 55.9, 55.9, 55.9, 56.0, 56.0, 56.0, 56.1, 56.1, 56.2, 56.2, 56.2, 56.3, 56.4, 56.4, 56.4, 56.5, 56.5, 56.6, 56.6, 56.6, 56.6, 56.7, 56.7, 56.7, 56.8, 56.8, 56.9, 56.9, 56.9, 56.9, 57.0, 57.0, 57.1, 57.1, 57.1, 57.1, 57.2, 57.2, 57.2, 57.2, 57.3, 57.4, 57.4, 57.4, 57.4, 57.5, 57.5, 57.6, 57.6, 57.6, 57.6, 57.7, 57.7, 57.8, 57.8, 57.8, 57.8, 57.9, 57.9, 57.9, 58.0, 58.0, 58.0, 58.0, 58.1, 58.1, 58.2, 58.2, 58.2, 58.2, 58.2, 58.2, 58.3, 58.3, 58.3, 58.3, 58.4, 58.4, 58.4, 58.5, 58.6, 58.6, 58.6, 58.6, 58.6, 58.6, 58.6, 58.6, 58.6, 58.6, 58.7, 58.7, 58.7, 58.7, 58.8, 58.8, 58.8, 58.8, 58.9, 58.9, 58.9, 58.9, 59.0, 59.1, 59.1, 59.1, 59.1, 59.2, 59.2, 59.2, 59.3, 59.3, 59.5, 59.5, 59.5, 59.5, 59.5, 59.5, 59.5, 59.6, 59.6, 59.6, 59.7, 59.7, 59.7, 59.7, 59.7, 59.7, 59.8, 59.8, 59.8, 59.8, 59.9, 60.0, 60.0, 60.0, 60.0, 60.1, 60.1, 60.1, 60.2, 60.2, 60.2, 60.3, 60.3, 60.3, 60.4, 60.5, 60.5, 60.6, 60.6, 60.7, 60.7, 60.8, 60.8, 60.8, 60.9, 60.9, 60.9, 60.9, 60.9, 61.0, 61.0, 61.1, 61.1, 61.3, 61.3, 61.3, 61.3, 61.4, 61.4, 61.4, 61.4, 61.4, 61.6, 61.6, 61.6, 61.7, 61.7, 61.8, 61.8, 61.8, 61.8, 61.9, 61.9, 62.0, 62.0, 62.1, 62.1, 62.2, 62.2, 62.2, 62.3, 62.4, 62.4, 62.4, 62.4, 62.4, 62.4, 62.5, 62.6, 62.8, 62.8, 62.8, 62.9, 62.9, 63.0, 63.0, 63.1, 63.1, 63.1, 63.1, 63.1, 63.1, 63.3, 63.3, 63.3, 63.4, 63.4, 63.4, 63.5, 63.5, 63.5, 63.6, 63.6, 63.6, 63.6, 63.6, 63.7, 63.7, 63.7, 63.7, 63.8, 63.8, 63.8, 63.9, 63.9, 63.9, 63.9, 64.0, 64.0, 64.0, 64.0, 64.0, 64.0, 64.0, 64.1, 64.1, 64.2, 64.2, 64.3, 64.3, 64.3, 64.3, 64.4, 64.4, 64.4, 64.4, 64.5, 64.5, 64.5, 64.5, 64.7, 64.8, 64.9, 64.9, 65.0, 65.0, 65.1, 65.1, 65.2, 65.2, 65.2, 65.2, 65.3, 65.3, 65.4, 65.4, 65.4, 65.4, 65.4, 65.5, 65.6, 65.6, 65.6, 65.7, 65.7, 65.8, 65.9, 65.9, 66.0, 66.0, 66.0, 66.1, 66.1, 66.1, 66.2, 66.3, 66.3, 66.3, 66.3, 66.3, 66.4, 66.5, 66.6, 66.6, 66.6, 66.6, 66.6, 66.7, 66.7, 66.7, 66.8, 66.8, 66.8, 66.8, 66.9, 67.0, 67.0, 67.1, 67.1, 67.2, 67.2, 67.2, 67.2, 67.3, 67.3, 67.4, 67.4, 67.5, 67.5, 67.5, 67.5, 67.6, 67.6, 67.8, 67.9, 67.9, 68.1, 68.2, 68.2, 68.2, 68.2, 68.2, 68.3, 68.3, 68.5, 68.5, 68.5, 68.5, 68.5, 68.5, 68.7, 68.7, 68.8, 68.8, 68.8, 68.9, 68.9, 68.9, 69.0, 69.0, 69.1, 69.3, 69.4, 69.4, 69.4, 69.5, 69.6, 69.6, 69.7, 69.7, 69.7, 69.7, 69.7, 69.9, 69.9, 70.1, 70.2, 70.2, 70.3, 70.3, 70.3, 70.3, 70.3, 70.4, 70.4, 70.4, 70.5, 70.7, 70.8, 70.8, 70.8, 70.9, 71.0, 71.0, 71.0, 71.1, 71.1, 71.2, 71.2, 71.2, 71.5, 71.5, 71.6, 71.7, 71.7, 71.7, 71.7, 71.7, 71.8, 71.8, 71.9, 71.9, 72.0, 72.1, 72.1, 72.3, 72.3, 72.3, 72.3, 72.3, 72.3, 72.4, 72.4, 72.4, 72.5, 72.6, 72.6, 72.7, 72.7, 72.9, 72.9, 72.9, 73.1, 73.1, 73.2, 73.2, 73.2, 73.2, 73.3, 73.4, 73.5, 73.5, 73.5, 73.5, 73.5, 73.7, 73.8, 73.8, 73.8, 73.9, 73.9, 73.9, 74.0, 74.0, 74.0, 74.2, 74.4, 74.4, 74.4, 74.4, 74.5, 74.6, 74.6, 74.7, 74.8, 74.9, 75.0, 75.0, 75.2, 75.2, 75.4, 75.5, 75.6, 75.6, 75.6, 75.6, 75.7, 75.7, 75.7, 75.8, 76.0, 76.1, 76.1, 76.1, 76.2, 76.3, 76.3, 76.4, 76.4, 76.5, 76.8, 76.8, 76.9, 77.0, 77.1, 77.2, 77.4, 77.5, 77.5, 77.5, 77.7, 77.7, 77.9, 77.9, 77.9, 78.0, 78.1, 78.1, 78.2, 78.4, 78.4, 78.5, 78.5, 78.5, 78.5, 78.6, 78.7, 78.7, 78.8, 78.9, 79.0, 79.1, 79.2, 79.4, 79.4, 79.4, 79.6, 79.7, 79.7, 79.8, 79.9, 79.9, 80.0, 80.1, 80.3, 80.7, 80.8, 80.9, 80.9, 81.4, 81.5, 81.7, 81.9, 82.0, 82.0, 82.2, 82.4, 82.4, 82.5, 82.7, 82.8, 82.8, 83.4, 83.4, 83.5, 83.5, 83.6, 83.7, 83.9, 84.0, 84.1, 84.2, 84.6, 84.6, 84.9, 85.2, 85.6, 85.7, 85.8, 85.8, 86.1, 86.2, 86.6, 86.8, 87.5, 87.6, 87.8, 88.7, 88.7, 88.7, 89.3, 89.5, 89.9, 90.7, 91.9, 94.3], "comparable_gyms": [{"name": "No Excuses Athletics CrossFit", "pct": 21.8, "rank": 8346}, {"name": "CrossFit Vidatha", "pct": 21.9, "rank": 8339}, {"name": "CrossFit Thalassa", "pct": 21.9, "rank": 8343}, {"name": "CrossFit Clermont l' H\u00e9rault", "pct": 21.5, "rank": 8357}, {"name": "Garage Grit CrossFit", "pct": 21.2, "rank": 8362}, {"name": "CrossFit Maddox", "pct": 22.3, "rank": 8331}, {"name": "CrossFit 259", "pct": 22.4, "rank": 8326}, {"name": "Mundo CrossFit", "pct": 20.8, "rank": 8369}, {"name": "North Jax CrossFit", "pct": 23.0, "rank": 8306}, {"name": "CrossFit MTN", "pct": 23.0, "rank": 8308}]}, "rx_decision": {"gym_rx_count": 50, "gym_scaled_count": 2, "gym_rx_pct": 96.2, "global_rx_pct": 95.6, "by_age": [{"age_range": "18-24", "gym_rx_pct": 100.0, "global_rx_pct": 96.1, "gym_count": 3}, {"age_range": "25-29", "gym_rx_pct": 100.0, "global_rx_pct": 96.4, "gym_count": 8}, {"age_range": "30-34", "gym_rx_pct": 100.0, "global_rx_pct": 96.3, "gym_count": 11}, {"age_range": "35-39", "gym_rx_pct": 100.0, "global_rx_pct": 96.0, "gym_count": 7}, {"age_range": "40-44", "gym_rx_pct": 90.0, "global_rx_pct": 95.2, "gym_count": 10}, {"age_range": "45-49", "gym_rx_pct": 85.7, "global_rx_pct": 94.3, "gym_count": 7}, {"age_range": "50-65", "gym_rx_pct": 100.0, "global_rx_pct": 93.0, "gym_count": 5}]}, "hidden_gems": [{"name": "Kerry Ceradini", "overall_pct": 5.0, "best_workout": "26.2", "best_pct": 95.0, "gap": 90.1, "wod1": 18.5, "wod2": 95.0, "wod3": 43.3}, {"name": "Alan Robson", "overall_pct": 9.9, "best_workout": "26.2", "best_pct": 99.4, "gap": 89.5, "wod1": 3.6, "wod2": 99.4, "wod3": 14.3}, {"name": "Joanna Santoro", "overall_pct": 7.5, "best_workout": "26.2", "best_pct": 96.8, "gap": 89.3, "wod1": 24.1, "wod2": 96.8, "wod3": 18.8}, {"name": "Emma Chavez", "overall_pct": 10.6, "best_workout": "26.2", "best_pct": 98.4, "gap": 87.8, "wod1": 31.7, "wod2": 98.4, "wod3": 32.5}, {"name": "Yashodha Maddumage", "overall_pct": 7.0, "best_workout": "26.2", "best_pct": 94.4, "gap": 87.4, "wod1": 16.7, "wod2": 94.4, "wod3": 28.5}, {"name": "Jayde Campion", "overall_pct": 9.4, "best_workout": "26.2", "best_pct": 95.9, "gap": 86.4, "wod1": 26.6, "wod2": 95.9, "wod3": 35.2}, {"name": "Gabrielle Ross", "overall_pct": 8.7, "best_workout": "26.2", "best_pct": 94.4, "gap": 85.7, "wod1": 44.9, "wod2": 94.4, "wod3": 86.5}, {"name": "Alicia Malatesta", "overall_pct": 7.5, "best_workout": "26.2", "best_pct": 91.3, "gap": 83.9, "wod1": 22.0, "wod2": 91.3, "wod3": 31.4}], "awards": [{"title": "Women's MVP", "subtitle": "Highest overall percentile", "name": "Allison Lindley", "detail": "Overall 79th percentile \u2014 your gym's top performer", "stats": {"wod1": 65.6, "wod2": 69.1, "wod3": 75.8}}, {"title": "Women's Wildcard", "subtitle": "Biggest swing between workouts", "name": "Joanna Santoro", "detail": "Range: 78 percentile points between best and worst", "stats": {"wod1": 24.1, "wod2": 96.8, "wod3": 18.8}}, {"title": "Women's Best on 26.1", "subtitle": "Top performer on 26.1", "name": "Emiko Ohara", "detail": "63th percentile on 26.1", "stats": {"wod1": 63.1, "wod2": 31.0, "wod3": 84.5}}, {"title": "Women's Best on 26.2", "subtitle": "Top performer on 26.2", "name": "Emma Chavez", "detail": "98th percentile on 26.2", "stats": {"wod1": 31.7, "wod2": 98.4, "wod3": 32.5}}, {"title": "Women's Best on 26.3", "subtitle": "Top performer on 26.3", "name": "Gabrielle Ross", "detail": "86th percentile on 26.3", "stats": {"wod1": 44.9, "wod2": 94.4, "wod3": 86.5}}, {"title": "Women's Metronome", "subtitle": "Most consistent across all 3 workouts", "name": "Mia Ngo", "detail": "Volatility: 1.8 \u2014 nearly the same percentile every week", "stats": {"wod1": 50.6, "wod2": 47.2, "wod3": 50.1}}, {"title": "Women's Closer", "subtitle": "Biggest improvement Week 1 \u2192 Week 3", "name": "Kerry Ceradini", "detail": "Jumped 25 percentile points from 26.1 to 26.3", "stats": {"wod1": 18.5, "wod2": 95.0, "wod3": 43.3}}, {"title": "Women's Best 35\u201339", "subtitle": "Top performer ages 35\u201339", "name": "Rachelle Aguada", "detail": "Age 39, overall 37th percentile", "stats": {"wod1": 9.8, "wod2": 9.9, "wod3": 18.2}}, {"title": "Women's Best 40\u201344", "subtitle": "Top performer ages 40\u201344", "name": "PROMILA DANGI", "detail": "Age 40, overall 15th percentile", "stats": {"wod1": 55.2, "wod2": 97.5, "wod3": 51.4}}, {"title": "Men's MVP", "subtitle": "Highest overall percentile", "name": "Damien Ralls", "detail": "Overall 74th percentile \u2014 your gym's top performer", "stats": {"wod1": 73.0, "wod2": 46.9, "wod3": 85.9}}, {"title": "Men's Wildcard", "subtitle": "Biggest swing between workouts", "name": "Alan Robson", "detail": "Range: 96 percentile points between best and worst", "stats": {"wod1": 3.6, "wod2": 99.4, "wod3": 14.3}}, {"title": "Men's Best on 26.1", "subtitle": "Top performer on 26.1", "name": "Dace Howard", "detail": "82th percentile on 26.1", "stats": {"wod1": 82.3, "wod2": 39.9, "wod3": 72.3}}, {"title": "Men's Best on 26.2", "subtitle": "Top performer on 26.2", "name": "John Michael Encinares", "detail": "91th percentile on 26.2", "stats": {"wod1": 28.6, "wod2": 90.6, "wod3": 65.0}}, {"title": "Men's Best on 26.3", "subtitle": "Top performer on 26.3", "name": "Bao Chau", "detail": "82th percentile on 26.3", "stats": {"wod1": 55.8, "wod2": 49.8, "wod3": 81.9}}, {"title": "Men's Metronome", "subtitle": "Most consistent across all 3 workouts", "name": "Dylan Kempster", "detail": "Volatility: 1.8 \u2014 nearly the same percentile every week", "stats": {"wod1": 10.6, "wod2": 12.5, "wod3": 14.3}}, {"title": "Men's Closer", "subtitle": "Biggest improvement Week 1 \u2192 Week 3", "name": "Dalvir Singh Sohi", "detail": "Jumped 49 percentile points from 26.1 to 26.3", "stats": {"wod1": 14.5, "wod2": 48.1, "wod3": 63.6}}, {"title": "Men's Best 35\u201339", "subtitle": "Top performer ages 35\u201339", "name": "Lee Warnest", "detail": "Age 39, overall 41th percentile", "stats": {"wod1": 45.6, "wod2": 20.6, "wod3": 36.9}}, {"title": "Men's Best 40\u201344", "subtitle": "Top performer ages 40\u201344", "name": "Ankur Patel", "detail": "Age 41, overall 22th percentile", "stats": {"wod1": 23.5, "wod2": 59.1, "wod3": 19.3}}, {"title": "Men's Best 45\u201349", "subtitle": "Top performer ages 45\u201349", "name": "Jose Hernandez", "detail": "Age 49, overall 70th percentile", "stats": {"wod1": 53.6, "wod2": 66.4, "wod3": 73.5}}, {"title": "Men's Best 50\u201354", "subtitle": "Top performer ages 50\u201354", "name": "Christian Chavez", "detail": "Age 51, overall 63th percentile", "stats": {"wod1": 59.4, "wod2": 52.9, "wod3": 61.7}}], "what_if": [{"name": "Alan Robson", "actual_pct": 39.1, "best_pct": 99.4, "potential_gain": 60.3, "best_workout": "26.2", "wod1": 3.6, "wod2": 99.4, "wod3": 14.3}, {"name": "Joanna Santoro", "actual_pct": 46.6, "best_pct": 96.8, "potential_gain": 50.3, "best_workout": "26.2", "wod1": 24.1, "wod2": 96.8, "wod3": 18.8}, {"name": "Yashodha Maddumage", "actual_pct": 46.6, "best_pct": 94.4, "potential_gain": 47.9, "best_workout": "26.2", "wod1": 16.7, "wod2": 94.4, "wod3": 28.5}, {"name": "Emma Chavez", "actual_pct": 54.2, "best_pct": 98.4, "potential_gain": 44.2, "best_workout": "26.2", "wod1": 31.7, "wod2": 98.4, "wod3": 32.5}, {"name": "Jayde Campion", "actual_pct": 52.5, "best_pct": 95.9, "potential_gain": 43.3, "best_workout": "26.2", "wod1": 26.6, "wod2": 95.9, "wod3": 35.2}, {"name": "Alicia Malatesta", "actual_pct": 48.3, "best_pct": 91.3, "potential_gain": 43.1, "best_workout": "26.2", "wod1": 22.0, "wod2": 91.3, "wod3": 31.4}, {"name": "Kerry Ceradini", "actual_pct": 52.3, "best_pct": 95.0, "potential_gain": 42.7, "best_workout": "26.2", "wod1": 18.5, "wod2": 95.0, "wod3": 43.3}, {"name": "Mikayla OGrady", "actual_pct": 54.4, "best_pct": 96.6, "potential_gain": 42.2, "best_workout": "26.2", "wod1": 29.7, "wod2": 96.6, "wod3": 36.9}, {"name": "Jami Carter", "actual_pct": 50.7, "best_pct": 88.7, "potential_gain": 38.0, "best_workout": "26.2", "wod1": 41.1, "wod2": 88.7, "wod3": 22.2}, {"name": "PROMILA DANGI", "actual_pct": 68.0, "best_pct": 97.5, "potential_gain": 29.5, "best_workout": "26.2", "wod1": 55.2, "wod2": 97.5, "wod3": 51.4}], "consistency": {"gym_median_vol": 13.77, "gym_mean_vol": 17.77, "global_median_vol": 9.4, "global_mean_vol": 11.47, "athletes": [{"name": "Dylan Kempster", "vol": 1.8, "range": 3.6, "wod1": 10.6, "wod2": 12.5, "wod3": 14.3}, {"name": "Mia Ngo", "vol": 1.81, "range": 3.3, "wod1": 50.6, "wod2": 47.2, "wod3": 50.1}, {"name": "Marnie Pearson", "vol": 2.16, "range": 4.1, "wod1": 19.9, "wod2": 18.9, "wod3": 15.7}, {"name": "Rachel Dempsey", "vol": 2.72, "range": 5.4, "wod1": 9.8, "wod2": 15.3, "wod3": 12.6}, {"name": "Alexis Wright", "vol": 3.48, "range": 6.8, "wod1": 11.8, "wod2": 14.0, "wod3": 18.6}, {"name": "Christian Chavez", "vol": 4.55, "range": 8.8, "wod1": 59.4, "wod2": 52.9, "wod3": 61.7}, {"name": "Rachelle Aguada", "vol": 4.8, "range": 8.3, "wod1": 9.8, "wod2": 9.9, "wod3": 18.2}, {"name": "Stephanie Nguyen", "vol": 4.91, "range": 8.6, "wod1": 27.4, "wod2": 18.8, "wod3": 19.0}, {"name": "Chan Bok", "vol": 5.0, "range": 9.3, "wod1": 9.2, "wod2": 10.6, "wod3": 18.5}, {"name": "Corey Clark", "vol": 5.03, "range": 10.0, "wod1": 18.7, "wod2": 12.6, "wod3": 22.6}, {"name": "Allison Lindley", "vol": 5.19, "range": 10.2, "wod1": 65.6, "wod2": 69.1, "wod3": 75.8}, {"name": "Jasmine Sekhon", "vol": 5.41, "range": 10.2, "wod1": 26.0, "wod2": 15.8, "wod3": 17.7}, {"name": "Naveen Munnangi", "vol": 5.48, "range": 9.7, "wod1": 19.7, "wod2": 19.2, "wod3": 29.0}, {"name": "Allan Bartlett", "vol": 5.53, "range": 10.8, "wod1": 21.7, "wod2": 10.9, "wod3": 14.4}, {"name": "Rohan Howson", "vol": 5.57, "range": 9.7, "wod1": 30.9, "wod2": 21.3, "wod3": 31.1}, {"name": "Stephen Chivers", "vol": 6.17, "range": 12.1, "wod1": 20.1, "wod2": 28.2, "wod3": 32.2}, {"name": "Tim Pearson", "vol": 7.27, "range": 13.9, "wod1": 58.3, "wod2": 61.6, "wod3": 72.2}, {"name": "Tiff Warnest", "vol": 8.82, "range": 17.6, "wod1": 55.5, "wod2": 73.2, "wod3": 64.3}, {"name": "Jose Hernandez", "vol": 10.08, "range": 19.9, "wod1": 53.6, "wod2": 66.4, "wod3": 73.5}, {"name": "Lee Warnest", "vol": 12.71, "range": 25.0, "wod1": 45.6, "wod2": 20.6, "wod3": 36.9}, {"name": "Phillip Moxey", "vol": 12.84, "range": 25.4, "wod1": 7.5, "wod2": 23.3, "wod3": 32.9}, {"name": "Tran Ngo", "vol": 13.71, "range": 26.6, "wod1": 35.2, "wod2": 54.4, "wod3": 27.8}, {"name": "Anthony Santoro", "vol": 13.77, "range": 26.3, "wod1": 11.5, "wod2": 37.9, "wod3": 17.7}, {"name": "Patricia Sorongon", "vol": 16.68, "range": 33.1, "wod1": 6.1, "wod2": 39.2, "wod3": 18.7}, {"name": "Bao Chau", "vol": 17.03, "range": 32.1, "wod1": 55.8, "wod2": 49.8, "wod3": 81.9}, {"name": "Marti Duya", "vol": 17.09, "range": 34.0, "wod1": 17.6, "wod2": 38.0, "wod3": 51.6}, {"name": "Don Jayasinghe", "vol": 18.61, "range": 35.4, "wod1": 61.8, "wod2": 34.2, "wod3": 69.6}, {"name": "Damien Ralls", "vol": 19.88, "range": 39.0, "wod1": 73.0, "wod2": 46.9, "wod3": 85.9}, {"name": "Brad Hajek", "vol": 20.51, "range": 37.7, "wod1": 51.7, "wod2": 14.0, "wod3": 46.8}, {"name": "Ankur Patel", "vol": 21.85, "range": 39.8, "wod1": 23.5, "wod2": 59.1, "wod3": 19.3}, {"name": "Dace Howard", "vol": 22.18, "range": 42.4, "wod1": 82.3, "wod2": 39.9, "wod3": 72.3}, {"name": "Dalvir Singh Sohi", "vol": 25.12, "range": 49.1, "wod1": 14.5, "wod2": 48.1, "wod3": 63.6}, {"name": "PROMILA DANGI", "vol": 25.61, "range": 46.1, "wod1": 55.2, "wod2": 97.5, "wod3": 51.4}, {"name": "Gabrielle Ross", "vol": 26.58, "range": 49.5, "wod1": 44.9, "wod2": 94.4, "wod3": 86.5}, {"name": "Emiko Ohara", "vol": 26.95, "range": 53.5, "wod1": 63.1, "wod2": 31.0, "wod3": 84.5}, {"name": "John Michael Encinares", "vol": 31.16, "range": 62.0, "wod1": 28.6, "wod2": 90.6, "wod3": 65.0}, {"name": "Jami Carter", "vol": 34.24, "range": 66.4, "wod1": 41.1, "wod2": 88.7, "wod3": 22.2}, {"name": "Mikayla OGrady", "vol": 36.72, "range": 66.9, "wod1": 29.7, "wod2": 96.6, "wod3": 36.9}, {"name": "Alicia Malatesta", "vol": 37.62, "range": 69.3, "wod1": 22.0, "wod2": 91.3, "wod3": 31.4}, {"name": "Jayde Campion", "vol": 37.76, "range": 69.3, "wod1": 26.6, "wod2": 95.9, "wod3": 35.2}, {"name": "Emma Chavez", "vol": 38.3, "range": 66.7, "wod1": 31.7, "wod2": 98.4, "wod3": 32.5}, {"name": "Kerry Ceradini", "vol": 39.05, "range": 76.6, "wod1": 18.5, "wod2": 95.0, "wod3": 43.3}, {"name": "Yashodha Maddumage", "vol": 41.89, "range": 77.8, "wod1": 16.7, "wod2": 94.4, "wod3": 28.5}, {"name": "Joanna Santoro", "vol": 43.62, "range": 78.1, "wod1": 24.1, "wod2": 96.8, "wod3": 18.8}, {"name": "Alan Robson", "vol": 52.47, "range": 95.8, "wod1": 3.6, "wod2": 99.4, "wod3": 14.3}], "global_hist": [3734, 5998, 8092, 10240, 11685, 12327, 11755, 11584, 11276, 10510, 9754, 8837, 7656, 6439, 5889, 5059, 4281, 3720, 3238, 2856, 2360, 2050, 1734, 1519, 1338, 1268, 1068, 1043, 923, 811, 760, 682, 645, 587, 570, 536, 500, 490, 455], "global_edges": [0.0, 1.0256410256410255, 2.051282051282051, 3.0769230769230766, 4.102564102564102, 5.128205128205128, 6.153846153846153, 7.179487179487179, 8.205128205128204, 9.23076923076923, 10.256410256410255, 11.282051282051281, 12.307692307692307, 13.333333333333332, 14.358974358974358, 15.384615384615383, 16.41025641025641, 17.435897435897434, 18.46153846153846, 19.487179487179485, 20.51282051282051, 21.538461538461537, 22.564102564102562, 23.589743589743588, 24.615384615384613, 25.64102564102564, 26.666666666666664, 27.69230769230769, 28.717948717948715, 29.74358974358974, 30.769230769230766, 31.794871794871792, 32.82051282051282, 33.84615384615384, 34.87179487179487, 35.8974358974359, 36.92307692307692, 37.94871794871794, 38.97435897435897, 40.0]}, "demographics": {"gym_median_age": 35, "global_median_age": 36, "gym_men": 27, "gym_women": 25, "gym_men_pct": 51.9, "global_men_pct": 54.1, "age_bins": [17.5, 22.5, 27.5, 32.5, 37.5, 42.5, 47.5, 52.5, 57.5, 62.5], "gym_age_pct": [3.8, 3.8, 15.4, 21.2, 13.5, 19.2, 13.5, 9.6, 0.0, 0.0], "global_age_pct": [1.9, 4.9, 14.6, 22.2, 22.2, 16.8, 11.2, 6.3, 0.0, 0.0]}, "athletes": [{"name": "Dalvir Singh Sohi", "division": "men_scaled", "overall_rank": 3047, "overall_pct": 39.1, "wod1_pct": 8.5, "wod2_pct": 33.6, "wod3_pct": 72.3, "wod1_reps": 148, "wod2_reps": 112, "wod3_reps": 172, "archetype": "Barbell", "volatility": 32.2, "age": 42, "wrapped": {"persona": "The Comeback Kid", "headline": "The Comeback Kid", "tagline": "You gained 64 percentile points from Week 1 to Week 3. Peaked when it mattered.", "best_workout": "26.3", "best_pct": 72.3, "worst_workout": "26.1", "worst_pct": 8.5, "spread": 63.9, "gym_rank": 1, "gym_total": 52, "award": "Men's Closer"}, "num_opens": 2}, {"name": "Brad Hajek", "division": "men_scaled", "overall_rank": 3811, "overall_pct": 23.8, "wod1_pct": 59.8, "wod2_pct": 4.4, "wod3_pct": 45.6, "wod1_reps": 199, "wod2_reps": 70, "wod3_reps": 152, "archetype": "Engine", "volatility": 28.8, "age": 49, "wrapped": {"persona": "The Ageless", "headline": "The Ageless", "tagline": "Age 49. Still making 25-year-olds nervous.", "best_workout": "26.1", "best_pct": 59.8, "worst_workout": "26.2", "worst_pct": 4.4, "spread": 55.4, "gym_rank": 2, "gym_total": 52, "award": null}, "height_in": 72, "weight_lb": 234, "num_opens": null}, {"name": "Allison Lindley", "division": "women_rx", "overall_rank": 21049, "overall_pct": 78.8, "wod1_pct": 65.6, "wod2_pct": 69.1, "wod3_pct": 75.8, "wod1_reps": 209, "wod2_reps": 112, "wod3_reps": 185, "archetype": "Barbell", "volatility": 5.2, "age": 29, "wrapped": {"persona": "The Natural", "headline": "The Natural", "tagline": "First Open. Top 70%. Explain yourself.", "best_workout": "26.3", "best_pct": 75.8, "worst_workout": "26.1", "worst_pct": 65.6, "spread": 10.2, "gym_rank": 3, "gym_total": 52, "award": "Women's MVP"}, "num_opens": 6}, {"name": "Tiff Warnest", "division": "women_rx", "overall_rank": 25130, "overall_pct": 74.6, "wod1_pct": 55.5, "wod2_pct": 73.2, "wod3_pct": 64.3, "wod1_reps": 194, "wod2_reps": 112, "wod3_reps": 173, "archetype": "Gymnast", "volatility": 8.8, "age": 34, "wrapped": {"persona": "The Natural", "headline": "The Natural", "tagline": "First Open. Top 64%. Explain yourself.", "best_workout": "26.2", "best_pct": 73.2, "worst_workout": "26.1", "worst_pct": 55.5, "spread": 17.6, "gym_rank": 4, "gym_total": 52, "award": null}, "height_in": 64, "weight_lb": 154, "num_opens": 3}, {"name": "Damien Ralls", "division": "men_rx", "overall_rank": 31055, "overall_pct": 73.7, "wod1_pct": 73.0, "wod2_pct": 46.9, "wod3_pct": 85.9, "wod1_reps": 225, "wod2_reps": 112, "wod3_reps": 198, "archetype": "Barbell", "volatility": 19.9, "age": 48, "wrapped": {"persona": "The Natural", "headline": "The Natural", "tagline": "First Open. Top 69%. Explain yourself.", "best_workout": "26.3", "best_pct": 85.9, "worst_workout": "26.2", "worst_pct": 46.9, "spread": 39.0, "gym_rank": 5, "gym_total": 52, "award": "Men's MVP"}, "num_opens": 3}, {"name": "Dace Howard", "division": "men_rx", "overall_rank": 35552, "overall_pct": 69.9, "wod1_pct": 82.3, "wod2_pct": 39.9, "wod3_pct": 72.3, "wod1_reps": 239, "wod2_reps": 112, "wod3_reps": 181, "archetype": "Engine", "volatility": 22.2, "age": 37, "wrapped": {"persona": "The Natural", "headline": "The Natural", "tagline": "First Open. Top 65%. Explain yourself.", "best_workout": "26.1", "best_pct": 82.3, "worst_workout": "26.2", "worst_pct": 39.9, "spread": 42.4, "gym_rank": 6, "gym_total": 52, "award": "Men's Best on 26.1"}, "height_in": 74, "weight_lb": 192, "num_opens": null}, {"name": "Jose Hernandez", "division": "men_rx", "overall_rank": 35938, "overall_pct": 69.5, "wod1_pct": 53.6, "wod2_pct": 66.4, "wod3_pct": 73.5, "wod1_reps": 201, "wod2_reps": 115, "wod3_reps": 182, "archetype": "Barbell", "volatility": 10.1, "age": 49, "wrapped": {"persona": "The Comeback Kid", "headline": "The Comeback Kid", "tagline": "You gained 20 percentile points from Week 1 to Week 3. Peaked when it mattered.", "best_workout": "26.3", "best_pct": 73.5, "worst_workout": "26.1", "worst_pct": 53.6, "spread": 19.9, "gym_rank": 7, "gym_total": 52, "award": "Men's Best 45\u201349"}, "height_in": 70, "weight_lb": 187, "num_opens": 8}, {"name": "Tim Pearson", "division": "men_rx", "overall_rank": 36491, "overall_pct": 69.1, "wod1_pct": 58.3, "wod2_pct": 61.6, "wod3_pct": 72.2, "wod1_reps": 208, "wod2_reps": 113, "wod3_reps": 181, "archetype": "Barbell", "volatility": 7.3, "age": 45, "wrapped": {"persona": "The Natural", "headline": "The Natural", "tagline": "First Open. Top 64%. Explain yourself.", "best_workout": "26.3", "best_pct": 72.2, "worst_workout": "26.1", "worst_pct": 58.3, "spread": 13.9, "gym_rank": 8, "gym_total": 52, "award": null}, "height_in": 66, "weight_lb": 165, "num_opens": 7}, {"name": "Bao Chau", "division": "men_rx", "overall_rank": 38366, "overall_pct": 67.5, "wod1_pct": 55.8, "wod2_pct": 49.8, "wod3_pct": 81.9, "wod1_reps": 204, "wod2_reps": 112, "wod3_reps": 191, "archetype": "Barbell", "volatility": 17.0, "age": 29, "wrapped": {"persona": "The Comeback Kid", "headline": "The Comeback Kid", "tagline": "You gained 26 percentile points from Week 1 to Week 3. Peaked when it mattered.", "best_workout": "26.3", "best_pct": 81.9, "worst_workout": "26.2", "worst_pct": 49.8, "spread": 32.1, "gym_rank": 9, "gym_total": 52, "award": "Men's Best on 26.3"}, "height_in": 68, "weight_lb": 174, "num_opens": 1}, {"name": "Christian Chavez", "division": "men_rx", "overall_rank": 43637, "overall_pct": 63.0, "wod1_pct": 59.4, "wod2_pct": 52.9, "wod3_pct": 61.7, "wod1_reps": 210, "wod2_reps": 112, "wod3_reps": 170, "archetype": "Barbell", "volatility": 4.6, "age": 51, "wrapped": {"persona": "The Ageless", "headline": "The Ageless", "tagline": "Age 51. Still making 25-year-olds nervous.", "best_workout": "26.3", "best_pct": 61.7, "worst_workout": "26.2", "worst_pct": 52.9, "spread": 8.8, "gym_rank": 10, "gym_total": 52, "award": "Men's Best 50\u201354"}, "height_in": 73, "weight_lb": 183, "num_opens": 9}, {"name": "Don Jayasinghe", "division": "men_rx", "overall_rank": 47006, "overall_pct": 60.1, "wod1_pct": 61.8, "wod2_pct": 34.2, "wod3_pct": 69.6, "wod1_reps": 212, "wod2_reps": 106, "wod3_reps": 180, "archetype": "Barbell", "volatility": 18.6, "age": 33, "wrapped": {"persona": "The Origin Story", "headline": "The Origin Story", "tagline": "Every great athlete has a Chapter 1. This is yours.", "best_workout": "26.3", "best_pct": 69.6, "worst_workout": "26.2", "worst_pct": 34.2, "spread": 35.4, "gym_rank": 11, "gym_total": 52, "award": null}, "num_opens": 1}, {"name": "Emiko Ohara", "division": "women_rx", "overall_rank": 56948, "overall_pct": 42.5, "wod1_pct": 63.1, "wod2_pct": 31.0, "wod3_pct": 84.5, "wod1_reps": 204, "wod2_reps": 72, "wod3_reps": 197, "archetype": "Barbell", "volatility": 26.9, "age": 47, "wrapped": {"persona": "The Comeback Kid", "headline": "The Comeback Kid", "tagline": "You gained 21 percentile points from Week 1 to Week 3. Peaked when it mattered.", "best_workout": "26.3", "best_pct": 84.5, "worst_workout": "26.2", "worst_pct": 31.0, "spread": 53.5, "gym_rank": 12, "gym_total": 52, "award": "Women's Best on 26.1"}, "num_opens": 1}, {"name": "Tran Ngo", "division": "women_rx", "overall_rank": 57860, "overall_pct": 41.6, "wod1_pct": 35.2, "wod2_pct": 54.4, "wod3_pct": 27.8, "wod1_reps": 170, "wod2_reps": 112, "wod3_reps": 133, "archetype": "Gymnast", "volatility": 13.7, "age": 29, "wrapped": {"persona": "The Origin Story", "headline": "The Origin Story", "tagline": "Every great athlete has a Chapter 1. This is yours.", "best_workout": "26.2", "best_pct": 54.4, "worst_workout": "26.3", "worst_pct": 27.8, "spread": 26.6, "gym_rank": 13, "gym_total": 52, "award": null}, "num_opens": null}, {"name": "Alexis Wright", "division": "women_rx", "overall_rank": 60871, "overall_pct": 38.6, "wod1_pct": 11.8, "wod2_pct": 14.0, "wod3_pct": 18.6, "wod1_reps": 132, "wod2_reps": 51, "wod3_reps": 116, "archetype": "Barbell", "volatility": 3.5, "age": 22, "wrapped": {"persona": "The Wolf", "headline": "The Wolf", "tagline": "Part of the pack. Stronger because of it.", "best_workout": "26.3", "best_pct": 18.6, "worst_workout": "26.1", "worst_pct": 11.8, "spread": 6.8, "gym_rank": 14, "gym_total": 52, "award": null}, "num_opens": 3}, {"name": "Mia Ngo", "division": "women_rx", "overall_rank": 61127, "overall_pct": 38.3, "wod1_pct": 50.6, "wod2_pct": 47.2, "wod3_pct": 50.1, "wod1_reps": 188, "wod2_reps": 95, "wod3_reps": 155, "archetype": "Engine", "volatility": 1.8, "age": 19, "wrapped": {"persona": "The Origin Story", "headline": "The Origin Story", "tagline": "Every great athlete has a Chapter 1. This is yours.", "best_workout": "26.1", "best_pct": 50.6, "worst_workout": "26.2", "worst_pct": 47.2, "spread": 3.3, "gym_rank": 15, "gym_total": 52, "award": "Women's Metronome"}, "num_opens": null}, {"name": "Rachelle Aguada", "division": "women_rx", "overall_rank": 62776, "overall_pct": 36.7, "wod1_pct": 9.8, "wod2_pct": 9.9, "wod3_pct": 18.2, "wod1_reps": 126, "wod2_reps": 24, "wod3_reps": 115, "archetype": "Barbell", "volatility": 4.8, "age": 39, "wrapped": {"persona": "The Wolf", "headline": "The Wolf", "tagline": "Part of the pack. Stronger because of it.", "best_workout": "26.3", "best_pct": 18.2, "worst_workout": "26.1", "worst_pct": 9.8, "spread": 8.3, "gym_rank": 16, "gym_total": 52, "award": "Women's Best 35\u201339"}, "height_in": 64, "weight_lb": 185, "num_opens": 1}, {"name": "Mikayla OGrady", "division": "women_rx", "overall_rank": 63517, "overall_pct": 35.9, "wod1_pct": 29.7, "wod2_pct": 96.6, "wod3_pct": 36.9, "wod1_reps": 164, "wod2_reps": 132, "wod3_reps": 140, "archetype": "Gymnast", "volatility": 36.7, "age": 27, "wrapped": {"persona": "The Sniper", "headline": "The Sniper", "tagline": "One shot. One kill. Your 26.2 was elite.", "best_workout": "26.2", "best_pct": 96.6, "worst_workout": "26.1", "worst_pct": 29.7, "spread": 66.9, "gym_rank": 17, "gym_total": 52, "award": null}, "num_opens": null}, {"name": "Marti Duya", "division": "men_rx", "overall_rank": 68347, "overall_pct": 42.0, "wod1_pct": 17.6, "wod2_pct": 38.0, "wod3_pct": 51.6, "wod1_reps": 154, "wod2_reps": 112, "wod3_reps": 158, "archetype": "Barbell", "volatility": 17.1, "age": 33, "wrapped": {"persona": "The Comeback Kid", "headline": "The Comeback Kid", "tagline": "You gained 34 percentile points from Week 1 to Week 3. Peaked when it mattered.", "best_workout": "26.3", "best_pct": 51.6, "worst_workout": "26.1", "worst_pct": 17.6, "spread": 34.0, "gym_rank": 18, "gym_total": 52, "award": null}, "num_opens": 1}, {"name": "Lee Warnest", "division": "men_rx", "overall_rank": 69374, "overall_pct": 41.2, "wod1_pct": 45.6, "wod2_pct": 20.6, "wod3_pct": 36.9, "wod1_reps": 191, "wod2_reps": 88, "wod3_reps": 140, "archetype": "Engine", "volatility": 12.7, "age": 39, "wrapped": {"persona": "The Origin Story", "headline": "The Origin Story", "tagline": "Every great athlete has a Chapter 1. This is yours.", "best_workout": "26.1", "best_pct": 45.6, "worst_workout": "26.2", "worst_pct": 20.6, "spread": 25.0, "gym_rank": 19, "gym_total": 52, "award": "Men's Best 35\u201339"}, "height_in": 70, "weight_lb": 163, "num_opens": 4}, {"name": "Patricia Sorongon", "division": "women_rx", "overall_rank": 76900, "overall_pct": 22.4, "wod1_pct": 6.1, "wod2_pct": 39.2, "wod3_pct": 18.7, "wod1_reps": 106, "wod2_reps": 86, "wod3_reps": 116, "archetype": "Gymnast", "volatility": 16.7, "age": 30, "wrapped": {"persona": "The Slow Burn", "headline": "The Slow Burn", "tagline": "Started quiet. Finished loud.", "best_workout": "26.2", "best_pct": 39.2, "worst_workout": "26.1", "worst_pct": 6.1, "spread": 33.1, "gym_rank": 20, "gym_total": 52, "award": null}, "num_opens": null}, {"name": "Rohan Howson", "division": "men_rx", "overall_rank": 77283, "overall_pct": 34.5, "wod1_pct": 30.9, "wod2_pct": 21.3, "wod3_pct": 31.1, "wod1_reps": 174, "wod2_reps": 88, "wod3_reps": 136, "archetype": "Barbell", "volatility": 5.6, "age": 31, "wrapped": {"persona": "The Origin Story", "headline": "The Origin Story", "tagline": "Every great athlete has a Chapter 1. This is yours.", "best_workout": "26.3", "best_pct": 31.1, "worst_workout": "26.2", "worst_pct": 21.3, "spread": 9.7, "gym_rank": 21, "gym_total": 52, "award": null}, "num_opens": null}, {"name": "Amanda Wright", "division": "women_rx", "overall_rank": 78065, "overall_pct": null, "wod1_pct": 3.5, "wod2_pct": null, "wod3_pct": 16.6, "wod1_reps": 20, "wod2_reps": 0, "wod3_reps": 108, "archetype": "Barbell", "volatility": 8.8, "age": 47, "wrapped": {"persona": "The Wolf", "headline": "The Wolf", "tagline": "Part of the pack. Stronger because of it.", "best_workout": "26.3", "best_pct": 16.6, "worst_workout": "26.2", "worst_pct": 0.0, "spread": 16.6, "gym_rank": 22, "gym_total": 52, "award": null}, "height_in": 59, "weight_lb": 176, "num_opens": 5}, {"name": "Stephanie Nguyen", "division": "women_rx", "overall_rank": 79925, "overall_pct": 19.4, "wod1_pct": 27.4, "wod2_pct": 18.8, "wod3_pct": 19.0, "wod1_reps": 160, "wod2_reps": 68, "wod3_reps": 117, "archetype": "Engine", "volatility": 4.9, "age": 27, "wrapped": {"persona": "The Origin Story", "headline": "The Origin Story", "tagline": "Every great athlete has a Chapter 1. This is yours.", "best_workout": "26.1", "best_pct": 27.4, "worst_workout": "26.2", "worst_pct": 18.8, "spread": 8.6, "gym_rank": 23, "gym_total": 52, "award": null}, "num_opens": null}, {"name": "PROMILA DANGI", "division": "women_rx", "overall_rank": 83765, "overall_pct": 15.5, "wod1_pct": 55.2, "wod2_pct": 97.5, "wod3_pct": 51.4, "wod1_reps": 194, "wod2_reps": 132, "wod3_reps": 156, "archetype": "Gymnast", "volatility": 25.6, "age": 40, "wrapped": {"persona": "The Sniper", "headline": "The Sniper", "tagline": "One shot. One kill. Your 26.2 was elite.", "best_workout": "26.2", "best_pct": 97.5, "worst_workout": "26.3", "worst_pct": 51.4, "spread": 46.1, "gym_rank": 24, "gym_total": 52, "award": "Women's Best 40\u201344"}, "num_opens": null}, {"name": "Phillip Moxey", "division": "men_rx", "overall_rank": 85210, "overall_pct": 27.7, "wod1_pct": 7.5, "wod2_pct": 23.3, "wod3_pct": 32.9, "wod1_reps": 127, "wod2_reps": 89, "wod3_reps": 137, "archetype": "Barbell", "volatility": 12.8, "age": 33, "wrapped": {"persona": "The Comeback Kid", "headline": "The Comeback Kid", "tagline": "You gained 25 percentile points from Week 1 to Week 3. Peaked when it mattered.", "best_workout": "26.3", "best_pct": 32.9, "worst_workout": "26.1", "worst_pct": 7.5, "spread": 25.4, "gym_rank": 25, "gym_total": 52, "award": null}, "num_opens": null}, {"name": "Rachel Dempsey", "division": "women_rx", "overall_rank": 85449, "overall_pct": 13.8, "wod1_pct": 9.8, "wod2_pct": 15.3, "wod3_pct": 12.6, "wod1_reps": 126, "wod2_reps": 68, "wod3_reps": 78, "archetype": "Gymnast", "volatility": 2.7, "age": 35, "wrapped": {"persona": "The Wolf", "headline": "The Wolf", "tagline": "Part of the pack. Stronger because of it.", "best_workout": "26.2", "best_pct": 15.3, "worst_workout": "26.1", "worst_pct": 9.8, "spread": 5.4, "gym_rank": 26, "gym_total": 52, "award": null}, "height_in": 64, "num_opens": 1}, {"name": "Emma Chavez", "division": "women_rx", "overall_rank": 88619, "overall_pct": 10.6, "wod1_pct": 31.7, "wod2_pct": 98.4, "wod3_pct": 32.5, "wod1_reps": 166, "wod2_reps": 132, "wod3_reps": 136, "archetype": "Gymnast", "volatility": 38.3, "age": 42, "wrapped": {"persona": "The Sniper", "headline": "The Sniper", "tagline": "One shot. One kill. Your 26.2 was elite.", "best_workout": "26.2", "best_pct": 98.4, "worst_workout": "26.1", "worst_pct": 31.7, "spread": 66.7, "gym_rank": 27, "gym_total": 52, "award": "Women's Best on 26.2"}, "num_opens": null}, {"name": "Jayde Campion", "division": "women_rx", "overall_rank": 89743, "overall_pct": 9.4, "wod1_pct": 26.6, "wod2_pct": 95.9, "wod3_pct": 35.2, "wod1_reps": 159, "wod2_reps": 132, "wod3_reps": 138, "archetype": "Gymnast", "volatility": 37.8, "age": 29, "wrapped": {"persona": "The Sniper", "headline": "The Sniper", "tagline": "One shot. One kill. Your 26.2 was elite.", "best_workout": "26.2", "best_pct": 95.9, "worst_workout": "26.1", "worst_pct": 26.6, "spread": 69.3, "gym_rank": 28, "gym_total": 52, "award": null}, "num_opens": null}, {"name": "Stephen Chivers", "division": "men_rx", "overall_rank": 89767, "overall_pct": 23.9, "wod1_pct": 20.1, "wod2_pct": 28.2, "wod3_pct": 32.2, "wod1_reps": 158, "wod2_reps": 91, "wod3_reps": 137, "archetype": "Barbell", "volatility": 6.2, "age": 35, "wrapped": {"persona": "The Slow Burn", "headline": "The Slow Burn", "tagline": "Started quiet. Finished loud.", "best_workout": "26.3", "best_pct": 32.2, "worst_workout": "26.1", "worst_pct": 20.1, "spread": 12.1, "gym_rank": 29, "gym_total": 52, "award": null}, "num_opens": null}, {"name": "Jasmine Sekhon", "division": "women_rx", "overall_rank": 90134, "overall_pct": 9.0, "wod1_pct": 26.0, "wod2_pct": 15.8, "wod3_pct": 17.7, "wod1_reps": 159, "wod2_reps": 68, "wod3_reps": 113, "archetype": "Engine", "volatility": 5.4, "age": 30, "wrapped": {"persona": "The Wolf", "headline": "The Wolf", "tagline": "Part of the pack. Stronger because of it.", "best_workout": "26.1", "best_pct": 26.0, "worst_workout": "26.2", "worst_pct": 15.8, "spread": 10.2, "gym_rank": 30, "gym_total": 52, "award": null}, "height_in": 60, "num_opens": null}, {"name": "Gabrielle Ross", "division": "women_rx", "overall_rank": 90443, "overall_pct": 8.7, "wod1_pct": 44.9, "wod2_pct": 94.4, "wod3_pct": 86.5, "wod1_reps": 182, "wod2_reps": 132, "wod3_reps": 201, "archetype": "Gymnast", "volatility": 26.6, "age": 32, "wrapped": {"persona": "The Comeback Kid", "headline": "The Comeback Kid", "tagline": "You gained 42 percentile points from Week 1 to Week 3. Peaked when it mattered.", "best_workout": "26.2", "best_pct": 94.4, "worst_workout": "26.1", "worst_pct": 44.9, "spread": 49.5, "gym_rank": 31, "gym_total": 52, "award": "Women's Best on 26.3"}, "weight_lb": 168, "num_opens": 5}, {"name": "Jami Carter", "division": "women_rx", "overall_rank": 90484, "overall_pct": 8.7, "wod1_pct": 41.1, "wod2_pct": 88.7, "wod3_pct": 22.2, "wod1_reps": 177, "wod2_reps": 126, "wod3_reps": 125, "archetype": "Gymnast", "volatility": 34.2, "age": 25, "wrapped": {"persona": "The Origin Story", "headline": "The Origin Story", "tagline": "Every great athlete has a Chapter 1. This is yours.", "best_workout": "26.2", "best_pct": 88.7, "worst_workout": "26.3", "worst_pct": 22.2, "spread": 66.4, "gym_rank": 32, "gym_total": 52, "award": null}, "num_opens": null}, {"name": "Marnie Pearson", "division": "women_rx", "overall_rank": 90661, "overall_pct": 8.5, "wod1_pct": 19.9, "wod2_pct": 18.9, "wod3_pct": 15.7, "wod1_reps": 150, "wod2_reps": 68, "wod3_reps": 107, "archetype": "Engine", "volatility": 2.2, "age": 16, "wrapped": {"persona": "The Wolf", "headline": "The Wolf", "tagline": "Part of the pack. Stronger because of it.", "best_workout": "26.1", "best_pct": 19.9, "worst_workout": "26.3", "worst_pct": 15.7, "spread": 4.1, "gym_rank": 33, "gym_total": 52, "award": null}, "num_opens": null}, {"name": "John Michael Encinares", "division": "men_rx", "overall_rank": 91339, "overall_pct": 22.5, "wod1_pct": 28.6, "wod2_pct": 90.6, "wod3_pct": 65.0, "wod1_reps": 170, "wod2_reps": 132, "wod3_reps": 174, "archetype": "Gymnast", "volatility": 31.2, "age": 40, "wrapped": {"persona": "The Comeback Kid", "headline": "The Comeback Kid", "tagline": "You gained 36 percentile points from Week 1 to Week 3. Peaked when it mattered.", "best_workout": "26.2", "best_pct": 90.6, "worst_workout": "26.1", "worst_pct": 28.6, "spread": 62.0, "gym_rank": 34, "gym_total": 52, "award": "Men's Best on 26.2"}, "num_opens": null}, {"name": "Joanna Santoro", "division": "women_rx", "overall_rank": 91665, "overall_pct": 7.5, "wod1_pct": 24.1, "wod2_pct": 96.8, "wod3_pct": 18.8, "wod1_reps": 156, "wod2_reps": 132, "wod3_reps": 116, "archetype": "Gymnast", "volatility": 43.6, "age": 40, "wrapped": {"persona": "The Sniper", "headline": "The Sniper", "tagline": "One shot. One kill. Your 26.2 was elite.", "best_workout": "26.2", "best_pct": 96.8, "worst_workout": "26.3", "worst_pct": 18.8, "spread": 78.1, "gym_rank": 35, "gym_total": 52, "award": "Women's Wildcard"}, "num_opens": 1}, {"name": "Alicia Malatesta", "division": "women_rx", "overall_rank": 91700, "overall_pct": 7.5, "wod1_pct": 22.0, "wod2_pct": 91.3, "wod3_pct": 31.4, "wod1_reps": 153, "wod2_reps": 132, "wod3_reps": 136, "archetype": "Gymnast", "volatility": 37.6, "age": 23, "wrapped": {"persona": "The Sniper", "headline": "The Sniper", "tagline": "One shot. One kill. Your 26.2 was elite.", "best_workout": "26.2", "best_pct": 91.3, "worst_workout": "26.1", "worst_pct": 22.0, "spread": 69.3, "gym_rank": 36, "gym_total": 52, "award": null}, "num_opens": null}, {"name": "Yashodha Maddumage", "division": "women_rx", "overall_rank": 92165, "overall_pct": 7.0, "wod1_pct": 16.7, "wod2_pct": 94.4, "wod3_pct": 28.5, "wod1_reps": 144, "wod2_reps": 132, "wod3_reps": 133, "archetype": "Gymnast", "volatility": 41.9, "age": 32, "wrapped": {"persona": "The Sniper", "headline": "The Sniper", "tagline": "One shot. One kill. Your 26.2 was elite.", "best_workout": "26.2", "best_pct": 94.4, "worst_workout": "26.1", "worst_pct": 16.7, "spread": 77.8, "gym_rank": 37, "gym_total": 52, "award": null}, "num_opens": null}, {"name": "Ankur Patel", "division": "men_rx", "overall_rank": 92290, "overall_pct": 21.7, "wod1_pct": 23.5, "wod2_pct": 59.1, "wod3_pct": 19.3, "wod1_reps": 164, "wod2_reps": 113, "wod3_reps": 119, "archetype": "Gymnast", "volatility": 21.8, "age": 41, "wrapped": {"persona": "The Ageless", "headline": "The Ageless", "tagline": "Age 41. Still making 25-year-olds nervous.", "best_workout": "26.2", "best_pct": 59.1, "worst_workout": "26.3", "worst_pct": 19.3, "spread": 39.8, "gym_rank": 38, "gym_total": 52, "award": "Men's Best 40\u201344"}, "num_opens": 2}, {"name": "Kerry Ceradini", "division": "women_rx", "overall_rank": 94173, "overall_pct": 5.0, "wod1_pct": 18.5, "wod2_pct": 95.0, "wod3_pct": 43.3, "wod1_reps": 147, "wod2_reps": 132, "wod3_reps": 146, "archetype": "Gymnast", "volatility": 39.1, "age": 50, "wrapped": {"persona": "The Comeback Kid", "headline": "The Comeback Kid", "tagline": "You gained 25 percentile points from Week 1 to Week 3. Peaked when it mattered.", "best_workout": "26.2", "best_pct": 95.0, "worst_workout": "26.1", "worst_pct": 18.5, "spread": 76.6, "gym_rank": 39, "gym_total": 52, "award": "Women's Closer"}, "num_opens": null}, {"name": "Chan Bok", "division": "men_rx", "overall_rank": 95181, "overall_pct": 19.3, "wod1_pct": 9.2, "wod2_pct": 10.6, "wod3_pct": 18.5, "wod1_reps": 134, "wod2_reps": 47, "wod3_reps": 116, "archetype": "Barbell", "volatility": 5.0, "age": 43, "wrapped": {"persona": "The Wolf", "headline": "The Wolf", "tagline": "Part of the pack. Stronger because of it.", "best_workout": "26.3", "best_pct": 18.5, "worst_workout": "26.1", "worst_pct": 9.2, "spread": 9.3, "gym_rank": 40, "gym_total": 52, "award": null}, "height_in": 70, "weight_lb": 247, "num_opens": 3}, {"name": "Ebony Rankine", "division": "women_rx", "overall_rank": 96621, "overall_pct": null, "wod1_pct": 15.2, "wod2_pct": null, "wod3_pct": null, "wod1_reps": 142, "wod2_reps": 0, "wod3_reps": 0, "archetype": "Engine", "volatility": 8.8, "age": 27, "wrapped": {"persona": "The Wolf", "headline": "The Wolf", "tagline": "Part of the pack. Stronger because of it.", "best_workout": "26.1", "best_pct": 15.2, "worst_workout": "26.2", "worst_pct": 0.0, "spread": 15.2, "gym_rank": 41, "gym_total": 52, "award": null}, "num_opens": 2}, {"name": "Anthea Obst", "division": "women_rx", "overall_rank": 96913, "overall_pct": null, "wod1_pct": 35.2, "wod2_pct": 97.0, "wod3_pct": null, "wod1_reps": 170, "wod2_reps": 132, "wod3_reps": 0, "archetype": "Gymnast", "volatility": 49.1, "age": 50, "wrapped": {"persona": "The Sniper", "headline": "The Sniper", "tagline": "One shot. One kill. Your 26.2 was elite.", "best_workout": "26.2", "best_pct": 97.0, "worst_workout": "26.3", "worst_pct": 0.0, "spread": 97.0, "gym_rank": 42, "gym_total": 52, "award": null}, "height_in": 68, "weight_lb": 201, "num_opens": 1}, {"name": "Anthony Santoro", "division": "men_rx", "overall_rank": 98284, "overall_pct": 16.7, "wod1_pct": 11.5, "wod2_pct": 37.9, "wod3_pct": 17.7, "wod1_reps": 142, "wod2_reps": 112, "wod3_reps": 113, "archetype": "Gymnast", "volatility": 13.8, "age": 41, "wrapped": {"persona": "The Ageless", "headline": "The Ageless", "tagline": "Age 41. Still making 25-year-olds nervous.", "best_workout": "26.2", "best_pct": 37.9, "worst_workout": "26.1", "worst_pct": 11.5, "spread": 26.3, "gym_rank": 43, "gym_total": 52, "award": null}, "num_opens": null}, {"name": "Alan Robson", "division": "men_rx", "overall_rank": 106288, "overall_pct": 9.9, "wod1_pct": 3.6, "wod2_pct": 99.4, "wod3_pct": 14.3, "wod1_reps": 68, "wod2_reps": 132, "wod3_reps": 91, "archetype": "Gymnast", "volatility": 52.5, "age": 36, "wrapped": {"persona": "The Sniper", "headline": "The Sniper", "tagline": "One shot. One kill. Your 26.2 was elite.", "best_workout": "26.2", "best_pct": 99.4, "worst_workout": "26.1", "worst_pct": 3.6, "spread": 95.8, "gym_rank": 44, "gym_total": 52, "award": "Men's Wildcard"}, "height_in": 67, "weight_lb": 203, "num_opens": 1}, {"name": "Dalvir Singh Sohi", "division": "men_rx", "overall_rank": 107964, "overall_pct": 8.4, "wod1_pct": 14.5, "wod2_pct": 48.1, "wod3_pct": 63.6, "wod1_reps": 148, "wod2_reps": 112, "wod3_reps": 172, "archetype": "Barbell", "volatility": 25.1, "age": 42, "wrapped": {"persona": "The Comeback Kid", "headline": "The Comeback Kid", "tagline": "You gained 49 percentile points from Week 1 to Week 3. Peaked when it mattered.", "best_workout": "26.3", "best_pct": 63.6, "worst_workout": "26.1", "worst_pct": 14.5, "spread": 49.1, "gym_rank": 45, "gym_total": 52, "award": "Men's Closer"}, "num_opens": 2}, {"name": "Brad Hajek", "division": "men_rx", "overall_rank": 109378, "overall_pct": 7.3, "wod1_pct": 51.7, "wod2_pct": 14.0, "wod3_pct": 46.8, "wod1_reps": 199, "wod2_reps": 70, "wod3_reps": 152, "archetype": "Engine", "volatility": 20.5, "age": 49, "wrapped": {"persona": "The Ageless", "headline": "The Ageless", "tagline": "Age 49. Still making 25-year-olds nervous.", "best_workout": "26.1", "best_pct": 51.7, "worst_workout": "26.2", "worst_pct": 14.0, "spread": 37.7, "gym_rank": 46, "gym_total": 52, "award": null}, "height_in": 72, "weight_lb": 234, "num_opens": null}, {"name": "Allan Bartlett", "division": "men_rx", "overall_rank": 109593, "overall_pct": 7.1, "wod1_pct": 21.7, "wod2_pct": 10.9, "wod3_pct": 14.4, "wod1_reps": 161, "wod2_reps": 48, "wod3_reps": 92, "archetype": "Engine", "volatility": 5.5, "age": 51, "wrapped": {"persona": "The Wolf", "headline": "The Wolf", "tagline": "Part of the pack. Stronger because of it.", "best_workout": "26.1", "best_pct": 21.7, "worst_workout": "26.2", "worst_pct": 10.9, "spread": 10.8, "gym_rank": 47, "gym_total": 52, "award": null}, "height_in": 71, "weight_lb": 265, "num_opens": 2}, {"name": "Dylan Kempster", "division": "men_rx", "overall_rank": 110522, "overall_pct": 6.3, "wod1_pct": 10.6, "wod2_pct": 12.5, "wod3_pct": 14.3, "wod1_reps": 138, "wod2_reps": 68, "wod3_reps": 90, "archetype": "Barbell", "volatility": 1.8, "age": 41, "wrapped": {"persona": "The Wolf", "headline": "The Wolf", "tagline": "Part of the pack. Stronger because of it.", "best_workout": "26.3", "best_pct": 14.3, "worst_workout": "26.1", "worst_pct": 10.6, "spread": 3.6, "gym_rank": 48, "gym_total": 52, "award": "Men's Metronome"}, "height_in": 74, "num_opens": 1}, {"name": "Naveen Munnangi", "division": "men_rx", "overall_rank": 112408, "overall_pct": 4.7, "wod1_pct": 19.7, "wod2_pct": 19.2, "wod3_pct": 29.0, "wod1_reps": 158, "wod2_reps": 85, "wod3_reps": 135, "archetype": "Barbell", "volatility": 5.5, "age": 33, "wrapped": {"persona": "The Origin Story", "headline": "The Origin Story", "tagline": "Every great athlete has a Chapter 1. This is yours.", "best_workout": "26.3", "best_pct": 29.0, "worst_workout": "26.2", "worst_pct": 19.2, "spread": 9.7, "gym_rank": 49, "gym_total": 52, "award": null}, "num_opens": null}, {"name": "Matt Hendrickx", "division": "men_rx", "overall_rank": 112813, "overall_pct": null, "wod1_pct": 3.6, "wod2_pct": null, "wod3_pct": null, "wod1_reps": 68, "wod2_reps": 0, "wod3_reps": 0, "archetype": "Engine", "volatility": 2.1, "age": 35, "wrapped": {"persona": "The Wolf", "headline": "The Wolf", "tagline": "Part of the pack. Stronger because of it.", "best_workout": "26.1", "best_pct": 3.6, "worst_workout": "26.2", "worst_pct": 0.0, "spread": 3.6, "gym_rank": 50, "gym_total": 52, "award": null}, "height_in": 67, "weight_lb": 163, "num_opens": 4}, {"name": "Corey Clark", "division": "men_rx", "overall_rank": 114084, "overall_pct": 3.3, "wod1_pct": 18.7, "wod2_pct": 12.6, "wod3_pct": 22.6, "wod1_reps": 156, "wod2_reps": 68, "wod3_reps": 127, "archetype": "Barbell", "volatility": 5.0, "age": 33, "wrapped": {"persona": "The Wolf", "headline": "The Wolf", "tagline": "Part of the pack. Stronger because of it.", "best_workout": "26.3", "best_pct": 22.6, "worst_workout": "26.2", "worst_pct": 12.6, "spread": 10.0, "gym_rank": 51, "gym_total": 52, "award": null}, "num_opens": null}, {"name": "Ravi Vetrivelu", "division": "men_rx", "overall_rank": 116102, "overall_pct": null, "wod1_pct": null, "wod2_pct": 11.8, "wod3_pct": 21.4, "wod1_reps": 0, "wod2_reps": 68, "wod3_reps": 124, "archetype": "Barbell", "volatility": 10.7, "age": 51, "wrapped": {"persona": "The Wolf", "headline": "The Wolf", "tagline": "Part of the pack. Stronger because of it.", "best_workout": "26.3", "best_pct": 21.4, "worst_workout": "26.1", "worst_pct": 0.0, "spread": 21.4, "gym_rank": 52, "gym_total": 52, "award": null}, "num_opens": null}]}